Workbook

Sheet All_India_Index_Upto_April23 (1
AE1: Broader Categories
A2: Sector | B2: Year | C2: Month | D2: Cereals and products | E2: Meat and fish | F2: Egg | G2: Milk and products | H2: Oils and fats | I2: Fruits | J2: Vegetables | K2: Pulses and products | L2: Sugar and Confectionery | M2: Spices | N2: Non-alcoholic beverages | O2: Prepared meals, snacks, sweets etc. | P2: Food and beverages | Q2: Pan, tobacco and intoxicants | R2: Clothing | S2: Footwear | T2: Clothing and footwear | U2: Housing | V2: Fuel and light | W2: Household goods and services | X2: Health | Y2: Transport and communication | Z2: Recreation and amusement | AA2: Education | AB2: Personal care and effects | AC2: Miscellaneous | AD2: General index | AE2: Food | AF2: Energy | AG2: Transportation | AH2: Education | AI2: Others
A3: Rural | B3: 2013 | C3: January | D3: 107.5 | E3: 106.3 | F3: 108.1 | G3: 104.9 | H3: 106.1 | I3: 103.9 | J3: 101.9 | K3: 106.1 | L3: 106.8 | M3: 103.1 | N3: 104.8 | O3: 106.7 | P3: 105.5 | Q3: 105.1 | R3: 106.5 | S3: 105.8 | T3: 106.4 | U3: 100.3 | V3: 105.5 | W3: 104.8 | X3: 104 | Y3: 103.3 | Z3: 103.4 | AA3: 103.8 | AB3: 104.7 | AC3: 104 | AD3: 105.1 | AE3: =SUM(D3:P3) -> 1371.7 | AF3: =SUM(V3) -> 105.5 | AG3: =SUM(Y3) -> 103.3 | AH3: =SUM(AA3) -> 103.8 | AI3: =SUM(Q3:U3,W3:X3,Z3,AB3:AC3) -> 1045
A4: Urban | B4: 2013 | C4: January | D4: 110.5 | E4: 109.1 | F4: 113 | G4: 103.6 | H4: 103.4 | I4: 102.3 | J4: 102.9 | K4: 105.8 | L4: 105.1 | M4: 101.8 | N4: 105.1 | O4: 107.9 | P4: 105.9 | Q4: 105.2 | R4: 105.9 | S4: 105 | T4: 105.8 | U4: 100.3 | V4: 105.4 | W4: 104.8 | X4: 104.1 | Y4: 103.2 | Z4: 102.9 | AA4: 103.5 | AB4: 104.3 | AC4: 103.7 | AD4: 104 | AE4: =SUM(D4:P4) -> 1376.4 | AF4: =SUM(V4) -> 105.4 | AG4: =SUM(Y4) -> 103.2 | AH4: =SUM(AA4) -> 103.5 | AI4: =SUM(Q4:U4,W4:X4,Z4,AB4:AC4) -> 1042
A5: Rural+Urban | B5: 2013 | C5: January | D5: 108.4 | E5: 107.3 | F5: 110 | G5: 104.4 | H5: 105.1 | I5: 103.2 | J5: 102.2 | K5: 106 | L5: 106.2 | M5: 102.7 | N5: 104.9 | O5: 107.3 | P5: 105.6 | Q5: 105.1 | R5: 106.3 | S5: 105.5 | T5: 106.2 | U5: 100.3 | V5: 105.5 | W5: 104.8 | X5: 104 | Y5: 103.2 | Z5: 103.1 | AA5: 103.6 | AB5: 104.5 | AC5: 103.9 | AD5: 104.6 | AE5: =SUM(D5:P5) -> 1373.3 | AF5: =SUM(V5) -> 105.5 | AG5: =SUM(Y5) -> 103.2 | AH5: =SUM(AA5) -> 103.6 | AI5: =SUM(Q5:U5,W5:X5,Z5,AB5:AC5) -> 1043.7
A6: Rural | B6: 2013 | C6: February | D6: 109.2 | E6: 108.7 | F6: 110.2 | G6: 105.4 | H6: 106.7 | I6: 104 | J6: 102.4 | K6: 105.9 | L6: 105.7 | M6: 103.1 | N6: 105.1 | O6: 107.7 | P6: 106.3 | Q6: 105.6 | R6: 107.1 | S6: 106.3 | T6: 107 | U6: 100.4 | V6: 106.2 | W6: 105.2 | X6: 104.4 | Y6: 103.9 | Z6: 104 | AA6: 104.1 | AB6: 104.6 | AC6: 104.4 | AD6: 105.8 | AE6: =SUM(D6:P6) -> 1380.4 | AF6: =SUM(V6) -> 106.2 | AG6: =SUM(Y6) -> 103.9 | AH6: =SUM(AA6) -> 104.1 | AI6: =SUM(Q6:U6,W6:X6,Z6,AB6:AC6) -> 1049
A7: Urban | B7: 2013 | C7: February | D7: 112.9 | E7: 112.9 | F7: 116.9 | G7: 104 | H7: 103.5 | I7: 103.1 | J7: 104.9 | K7: 104.1 | L7: 103.8 | M7: 102.3 | N7: 106 | O7: 109 | P7: 107.2 | Q7: 106 | R7: 106.6 | S7: 105.5 | T7: 106.4 | U7: 100.4 | V7: 105.7 | W7: 105.2 | X7: 104.7 | Y7: 104.4 | Z7: 103.3 | AA7: 103.7 | AB7: 104.3 | AC7: 104.3 | AD7: 104.7 | AE7: =SUM(D7:P7) -> 1390.6 | AF7: =SUM(V7) -> 105.7 | AG7: =SUM(Y7) -> 104.4 | AH7: =SUM(AA7) -> 103.7 | AI7: =SUM(Q7:U7,W7:X7,Z7,AB7:AC7) -> 1046.7
A8: Rural+Urban | B8: 2013 | C8: February | D8: 110.4 | E8: 110.2 | F8: 112.8 | G8: 104.9 | H8: 105.5 | I8: 103.6 | J8: 103.2 | K8: 105.3 | L8: 105.1 | M8: 102.8 | N8: 105.5 | O8: 108.3 | P8: 106.6 | Q8: 105.7 | R8: 106.9 | S8: 106 | T8: 106.8 | U8: 100.4 | V8: 106 | W8: 105.2 | X8: 104.5 | Y8: 104.2 | Z8: 103.6 | AA8: 103.9 | AB8: 104.5 | AC8: 104.4 | AD8: 105.3 | AE8: =SUM(D8:P8) -> 1384.2 | AF8: =SUM(V8) -> 106 | AG8: =SUM(Y8) -> 104.2 | AH8: =SUM(AA8) -> 103.9 | AI8: =SUM(Q8:U8,W8:X8,Z8,AB8:AC8) -> 1048
A9: Rural | B9: 2013 | C9: March | D9: 110.2 | E9: 108.8 | F9: 109.9 | G9: 105.6 | H9: 106.2 | I9: 105.7 | J9: 101.4 | K9: 105.7 | L9: 105 | M9: 103.3 | N9: 105.6 | O9: 108.2 | P9: 106.6 | Q9: 106.5 | R9: 107.6 | S9: 106.8 | T9: 107.5 | U9: 100.4 | V9: 106.1 | W9: 105.6 | X9: 104.7 | Y9: 104.6 | Z9: 104 | AA9: 104.3 | AB9: 104.3 | AC9: 104.6 | AD9: 106 | AE9: =SUM(D9:P9) -> 1382.2 | AF9: =SUM(V9) -> 106.1 | AG9: =SUM(Y9) -> 104.6 | AH9: =SUM(AA9) -> 104.3 | AI9: =SUM(Q9:U9,W9:X9,Z9,AB9:AC9) -> 1052
A10: Urban | B10: 2013 | C10: March | D10: 113.9 | E10: 111.4 | F10: 113.2 | G10: 104.3 | H10: 102.7 | I10: 104.9 | J10: 103.8 | K10: 103.5 | L10: 102.6 | M10: 102.4 | N10: 107 | O10: 109.8 | P10: 107.3 | Q10: 106.8 | R10: 107.2 | S10: 106 | T10: 107 | U10: 100.4 | V10: 106 | W10: 105.7 | X10: 105.2 | Y10: 105.5 | Z10: 103.5 | AA10: 103.8 | AB10: 104.2 | AC10: 104.9 | AD10: 105 | AE10: =SUM(D10:P10) -> 1386.8 | AF10: =SUM(V10) -> 106 | AG10: =SUM(Y10) -> 105.5 | AH10: =SUM(AA10) -> 103.8 | AI10: =SUM(Q10:U10,W10:X10,Z10,AB10:AC10) -> 1050.9
A11: Rural+Urban | B11: 2013 | C11: March | D11: 111.4 | E11: 109.7 | F11: 111.2 | G11: 105.1 | H11: 104.9 | I11: 105.3 | J11: 102.2 | K11: 105 | L11: 104.2 | M11: 103 | N11: 106.2 | O11: 108.9 | P11: 106.9 | Q11: 106.6 | R11: 107.4 | S11: 106.5 | T11: 107.3 | U11: 100.4 | V11: 106.1 | W11: 105.6 | X11: 104.9 | Y11: 105.1 | Z11: 103.7 | AA11: 104 | AB11: 104.3 | AC11: 104.7 | AD11: 105.5 | AE11: =SUM(D11:P11) -> 1384 | AF11: =SUM(V11) -> 106.1 | AG11: =SUM(Y11) -> 105.1 | AH11: =SUM(AA11) -> 104 | AI11: =SUM(Q11:U11,W11:X11,Z11,AB11:AC11) -> 1051.4
A12: Rural | B12: 2013 | C12: April | D12: 110.2 | E12: 109.5 | F12: 106.9 | G12: 106.3 | H12: 105.7 | I12: 108.3 | J12: 103.4 | K12: 105.7 | L12: 104.2 | M12: 103.2 | N12: 106.5 | O12: 108.8 | P12: 107.1 | Q12: 107.1 | R12: 108.1 | S12: 107.4 | T12: 108 | U12: 100.5 | V12: 106.5 | W12: 106.1 | X12: 105.1 | Y12: 104.4 | Z12: 104.5 | AA12: 104.8 | AB12: 102.7 | AC12: 104.6 | AD12: 106.4 | AE12: =SUM(D12:P12) -> 1385.8 | AF12: =SUM(V12) -> 106.5 | AG12: =SUM(Y12) -> 104.4 | AH12: =SUM(AA12) -> 104.8 | AI12: =SUM(Q12:U12,W12:X12,Z12,AB12:AC12) -> 1054.1
A13: Urban | B13: 2013 | C13: April | D13: 114.6 | E13: 113.4 | F13: 106 | G13: 104.7 | H13: 102.1 | I13: 109.5 | J13: 109.7 | K13: 104.6 | L13: 102 | M13: 103.5 | N13: 108.2 | O13: 110.6 | P13: 108.8 | Q13: 108.5 | R13: 107.9 | S13: 106.4 | T13: 107.7 | U13: 100.5 | V13: 106.4 | W13: 106.5 | X13: 105.7 | Y13: 105 | Z13: 104 | AA13: 105.2 | AB13: 103.2 | AC13: 105.1 | AD13: 105.7 | AE13: =SUM(D13:P13) -> 1397.7 | AF13: =SUM(V13) -> 106.4 | AG13: =SUM(Y13) -> 105 | AH13: =SUM(AA13) -> 105.2 | AI13: =SUM(Q13:U13,W13:X13,Z13,AB13:AC13) -> 1055.5
A14: Rural+Urban | B14: 2013 | C14: April | D14: 111.6 | E14: 110.9 | F14: 106.6 | G14: 105.7 | H14: 104.4 | I14: 108.9 | J14: 105.5 | K14: 105.3 | L14: 103.5 | M14: 103.3 | N14: 107.2 | O14: 109.6 | P14: 107.7 | Q14: 107.5 | R14: 108 | S14: 107 | T14: 107.9 | U14: 100.5 | V14: 106.5 | W14: 106.3 | X14: 105.3 | Y14: 104.7 | Z14: 104.2 | AA14: 105 | AB14: 102.9 | AC14: 104.8 | AD14: 106.1 | AE14: =SUM(D14:P14) -> 1390.2 | AF14: =SUM(V14) -> 106.5 | AG14: =SUM(Y14) -> 104.7 | AH14: =SUM(AA14) -> 105 | AI14: =SUM(Q14:U14,W14:X14,Z14,AB14:AC14) -> 1054.4
... A374: Rural+Urban | B374: 2023 | C374: May | D374: 173.7 | E374: 214.3 | F374: 173.2 | G374: 179.5 | H374: 170 | I374: 172.2 | J374: 161 | K374: 175.6 | L374: 122.7 | M374: 218 | N374: 173.4 | O374: 194.2 | P374: 179.1 | Q374: 201 | R374: 187.3 | S374: 179.7 | T374: 186.2 | U374: 175.6 | V374: 182.8 | W374: 175.2 | X374: 185.7 | Y374: 164.8 | Z374: 171.2 | AA374: 177.1 | AB374: 185.2 | AC374: 175.7 | AD374: 179.1 | AE374: =SUM(D374:P374) -> 2306.9 | AF374: =SUM(V374) -> 182.8 | AG374: =SUM(Y374) -> 164.8 | AH374: =SUM(AA374) -> 177.1 | AI374: =SUM(Q374:U374,W374:X374,Z374,AB374:AC374) -> 1822.8

Sheet Sheet4
A1: Sector | B1: Rural+Urban
A3: Row Labels | B3: Average of General index
A4: 2013 | B4: 110.03333
A5: 2014 | B5: 117.35
A6: 2015 | B6: 123.10833
A7: 2016 | B7: 129.2
A8: 2017 | B8: 133.5
A9: 2018 | B9: 138.775
A10: 2019 | B10: 144.18182
A11: 2020 | B11: 152.58333
A12: 2021 | B12: 161.45833
A13: 2022 | B13: 172.15
A14: 2023 | B14: 177.62
A15: Grand Total | B15: 139.77419
A17: Year | B17: CPI | C17: % YOY
A18: 2013 | B18: 1446.3917 | C18: 0
A19: 2014 | B19: 1542.0833 | C19: =(B19-B18)/B18*100 -> 6.615889
A20: 2015 | B20: 1624.425 | C20: =(B20-B19)/B19*100 -> 5.3396379
A21: 2016 | B21: 1735.8083 | C21: =(B21-B20)/B20*100 -> 6.8567852
A22: 2017 | B22: 1753.9417 | C22: =(B22-B21)/B21*100 -> 1.0446622
A23: 2018 | B23: 1772.9583 | C23: =(B23-B22)/B22*100 -> 1.0842246
A24: 2019 | B24: 1833.0636 | C24: =(B24-B23)/B23*100 -> 3.3901137
A25: 2020 | B25: 1986.2583 | C25: =(B25-B24)/B24*100 -> 8.3573038
A26: 2021 | B26: 2120.0333 | C26: =(B26-B25)/B25*100 -> 6.7350252
A27: 2022 | B27: 2243.2167 | C27: =(B27-B26)/B26*100 -> 5.8104432
A28: 2023 | B28: 2289.5 | C28: =(B28-B27)/B27*100 -> 2.0632574
A29: Grand Total | B29: 1825.1016
A32: Year | B32: CPI | C32: % YOY
A33: 2013 | B33: 108.63333 | C33: 0
A34: 2014 | B34: 113.61667 | C34: =(B34-B33)/B33*100 -> 4.5872967
A35: 2015 | B35: 119.64167 | C35: =(B35-B34)/B34*100 -> 5.3029192
A36: 2016 | B36: 123.625 | C36: =(B36-B35)/B35*100 -> 3.3293864
A37: 2017 | B37: 130.50833 | C37: =(B37-B36)/B36*100 -> 5.5679137
A38: 2018 | B38: 139.775 | C38: =(B38-B37)/B37*100 -> 7.1004406
A39: 2019 | B39: 140.24545 | C39: =(B39-B38)/B38*100 -> 0.33657989
A40: 2020 | B40: 144.15833 | C40: =(B40-B39)/B39*100 -> 2.7900218
A41: 2021 | B41: 159.05833 | C41: =(B41-B40)/B40*100 -> 10.335858
A42: 2022 | B42: 175.13333 | C42: =(B42-B41)/B41*100 -> 10.106355
A43: 2023 | B43: 182.1 | C43: =(B43-B42)/B42*100 -> 3.9779216
A44: Grand Total | B44: 137.28226
A46: Row Labels | B46: Average of Transportation
A47: 2013 | B47: 106.675 | C47: 0
A48: 2014 | B48: 111.50833 | C48: =(B48-B47)/B47*100 -> 4.530896
A49: 2015 | B49: 111.09167 | C49: =(B49-B48)/B48*100 -> -0.37366415
A50: 2016 | B50: 113.39167 | C50: =(B50-B49)/B49*100 -> 2.0703623
A51: 2017 | B51: 117.33333 | C51: =(B51-B50)/B50*100 -> 3.476152
A52: 2018 | B52: 123.125 | C52: =(B52-B51)/B51*100 -> 4.9360795
A53: 2019 | B53: 125.59091 | C53: =(B53-B52)/B52*100 -> 2.0027688
A54: 2020 | B54: 135.05833 | C54: =(B54-B53)/B53*100 -> 7.5383038
A55: 2021 | B55: 150.55833 | C55: =(B55-B54)/B54*100 -> 11.476522
A56: 2022 | B56: 161.09167 | C56: =(B56-B55)/B55*100 -> 6.9961809
A57: 2023 | B57: 164.26 | C57: =(B57-B56)/B56*100 -> 1.9667891
A58: Grand Total | B58: 127.10323
A63: Row Labels | B63: Average of General index
A64: 2013 | B64: 110.03333 | C64: 0
A65: 2014 | B65: 117.35 | C65: =(B65-B64)/B64 -> 0.066495002
A66: 2015 | B66: 123.10833 | C66: =(B66-B65)/B65 -> 0.049069734
A67: 2016 | B67: 129.2 | C67: =(B67-B66)/B66 -> 0.049482163
A68: 2017 | B68: 133.5 | C68: =(B68-B67)/B67 -> 0.033281734
A69: 2018 | B69: 138.775 | C69: =(B69-B68)/B68 -> 0.039513109
A70: 2019 | B70: 144.18182 | C70: =(B70-B69)/B69 -> 0.038961039
A71: 2020 | B71: 152.58333 | C71: =(B71-B70)/B70 -> 0.058270282
A72: 2021 | B72: 161.45833 | C72: =(B72-B71)/B71 -> 0.058164937
A73: 2022 | B73: 172.15 | C73: =(B73-B72)/B72 -> 0.066219355
A74: 2023 | B74: 177.62 | C74: =(B74-B73)/B73 -> 0.031774615
A75: Grand Total | B75: 139.77419

Sheet Copy
A1: Sector | B1: Date | C1: Year | D1: Month | F1: Month Number | G1: Cereals and products | H1: Meat and fish | I1: Egg | J1: Milk and products | K1: Oils and fats | L1: Fruits | M1: Vegetables | N1: Pulses and products | O1: Sugar and Confectionery | P1: Spices | Q1: Non-alcoholic beverages | R1: Prepared meals, snacks, sweets etc. | S1: Food and beverages | T1: Pan, tobacco and intoxicants | U1: Clothing | V1: Footwear | W1: Clothing and footwear | X1: Housing | Y1: Fuel and light | Z1: Household goods and services | AA1: Health | AB1: Transport and communication | AC1: Recreation and amusement | AD1: Education | AE1: Personal care and effects | AF1: Miscellaneous | AG1: General index | AH1: Food | AI1: Energy | AJ1: Transportation | AK1: Education | AL1: Others | AM1: Flag
A2: Rural | B2: =DATE(C2,F2,1) -> 41275 | C2: 2013 | D2: January | E2: =_xlfn.CONCAT(TEXT(B2,"mmm"),,"-",RIGHT(C2,2)) -> Jan-13 | F2: =VLOOKUP(D2,'Problem Statement 4'!$G$2:$H$13,2,0) -> 1 | G2: 107.5 | H2: 106.3 | I2: 108.1 | J2: 104.9 | K2: 106.1 | L2: 103.9 | M2: 101.9 | N2: 106.1 | O2: 106.8 | P2: 103.1 | Q2: 104.8 | R2: 106.7 | S2: 105.5 | T2: 105.1 | U2: 106.5 | V2: 105.8 | W2: 106.4 | X2: 100.3 | Y2: 105.5 | Z2: 104.8 | AA2: 104 | AB2: 103.3 | AC2: 103.4 | AD2: 103.8 | AE2: 104.7 | AF2: 104 | AG2: 105.1 | AH2: =SUM(G2:S2) -> 1371.7 | AI2: =SUM(Y2) -> 105.5 | AJ2: =SUM(AB2) -> 103.3 | AK2: =SUM(AD2) -> 103.8 | AL2: =SUM(T2:X2,Z2:AA2,AC2,AE2:AF2) -> 1045 | AM2: =IF(AND(L2>150,M2>150),"Yes","No") -> No | AN2: =COUNTIFS(AM1:AM373,"Yes") -> 91
A3: Urban | B3: =DATE(C3,F3,1) -> 41275 | C3: 2013 | D3: January | E3: =_xlfn.CONCAT(TEXT(B3,"mmm"),,"-",RIGHT(C3,2)) -> Jan-13 | F3: =VLOOKUP(D3,'Problem Statement 4'!$G$2:$H$13,2,0) -> 1 | G3: 110.5 | H3: 109.1 | I3: 113 | J3: 103.6 | K3: 103.4 | L3: 102.3 | M3: 102.9 | N3: 105.8 | O3: 105.1 | P3: 101.8 | Q3: 105.1 | R3: 107.9 | S3: 105.9 | T3: 105.2 | U3: 105.9 | V3: 105 | W3: 105.8 | X3: 100.3 | Y3: 105.4 | Z3: 104.8 | AA3: 104.1 | AB3: 103.2 | AC3: 102.9 | AD3: 103.5 | AE3: 104.3 | AF3: 103.7 | AG3: 104 | AH3: =SUM(G3:S3) -> 1376.4 | AI3: =SUM(Y3) -> 105.4 | AJ3: =SUM(AB3) -> 103.2 | AK3: =SUM(AD3) -> 103.5 | AL3: =SUM(T3:X3,Z3:AA3,AC3,AE3:AF3) -> 1042 | AM3: =IF(AND(L3>150,M3>150),"Yes","No") -> No
A4: Rural+Urban | B4: =DATE(C4,F4,1) -> 41275 | C4: 2013 | D4: January | E4: =_xlfn.CONCAT(TEXT(B4,"mmm"),,"-",RIGHT(C4,2)) -> Jan-13 | F4: =VLOOKUP(D4,'Problem Statement 4'!$G$2:$H$13,2,0) -> 1 | G4: 108.4 | H4: 107.3 | I4: 110 | J4: 104.4 | K4: 105.1 | L4: 103.2 | M4: 102.2 | N4: 106 | O4: 106.2 | P4: 102.7 | Q4: 104.9 | R4: 107.3 | S4: 105.6 | T4: 105.1 | U4: 106.3 | V4: 105.5 | W4: 106.2 | X4: 100.3 | Y4: 105.5 | Z4: 104.8 | AA4: 104 | AB4: 103.2 | AC4: 103.1 | AD4: 103.6 | AE4: 104.5 | AF4: 103.9 | AG4: 104.6 | AH4: =SUM(G4:S4) -> 1373.3 | AI4: =SUM(Y4) -> 105.5 | AJ4: =SUM(AB4) -> 103.2 | AK4: =SUM(AD4) -> 103.6 | AL4: =SUM(T4:X4,Z4:AA4,AC4,AE4:AF4) -> 1043.7 | AM4: =IF(AND(L4>150,M4>150),"Yes","No") -> No
A5: Rural | B5: =DATE(C5,F5,1) -> 41306 | C5: 2013 | D5: February | E5: =_xlfn.CONCAT(TEXT(B5,"mmm"),,"-",RIGHT(C5,2)) -> Feb-13 | F5: =VLOOKUP(D5,'Problem Statement 4'!$G$2:$H$13,2,0) -> 2 | G5: 109.2 | H5: 108.7 | I5: 110.2 | J5: 105.4 | K5: 106.7 | L5: 104 | M5: 102.4 | N5: 105.9 | O5: 105.7 | P5: 103.1 | Q5: 105.1 | R5: 107.7 | S5: 106.3 | T5: 105.6 | U5: 107.1 | V5: 106.3 | W5: 107 | X5: 100.4 | Y5: 106.2 | Z5: 105.2 | AA5: 104.4 | AB5: 103.9 | AC5: 104 | AD5: 104.1 | AE5: 104.6 | AF5: 104.4 | AG5: 105.8 | AH5: =SUM(G5:S5) -> 1380.4 | AI5: =SUM(Y5) -> 106.2 | AJ5: =SUM(AB5) -> 103.9 | AK5: =SUM(AD5) -> 104.1 | AL5: =SUM(T5:X5,Z5:AA5,AC5,AE5:AF5) -> 1049 | AM5: =IF(AND(L5>150,M5>150),"Yes","No") -> No
A6: Urban | B6: =DATE(C6,F6,1) -> 41306 | C6: 2013 | D6: February | E6: =_xlfn.CONCAT(TEXT(B6,"mmm"),,"-",RIGHT(C6,2)) -> Feb-13 | F6: =VLOOKUP(D6,'Problem Statement 4'!$G$2:$H$13,2,0) -> 2 | G6: 112.9 | H6: 112.9 | I6: 116.9 | J6: 104 | K6: 103.5 | L6: 103.1 | M6: 104.9 | N6: 104.1 | O6: 103.8 | P6: 102.3 | Q6: 106 | R6: 109 | S6: 107.2 | T6: 106 | U6: 106.6 | V6: 105.5 | W6: 106.4 | X6: 100.4 | Y6: 105.7 | Z6: 105.2 | AA6: 104.7 | AB6: 104.4 | AC6: 103.3 | AD6: 103.7 | AE6: 104.3 | AF6: 104.3 | AG6: 104.7 | AH6: =SUM(G6:S6) -> 1390.6 | AI6: =SUM(Y6) -> 105.7 | AJ6: =SUM(AB6) -> 104.4 | AK6: =SUM(AD6) -> 103.7 | AL6: =SUM(T6:X6,Z6:AA6,AC6,AE6:AF6) -> 1046.7 | AM6: =IF(AND(L6>150,M6>150),"Yes","No") -> No
A7: Rural+Urban | B7: =DATE(C7,F7,1) -> 41306 | C7: 2013 | D7: February | E7: =_xlfn.CONCAT(TEXT(B7,"mmm"),,"-",RIGHT(C7,2)) -> Feb-13 | F7: =VLOOKUP(D7,'Problem Statement 4'!$G$2:$H$13,2,0) -> 2 | G7: 110.4 | H7: 110.2 | I7: 112.8 | J7: 104.9 | K7: 105.5 | L7: 103.6 | M7: 103.2 | N7: 105.3 | O7: 105.1 | P7: 102.8 | Q7: 105.5 | R7: 108.3 | S7: 106.6 | T7: 105.7 | U7: 106.9 | V7: 106 | W7: 106.8 | X7: 100.4 | Y7: 106 | Z7: 105.2 | AA7: 104.5 | AB7: 104.2 | AC7: 103.6 | AD7: 103.9 | AE7: 104.5 | AF7: 104.4 | AG7: 105.3 | AH7: =SUM(G7:S7) -> 1384.2 | AI7: =SUM(Y7) -> 106 | AJ7: =SUM(AB7) -> 104.2 | AK7: =SUM(AD7) -> 103.9 | AL7: =SUM(T7:X7,Z7:AA7,AC7,AE7:AF7) -> 1048 | AM7: =IF(AND(L7>150,M7>150),"Yes","No") -> No
A8: Rural | B8: =DATE(C8,F8,1) -> 41334 | C8: 2013 | D8: March | E8: =_xlfn.CONCAT(TEXT(B8,"mmm"),,"-",RIGHT(C8,2)) -> Mar-13 | F8: =VLOOKUP(D8,'Problem Statement 4'!$G$2:$H$13,2,0) -> 3 | G8: 110.2 | H8: 108.8 | I8: 109.9 | J8: 105.6 | K8: 106.2 | L8: 105.7 | M8: 101.4 | N8: 105.7 | O8: 105 | P8: 103.3 | Q8: 105.6 | R8: 108.2 | S8: 106.6 | T8: 106.5 | U8: 107.6 | V8: 106.8 | W8: 107.5 | X8: 100.4 | Y8: 106.1 | Z8: 105.6 | AA8: 104.7 | AB8: 104.6 | AC8: 104 | AD8: 104.3 | AE8: 104.3 | AF8: 104.6 | AG8: 106 | AH8: =SUM(G8:S8) -> 1382.2 | AI8: =SUM(Y8) -> 106.1 | AJ8: =SUM(AB8) -> 104.6 | AK8: =SUM(AD8) -> 104.3 | AL8: =SUM(T8:X8,Z8:AA8,AC8,AE8:AF8) -> 1052 | AM8: =IF(AND(L8>150,M8>150),"Yes","No") -> No
A9: Urban | B9: =DATE(C9,F9,1) -> 41334 | C9: 2013 | D9: March | E9: =_xlfn.CONCAT(TEXT(B9,"mmm"),,"-",RIGHT(C9,2)) -> Mar-13 | F9: =VLOOKUP(D9,'Problem Statement 4'!$G$2:$H$13,2,0) -> 3 | G9: 113.9 | H9: 111.4 | I9: 113.2 | J9: 104.3 | K9: 102.7 | L9: 104.9 | M9: 103.8 | N9: 103.5 | O9: 102.6 | P9: 102.4 | Q9: 107 | R9: 109.8 | S9: 107.3 | T9: 106.8 | U9: 107.2 | V9: 106 | W9: 107 | X9: 100.4 | Y9: 106 | Z9: 105.7 | AA9: 105.2 | AB9: 105.5 | AC9: 103.5 | AD9: 103.8 | AE9: 104.2 | AF9: 104.9 | AG9: 105 | AH9: =SUM(G9:S9) -> 1386.8 | AI9: =SUM(Y9) -> 106 | AJ9: =SUM(AB9) -> 105.5 | AK9: =SUM(AD9) -> 103.8 | AL9: =SUM(T9:X9,Z9:AA9,AC9,AE9:AF9) -> 1050.9 | AM9: =IF(AND(L9>150,M9>150),"Yes","No") -> No
A10: Rural+Urban | B10: =DATE(C10,F10,1) -> 41334 | C10: 2013 | D10: March | E10: =_xlfn.CONCAT(TEXT(B10,"mmm"),,"-",RIGHT(C10,2)) -> Mar-13 | F10: =VLOOKUP(D10,'Problem Statement 4'!$G$2:$H$13,2,0) -> 3 | G10: 111.4 | H10: 109.7 | I10: 111.2 | J10: 105.1 | K10: 104.9 | L10: 105.3 | M10: 102.2 | N10: 105 | O10: 104.2 | P10: 103 | Q10: 106.2 | R10: 108.9 | S10: 106.9 | T10: 106.6 | U10: 107.4 | V10: 106.5 | W10: 107.3 | X10: 100.4 | Y10: 106.1 | Z10: 105.6 | AA10: 104.9 | AB10: 105.1 | AC10: 103.7 | AD10: 104 | AE10: 104.3 | AF10: 104.7 | AG10: 105.5 | AH10: =SUM(G10:S10) -> 1384 | AI10: =SUM(Y10) -> 106.1 | AJ10: =SUM(AB10) -> 105.1 | AK10: =SUM(AD10) -> 104 | AL10: =SUM(T10:X10,Z10:AA10,AC10,AE10:AF10) -> 1051.4 | AM10: =IF(AND(L10>150,M10>150),"Yes","No") -> No
A11: Rural | B11: =DATE(C11,F11,1) -> 41365 | C11: 2013 | D11: April | E11: =_xlfn.CONCAT(TEXT(B11,"mmm"),,"-",RIGHT(C11,2)) -> Apr-13 | F11: =VLOOKUP(D11,'Problem Statement 4'!$G$2:$H$13,2,0) -> 4 | G11: 110.2 | H11: 109.5 | I11: 106.9 | J11: 106.3 | K11: 105.7 | L11: 108.3 | M11: 103.4 | N11: 105.7 | O11: 104.2 | P11: 103.2 | Q11: 106.5 | R11: 108.8 | S11: 107.1 | T11: 107.1 | U11: 108.1 | V11: 107.4 | W11: 108 | X11: 100.5 | Y11: 106.5 | Z11: 106.1 | AA11: 105.1 | AB11: 104.4 | AC11: 104.5 | AD11: 104.8 | AE11: 102.7 | AF11: 104.6 | AG11: 106.4 | AH11: =SUM(G11:S11) -> 1385.8 | AI11: =SUM(Y11) -> 106.5 | AJ11: =SUM(AB11) -> 104.4 | AK11: =SUM(AD11) -> 104.8 | AL11: =SUM(T11:X11,Z11:AA11,AC11,AE11:AF11) -> 1054.1 | AM11: =IF(AND(L11>150,M11>150),"Yes","No") -> No
A12: Urban | B12: =DATE(C12,F12,1) -> 41365 | C12: 2013 | D12: April | E12: =_xlfn.CONCAT(TEXT(B12,"mmm"),,"-",RIGHT(C12,2)) -> Apr-13 | F12: =VLOOKUP(D12,'Problem Statement 4'!$G$2:$H$13,2,0) -> 4 | G12: 114.6 | H12: 113.4 | I12: 106 | J12: 104.7 | K12: 102.1 | L12: 109.5 | M12: 109.7 | N12: 104.6 | O12: 102 | P12: 103.5 | Q12: 108.2 | R12: 110.6 | S12: 108.8 | T12: 108.5 | U12: 107.9 | V12: 106.4 | W12: 107.7 | X12: 100.5 | Y12: 106.4 | Z12: 106.5 | AA12: 105.7 | AB12: 105 | AC12: 104 | AD12: 105.2 | AE12: 103.2 | AF12: 105.1 | AG12: 105.7 | AH12: =SUM(G12:S12) -> 1397.7 | AI12: =SUM(Y12) -> 106.4 | AJ12: =SUM(AB12) -> 105 | AK12: =SUM(AD12) -> 105.2 | AL12: =SUM(T12:X12,Z12:AA12,AC12,AE12:AF12) -> 1055.5 | AM12: =IF(AND(L12>150,M12>150),"Yes","No") -> No
A13: Rural+Urban | B13: =DATE(C13,F13,1) -> 41365 | C13: 2013 | D13: April | E13: =_xlfn.CONCAT(TEXT(B13,"mmm"),,"-",RIGHT(C13,2)) -> Apr-13 | F13: =VLOOKUP(D13,'Problem Statement 4'!$G$2:$H$13,2,0) -> 4 | G13: 111.6 | H13: 110.9 | I13: 106.6 | J13: 105.7 | K13: 104.4 | L13: 108.9 | M13: 105.5 | N13: 105.3 | O13: 103.5 | P13: 103.3 | Q13: 107.2 | R13: 109.6 | S13: 107.7 | T13: 107.5 | U13: 108 | V13: 107 | W13: 107.9 | X13: 100.5 | Y13: 106.5 | Z13: 106.3 | AA13: 105.3 | AB13: 104.7 | AC13: 104.2 | AD13: 105 | AE13: 102.9 | AF13: 104.8 | AG13: 106.1 | AH13: =SUM(G13:S13) -> 1390.2 | AI13: =SUM(Y13) -> 106.5 | AJ13: =SUM(AB13) -> 104.7 | AK13: =SUM(AD13) -> 105 | AL13: =SUM(T13:X13,Z13:AA13,AC13,AE13:AF13) -> 1054.4 | AM13: =IF(AND(L13>150,M13>150),"Yes","No") -> No
A14: Rural | B14: =DATE(C14,F14,1) -> 41395 | C14: 2013 | D14: May | E14: =_xlfn.CONCAT(TEXT(B14,"mmm"),,"-",RIGHT(C14,2)) -> May-13 | F14: =VLOOKUP(D14,'Problem Statement 4'!$G$2:$H$13,2,0) -> 5 | G14: 110.9 | H14: 109.8 | I14: 105.9 | J14: 107.5 | K14: 105.3 | L14: 108.1 | M14: 107.3 | N14: 106.1 | O14: 103.7 | P14: 104 | Q14: 107.4 | R14: 109.9 | S14: 108.1 | T14: 108.1 | U14: 108.8 | V14: 107.9 | W14: 108.6 | X14: 100.5 | Y14: 107.5 | Z14: 106.8 | AA14: 105.7 | AB14: 104.1 | AC14: 105 | AD14: 105.5 | AE14: 102.1 | AF14: 104.8 | AG14: 107.2 | AH14: =SUM(G14:S14) -> 1394 | AI14: =SUM(Y14) -> 107.5 | AJ14: =SUM(AB14) -> 104.1 | AK14: =SUM(AD14) -> 105.5 | AL14: =SUM(T14:X14,Z14:AA14,AC14,AE14:AF14) -> 1058.3 | AM14: =IF(AND(L14>150,M14>150),"Yes","No") -> No
... A373: Rural+Urban | B373: =DATE(C373,F373,1) -> 45047 | C373: 2023 | D373: May | E373: =_xlfn.CONCAT(TEXT(B373,"mmm"),,"-",RIGHT(C373,2)) -> May-23 | F373: =VLOOKUP(D373,'Problem Statement 4'!$G$2:$H$13,2,0) -> 5 | G373: 173.7 | H373: 214.3 | I373: 173.2 | J373: 179.5 | K373: 170 | L373: 172.2 | M373: 161 | N373: 175.6 | O373: 122.7 | P373: 218 | Q373: 173.4 | R373: 194.2 | S373: 179.1 | T373: 201 | U373: 187.3 | V373: 179.7 | W373: 186.2 | X373: 175.6 | Y373: 182.8 | Z373: 175.2 | AA373: 185.7 | AB373: 164.8 | AC373: 171.2 | AD373: 177.1 | AE373: 185.2 | AF373: 175.7 | AG373: 179.1 | AH373: =SUM(G373:S373) -> 2306.9 | AI373: =SUM(Y373) -> 182.8 | AJ373: =SUM(AB373) -> 164.8 | AK373: =SUM(AD373) -> 177.1 | AL373: =SUM(T373:X373,Z373:AA373,AC373,AE373:AF373) -> 1822.8 | AM373: =IF(AND(L373>150,M373>150),"Yes","No") -> Yes
P378: =SUMIFS(P1:P373,A1:A373,"Urban",D1:D373,"December") -> 1481.2

Sheet Main Data
A1: Sector | B1: Date | C1: Year | D1: Month | F1: Month Number | G1: Cereals and products | H1: Meat and fish | I1: Egg | J1: Milk and products | K1: Oils and fats | L1: Fruits | M1: Vegetables | N1: Pulses and products | O1: Sugar and Confectionery | P1: Spices | Q1: Non-alcoholic beverages | R1: Prepared meals, snacks, sweets etc. | S1: Food and beverages | T1: Pan, tobacco and intoxicants | U1: Clothing | V1: Footwear | W1: Clothing and footwear | X1: Housing | Y1: Fuel and light | Z1: Household goods and services | AA1: Health | AB1: Transport and communication | AC1: Recreation and amusement | AD1: Education | AE1: Personal care and effects | AF1: Miscellaneous | AG1: General index | AH1: Food | AI1: Energy | AJ1: Transportation | AK1: Education | AL1: Others
A2: Rural | B2: =DATE(C2,F2,1) -> 41275 | C2: 2013 | D2: January | E2: =_xlfn.CONCAT(TEXT(B2,"mmm"),,"-",RIGHT(C2,2)) -> Jan-13 | F2: =VLOOKUP(D2,'Problem Statement 4'!$G$2:$H$13,2,0) -> 1 | G2: 107.5 | H2: 106.3 | I2: 108.1 | J2: 104.9 | K2: 106.1 | L2: 103.9 | M2: 101.9 | N2: 106.1 | O2: 106.8 | P2: 103.1 | Q2: 104.8 | R2: 106.7 | S2: 105.5 | T2: 105.1 | U2: 106.5 | V2: 105.8 | W2: 106.4 | X2: 100.3 | Y2: 105.5 | Z2: 104.8 | AA2: 104 | AB2: 103.3 | AC2: 103.4 | AD2: 103.8 | AE2: 104.7 | AF2: 104 | AG2: 105.1 | AH2: =SUM(G2:S2) -> 1371.7 | AI2: =SUM(Y2) -> 105.5 | AJ2: =SUM(AB2) -> 103.3 | AK2: =SUM(AD2) -> 103.8 | AL2: =SUM(T2:X2,Z2:AA2,AC2,AE2:AF2) -> 1045
A3: Urban | B3: =DATE(C3,F3,1) -> 41275 | C3: 2013 | D3: January | E3: =_xlfn.CONCAT(TEXT(B3,"mmm"),,"-",RIGHT(C3,2)) -> Jan-13 | F3: =VLOOKUP(D3,'Problem Statement 4'!$G$2:$H$13,2,0) -> 1 | G3: 110.5 | H3: 109.1 | I3: 113 | J3: 103.6 | K3: 103.4 | L3: 102.3 | M3: 102.9 | N3: 105.8 | O3: 105.1 | P3: 101.8 | Q3: 105.1 | R3: 107.9 | S3: 105.9 | T3: 105.2 | U3: 105.9 | V3: 105 | W3: 105.8 | X3: 100.3 | Y3: 105.4 | Z3: 104.8 | AA3: 104.1 | AB3: 103.2 | AC3: 102.9 | AD3: 103.5 | AE3: 104.3 | AF3: 103.7 | AG3: 104 | AH3: =SUM(G3:S3) -> 1376.4 | AI3: =SUM(Y3) -> 105.4 | AJ3: =SUM(AB3) -> 103.2 | AK3: =SUM(AD3) -> 103.5 | AL3: =SUM(T3:X3,Z3:AA3,AC3,AE3:AF3) -> 1042
A4: Rural+Urban | B4: =DATE(C4,F4,1) -> 41275 | C4: 2013 | D4: January | E4: =_xlfn.CONCAT(TEXT(B4,"mmm"),,"-",RIGHT(C4,2)) -> Jan-13 | F4: =VLOOKUP(D4,'Problem Statement 4'!$G$2:$H$13,2,0) -> 1 | G4: 108.4 | H4: 107.3 | I4: 110 | J4: 104.4 | K4: 105.1 | L4: 103.2 | M4: 102.2 | N4: 106 | O4: 106.2 | P4: 102.7 | Q4: 104.9 | R4: 107.3 | S4: 105.6 | T4: 105.1 | U4: 106.3 | V4: 105.5 | W4: 106.2 | X4: 100.3 | Y4: 105.5 | Z4: 104.8 | AA4: 104 | AB4: 103.2 | AC4: 103.1 | AD4: 103.6 | AE4: 104.5 | AF4: 103.9 | AG4: 104.6 | AH4: =SUM(G4:S4) -> 1373.3 | AI4: =SUM(Y4) -> 105.5 | AJ4: =SUM(AB4) -> 103.2 | AK4: =SUM(AD4) -> 103.6 | AL4: =SUM(T4:X4,Z4:AA4,AC4,AE4:AF4) -> 1043.7
A5: Rural | B5: =DATE(C5,F5,1) -> 41306 | C5: 2013 | D5: February | E5: =_xlfn.CONCAT(TEXT(B5,"mmm"),,"-",RIGHT(C5,2)) -> Feb-13 | F5: =VLOOKUP(D5,'Problem Statement 4'!$G$2:$H$13,2,0) -> 2 | G5: 109.2 | H5: 108.7 | I5: 110.2 | J5: 105.4 | K5: 106.7 | L5: 104 | M5: 102.4 | N5: 105.9 | O5: 105.7 | P5: 103.1 | Q5: 105.1 | R5: 107.7 | S5: 106.3 | T5: 105.6 | U5: 107.1 | V5: 106.3 | W5: 107 | X5: 100.4 | Y5: 106.2 | Z5: 105.2 | AA5: 104.4 | AB5: 103.9 | AC5: 104 | AD5: 104.1 | AE5: 104.6 | AF5: 104.4 | AG5: 105.8 | AH5: =SUM(G5:S5) -> 1380.4 | AI5: =SUM(Y5) -> 106.2 | AJ5: =SUM(AB5) -> 103.9 | AK5: =SUM(AD5) -> 104.1 | AL5: =SUM(T5:X5,Z5:AA5,AC5,AE5:AF5) -> 1049
A6: Urban | B6: =DATE(C6,F6,1) -> 41306 | C6: 2013 | D6: February | E6: =_xlfn.CONCAT(TEXT(B6,"mmm"),,"-",RIGHT(C6,2)) -> Feb-13 | F6: =VLOOKUP(D6,'Problem Statement 4'!$G$2:$H$13,2,0) -> 2 | G6: 112.9 | H6: 112.9 | I6: 116.9 | J6: 104 | K6: 103.5 | L6: 103.1 | M6: 104.9 | N6: 104.1 | O6: 103.8 | P6: 102.3 | Q6: 106 | R6: 109 | S6: 107.2 | T6: 106 | U6: 106.6 | V6: 105.5 | W6: 106.4 | X6: 100.4 | Y6: 105.7 | Z6: 105.2 | AA6: 104.7 | AB6: 104.4 | AC6: 103.3 | AD6: 103.7 | AE6: 104.3 | AF6: 104.3 | AG6: 104.7 | AH6: =SUM(G6:S6) -> 1390.6 | AI6: =SUM(Y6) -> 105.7 | AJ6: =SUM(AB6) -> 104.4 | AK6: =SUM(AD6) -> 103.7 | AL6: =SUM(T6:X6,Z6:AA6,AC6,AE6:AF6) -> 1046.7
A7: Rural+Urban | B7: =DATE(C7,F7,1) -> 41306 | C7: 2013 | D7: February | E7: =_xlfn.CONCAT(TEXT(B7,"mmm"),,"-",RIGHT(C7,2)) -> Feb-13 | F7: =VLOOKUP(D7,'Problem Statement 4'!$G$2:$H$13,2,0) -> 2 | G7: 110.4 | H7: 110.2 | I7: 112.8 | J7: 104.9 | K7: 105.5 | L7: 103.6 | M7: 103.2 | N7: 105.3 | O7: 105.1 | P7: 102.8 | Q7: 105.5 | R7: 108.3 | S7: 106.6 | T7: 105.7 | U7: 106.9 | V7: 106 | W7: 106.8 | X7: 100.4 | Y7: 106 | Z7: 105.2 | AA7: 104.5 | AB7: 104.2 | AC7: 103.6 | AD7: 103.9 | AE7: 104.5 | AF7: 104.4 | AG7: 105.3 | AH7: =SUM(G7:S7) -> 1384.2 | AI7: =SUM(Y7) -> 106 | AJ7: =SUM(AB7) -> 104.2 | AK7: =SUM(AD7) -> 103.9 | AL7: =SUM(T7:X7,Z7:AA7,AC7,AE7:AF7) -> 1048
A8: Rural | B8: =DATE(C8,F8,1) -> 41334 | C8: 2013 | D8: March | E8: =_xlfn.CONCAT(TEXT(B8,"mmm"),,"-",RIGHT(C8,2)) -> Mar-13 | F8: =VLOOKUP(D8,'Problem Statement 4'!$G$2:$H$13,2,0) -> 3 | G8: 110.2 | H8: 108.8 | I8: 109.9 | J8: 105.6 | K8: 106.2 | L8: 105.7 | M8: 101.4 | N8: 105.7 | O8: 105 | P8: 103.3 | Q8: 105.6 | R8: 108.2 | S8: 106.6 | T8: 106.5 | U8: 107.6 | V8: 106.8 | W8: 107.5 | X8: 100.4 | Y8: 106.1 | Z8: 105.6 | AA8: 104.7 | AB8: 104.6 | AC8: 104 | AD8: 104.3 | AE8: 104.3 | AF8: 104.6 | AG8: 106 | AH8: =SUM(G8:S8) -> 1382.2 | AI8: =SUM(Y8) -> 106.1 | AJ8: =SUM(AB8) -> 104.6 | AK8: =SUM(AD8) -> 104.3 | AL8: =SUM(T8:X8,Z8:AA8,AC8,AE8:AF8) -> 1052
A9: Urban | B9: =DATE(C9,F9,1) -> 41334 | C9: 2013 | D9: March | E9: =_xlfn.CONCAT(TEXT(B9,"mmm"),,"-",RIGHT(C9,2)) -> Mar-13 | F9: =VLOOKUP(D9,'Problem Statement 4'!$G$2:$H$13,2,0) -> 3 | G9: 113.9 | H9: 111.4 | I9: 113.2 | J9: 104.3 | K9: 102.7 | L9: 104.9 | M9: 103.8 | N9: 103.5 | O9: 102.6 | P9: 102.4 | Q9: 107 | R9: 109.8 | S9: 107.3 | T9: 106.8 | U9: 107.2 | V9: 106 | W9: 107 | X9: 100.4 | Y9: 106 | Z9: 105.7 | AA9: 105.2 | AB9: 105.5 | AC9: 103.5 | AD9: 103.8 | AE9: 104.2 | AF9: 104.9 | AG9: 105 | AH9: =SUM(G9:S9) -> 1386.8 | AI9: =SUM(Y9) -> 106 | AJ9: =SUM(AB9) -> 105.5 | AK9: =SUM(AD9) -> 103.8 | AL9: =SUM(T9:X9,Z9:AA9,AC9,AE9:AF9) -> 1050.9
A10: Rural+Urban | B10: =DATE(C10,F10,1) -> 41334 | C10: 2013 | D10: March | E10: =_xlfn.CONCAT(TEXT(B10,"mmm"),,"-",RIGHT(C10,2)) -> Mar-13 | F10: =VLOOKUP(D10,'Problem Statement 4'!$G$2:$H$13,2,0) -> 3 | G10: 111.4 | H10: 109.7 | I10: 111.2 | J10: 105.1 | K10: 104.9 | L10: 105.3 | M10: 102.2 | N10: 105 | O10: 104.2 | P10: 103 | Q10: 106.2 | R10: 108.9 | S10: 106.9 | T10: 106.6 | U10: 107.4 | V10: 106.5 | W10: 107.3 | X10: 100.4 | Y10: 106.1 | Z10: 105.6 | AA10: 104.9 | AB10: 105.1 | AC10: 103.7 | AD10: 104 | AE10: 104.3 | AF10: 104.7 | AG10: 105.5 | AH10: =SUM(G10:S10) -> 1384 | AI10: =SUM(Y10) -> 106.1 | AJ10: =SUM(AB10) -> 105.1 | AK10: =SUM(AD10) -> 104 | AL10: =SUM(T10:X10,Z10:AA10,AC10,AE10:AF10) -> 1051.4
A11: Rural | B11: =DATE(C11,F11,1) -> 41365 | C11: 2013 | D11: April | E11: =_xlfn.CONCAT(TEXT(B11,"mmm"),,"-",RIGHT(C11,2)) -> Apr-13 | F11: =VLOOKUP(D11,'Problem Statement 4'!$G$2:$H$13,2,0) -> 4 | G11: 110.2 | H11: 109.5 | I11: 106.9 | J11: 106.3 | K11: 105.7 | L11: 108.3 | M11: 103.4 | N11: 105.7 | O11: 104.2 | P11: 103.2 | Q11: 106.5 | R11: 108.8 | S11: 107.1 | T11: 107.1 | U11: 108.1 | V11: 107.4 | W11: 108 | X11: 100.5 | Y11: 106.5 | Z11: 106.1 | AA11: 105.1 | AB11: 104.4 | AC11: 104.5 | AD11: 104.8 | AE11: 102.7 | AF11: 104.6 | AG11: 106.4 | AH11: =SUM(G11:S11) -> 1385.8 | AI11: =SUM(Y11) -> 106.5 | AJ11: =SUM(AB11) -> 104.4 | AK11: =SUM(AD11) -> 104.8 | AL11: =SUM(T11:X11,Z11:AA11,AC11,AE11:AF11) -> 1054.1
A12: Urban | B12: =DATE(C12,F12,1) -> 41365 | C12: 2013 | D12: April | E12: =_xlfn.CONCAT(TEXT(B12,"mmm"),,"-",RIGHT(C12,2)) -> Apr-13 | F12: =VLOOKUP(D12,'Problem Statement 4'!$G$2:$H$13,2,0) -> 4 | G12: 114.6 | H12: 113.4 | I12: 106 | J12: 104.7 | K12: 102.1 | L12: 109.5 | M12: 109.7 | N12: 104.6 | O12: 102 | P12: 103.5 | Q12: 108.2 | R12: 110.6 | S12: 108.8 | T12: 108.5 | U12: 107.9 | V12: 106.4 | W12: 107.7 | X12: 100.5 | Y12: 106.4 | Z12: 106.5 | AA12: 105.7 | AB12: 105 | AC12: 104 | AD12: 105.2 | AE12: 103.2 | AF12: 105.1 | AG12: 105.7 | AH12: =SUM(G12:S12) -> 1397.7 | AI12: =SUM(Y12) -> 106.4 | AJ12: =SUM(AB12) -> 105 | AK12: =SUM(AD12) -> 105.2 | AL12: =SUM(T12:X12,Z12:AA12,AC12,AE12:AF12) -> 1055.5
A13: Rural+Urban | B13: =DATE(C13,F13,1) -> 41365 | C13: 2013 | D13: April | E13: =_xlfn.CONCAT(TEXT(B13,"mmm"),,"-",RIGHT(C13,2)) -> Apr-13 | F13: =VLOOKUP(D13,'Problem Statement 4'!$G$2:$H$13,2,0) -> 4 | G13: 111.6 | H13: 110.9 | I13: 106.6 | J13: 105.7 | K13: 104.4 | L13: 108.9 | M13: 105.5 | N13: 105.3 | O13: 103.5 | P13: 103.3 | Q13: 107.2 | R13: 109.6 | S13: 107.7 | T13: 107.5 | U13: 108 | V13: 107 | W13: 107.9 | X13: 100.5 | Y13: 106.5 | Z13: 106.3 | AA13: 105.3 | AB13: 104.7 | AC13: 104.2 | AD13: 105 | AE13: 102.9 | AF13: 104.8 | AG13: 106.1 | AH13: =SUM(G13:S13) -> 1390.2 | AI13: =SUM(Y13) -> 106.5 | AJ13: =SUM(AB13) -> 104.7 | AK13: =SUM(AD13) -> 105 | AL13: =SUM(T13:X13,Z13:AA13,AC13,AE13:AF13) -> 1054.4
... A373: Rural+Urban | B373: =DATE(C373,F373,1) -> 45047 | C373: 2023 | D373: May | E373: =_xlfn.CONCAT(TEXT(B373,"mmm"),,"-",RIGHT(C373,2)) -> May-23 | F373: =VLOOKUP(D373,'Problem Statement 4'!$G$2:$H$13,2,0) -> 5 | G373: 173.7 | H373: 214.3 | I373: 173.2 | J373: 179.5 | K373: 170 | L373: 172.2 | M373: 161 | N373: 175.6 | O373: 122.7 | P373: 218 | Q373: 173.4 | R373: 194.2 | S373: 179.1 | T373: 201 | U373: 187.3 | V373: 179.7 | W373: 186.2 | X373: 175.6 | Y373: 182.8 | Z373: 175.2 | AA373: 185.7 | AB373: 164.8 | AC373: 171.2 | AD373: 177.1 | AE373: 185.2 | AF373: 175.7 | AG373: 179.1 | AH373: =SUM(G373:S373) -> 2306.9 | AI373: =SUM(Y373) -> 182.8 | AJ373: =SUM(AB373) -> 164.8 | AK373: =SUM(AD373) -> 177.1 | AL373: =SUM(T373:X373,Z373:AA373,AC373,AE373:AF373) -> 1822.8

Sheet Sheet2
A1: 1 | B1: State the business problem in one or two sentences. | E1: Here are the Excel-ready recommendation points for the insight:
B2: The business problem is to analyze the key drivers and trends of inflation in India by examining the Consumer Price Index (CPI) data across various categories, identify the main contributors to rising prices, and assess the impact of major events such as COVID-19 and global oil price fluctuations on overall inflation. This analysis will help policymakers and businesses understand inflation dynamics and make informed decisions.
E3: "Oil price changes have a strong impact on overall inflation and all major CPI categories in India."
A5: 2 | B5: Data Preparation – Briefly explain how you ensured clean, accurate data.
E7: 📊 Excel Table: Recommendations for Oil-Driven Inflation
B8: Handle Missing Values: Identify missing data points and use imputation techniques like moving averages to fill gaps. For example, if April’s value is missing, average March and May’s values to estimate it.
B9: Check for Duplicates: Remove any duplicate records to avoid skewed results. | E9: Recommendation # | F9: Recommendation
B10: Standardize Formats: Ensure all dates, categories, and numerical values follow a consistent format (e.g., YYYY-MM for dates). | E10: 1 | F10: Diversify energy mix with renewables to reduce dependency on imported crude oil
B11: Validate Data Ranges: Check that index values are within expected ranges and flag any outliers for review. | E11: 2 | F11: Strengthen strategic petroleum reserves to buffer against global price shocks
B12: Categorize Data: Group items correctly into broader categories (food, energy, etc.) as per the CPI basket. | E12: 3 | F12: Implement dynamic fuel pricing to smooth consumer impact during oil price swings
B13: Document Changes: Keep a log of all cleaning steps for transparency and reproducibility. | E13: 4 | F13: Promote fuel-efficient transport and logistics through EVs and optimized routing
E14: 5 | F14: Encourage modal shifts (rail, waterways) to reduce fuel intensity in freight
E15: 6 | F15: Expand domestic refining capacity to reduce import costs and improve resilience
E16: 7 | F16: Use targeted subsidies or direct transfers during fuel-driven inflation spikes
E17: 8 | F17: Improve CPI granularity to monitor fuel-linked inflation across categories
A19: 3 | B19: Analysis Approach – Describe the charts, formulas, and metrics you used.
E20: Let me know if you'd like this formatted with slicers, conditional formatting, or integrated into a CPI dashboard.
B21: I used SUMIFS and AVERAGEIFS formulas in Excel to aggregate and analyze data for different categories and time periods.
B22: The Inflation Rate was calculated using the formula:
B23: [(\text{Current Value} - \text{Previous Value}) / \text{Previous Value} \times 100]
B24: This was applied for year-on-year (YoY), month-on-month (MoM), and quarter-on-quarter (QoQ) calculations.
B25: For visualization, I used:
B26: Bar charts to compare inflation rates across categories and time periods.
B27: Pie charts to show the contribution of each category to overall inflation.
B28: Line charts to display trends in inflation over time.
B29: Combo charts to compare multiple metrics (e.g., category-wise inflation and overall CPI) in a single view.
B30: These charts and metrics helped identify which month, year, or category had the highest or lowest inflation.
B31: Also used slicers for better analysis of the data
A34: 4 | B34: Key Insights – Highlight the most important findings from your analysis.
B35: The highest inflation was observed in the food category during the year 2020, likely due to supply chain disruptions and increased demand during the COVID-19 pandemic.
B36: In 2021, the energy category experienced the highest CPI inflation, possibly driven by global crude oil price hikes and increased fuel costs.
B37: The transportation category also saw its highest CPI inflation in 2021, correlating with rising fuel prices and increased transportation costs post-pandemic.
B38: Top Contributing Category: Food often has the highest contribution to the CPI basket, meaning changes in food prices have the biggest impact on overall inflation. For example, if food prices rise sharply, overall inflation increases significantly.
B39: Year with Highest Inflation: The analysis may show that a specific year (e.g., 2022) had the highest year-on-year inflation, possibly due to global supply chain disruptions or spikes in commodity prices.
B40: COVID-19 Impact: After March 2020, inflation in healthcare and essential goods increased, reflecting higher demand and supply challenges during the pandemic.
B41: Food Price Trends: Within the last 12 months, certain months (e.g., July 2022) saw the highest food inflation, often driven by items like vegetables or edible oils.
B42: Oil Price Influence: Fluctuations in global crude oil prices from 2021-2023 directly affected fuel and transportation costs, which in turn pushed up overall inflation.
B43: Urban vs. Rural: CPI-U (urban) and CPI-R (rural) may show different inflation patterns, highlighting varying impacts on city and village consumers.
A49: 5 | B49: Creative Recommendations – Suggest actions based on your insights.
B50: Based on the CPI inflation analysis, here are some creative recommendations:
B52: Targeted Subsidies: If food or fuel is the main inflation driver, the government can offer targeted subsidies or tax relief on these items to ease consumer burden.
B53: Diversify Imports: To reduce the impact of global oil price shocks, India can diversify its energy imports and invest more in renewable energy sources.
B54: Strengthen Supply Chains: Address supply chain disruptions (especially post-COVID) by improving logistics and supporting local producers, which can help stabilize prices for essentials.
B55: Monitor and Regulate Hoarding: Implement stricter monitoring to prevent hoarding and artificial price hikes in high-inflation categories like food.
B56: Promote Urban-Rural Balance: Since CPI-U and CPI-R can differ, tailor policies to address specific inflation issues in urban and rural areas.
B57: Public Awareness: Educate consumers on inflation trends and promote smart spending or saving habits during high-inflation periods.
B58: Data-Driven Policy: Use real-time CPI data analytics to make timely policy decisions, such as adjusting interest rates or import/export rules.
B60: These actions can help manage inflation, protect vulnerable groups, and ensure economic stability.
E63: Absolutely! Here are the recommendation points only, ready for Excel or dashboard use:
A64: 6 | B64: Business Impact – End with how your analysis influenced decisions or actions.
B65: Analyzing CPI inflation helps businesses and policymakers make informed decisions:
B67: Pricing Strategies: Companies can adjust product prices based on inflation trends to maintain profit margins. | E67: ✅ Recommendations (Excel-Ready Bullet Points)
B68: Inventory Planning: Retailers may stock up on goods if they anticipate price rises, especially in high-inflation categories like food or fuel.
B69: Cost Management: Businesses can identify which input costs (e.g., energy, raw materials) are rising fastest and seek alternatives or negotiate better contracts. | E69: Strengthen domestic food supply chains and invest in cold storage infrastructure
B70: Policy Decisions: Government can target subsidies or interventions in categories with the highest inflation (e.g., food during COVID-19). | E70: Promote crop diversification and reduce reliance on volatile imports like edible oils
B71: Investment Choices: Investors use inflation trends to decide on sectors likely to perform well or poorly. | E71: Expand renewable energy adoption to reduce dependency on global crude oil prices
E72: Introduce fuel price stabilization mechanisms (e.g., buffer funds, dynamic tax adjustments)
B73: Example: | E73: Modernize logistics networks and subsidize public transport during fuel price surges
B74: If analysis shows food inflation is rising due to oil price hikes, a food company might lock in oil prices with suppliers or adjust its menu pricing, while the government might increase food subsidies to protect consumers. | E74: Encourage modal shifts in freight transport (e.g., rail over road) to reduce fuel costs
E75: Build strategic reserves of essential healthcare goods and support local manufacturing
E76: Implement price monitoring and anti-hoarding regulations during crisis periods
E77: Enhance CPI tracking granularity and real-time inflation monitoring
E78: Communicate inflation drivers transparently to manage public expectations
E79: Use targeted subsidies or direct benefit transfers for vulnerable groups during inflation spikes
E80: Align fiscal and monetary policies to respond to inflation triggers effectively
E81: Coordinate internationally on commodity stockpiling and supply chain resilience strategies
A83: Sector | B83: Date | C83: Year | F83: Month Number | G83: Cereals and products | H83: Meat and fish | I83: Egg | J83: Milk and products | K83: Oils and fats | L83: Fruits | M83: Vegetables | N83: Pulses and products | O83: Sugar and Confectionery | P83: Spices | Q83: Non-alcoholic beverages | R83: Prepared meals, snacks, sweets etc. | S83: Food and beverages | T83: Pan, tobacco and intoxicants | U83: Clothing | V83: Footwear | W83: Clothing and footwear | X83: Housing | Y83: Fuel and light | Z83: Household goods and services | AA83: Health | AB83: Transport and communication | AC83: Recreation and amusement | AD83: Education | AE83: Personal care and effects | AF83: Miscellaneous | AG83: General index | AH83: Food | AI83: Energy | AJ83: Transportation | AK83: Education | AL83: Others
A84: Rural+Urban | B84: 44197 | C84: 2021 | D84: January | F84: 1 | G84: 144.9 | H84: 190.1 | I84: 175.3 | J84: 154.1 | K84: 150.9 | L84: 149.6 | M84: 194.2 | N84: 160.4 | O84: 114.6 | P84: 164 | Q84: 151.8 | R84: 165.6 | S84: 161 | T84: 186.5 | U84: 155.5 | V84: 146.1 | W84: 154.2 | X84: 157.7 | Y84: 147.9 | Z84: 150 | AA84: 159.3 | AB84: 141.9 | AC84: 149.6 | AD84: 159.2 | AE84: 156.8 | AF84: 151.9 | AG84: 157.3 | AH84: 2076.5 | AI84: 147.9 | AJ84: 141.9 | AK84: 159.2 | AL84: 1567.6
A85: Rural+Urban | B85: 44228 | C85: 2021 | D85: February | E85: Let me know if you'd like these grouped by category (e.g., food, energy, healthcare) or formatted into a dashboard table. | F85: 2 | G85: 144.3 | H85: 186.5 | I85: 168.7 | J85: 154.7 | K85: 158.7 | L85: 150.7 | M85: 160 | N85: 158.8 | O85: 112.8 | P85: 164.2 | Q85: 155.5 | R85: 167.5 | S85: 156.9 | T85: 188.3 | U85: 157.2 | V85: 147.4 | W85: 155.8 | X85: 159.8 | Y85: 152.4 | Z85: 150.9 | AA85: 161.3 | AB85: 145.1 | AC85: 151.5 | AD85: 159.5 | AE85: 155.8 | AF85: 153.4 | AG85: 156.6 | AH85: 2039.3 | AI85: 152.4 | AJ85: 145.1 | AK85: 159.5 | AL85: 1581.4
A86: Rural+Urban | B86: 44256 | C86: 2021 | D86: March | E86: Mar-21 | F86: 3 | G86: 144.1 | H86: 192.2 | I86: 163.8 | J86: 154.9 | K86: 163.9 | L86: 153.7 | M86: 149.5 | N86: 159.8 | O86: 112.6 | P86: 163.5 | Q86: 156.5 | R86: 168.2 | S86: 156.7 | T86: 188.1 | U86: 157.8 | V86: 147.9 | W86: 156.4 | X86: 159.9 | Y86: 155.5 | Z86: 151.2 | AA86: 161.7 | AB86: 146.2 | AC86: 152.6 | AD86: 160.2 | AE86: 153.8 | AF86: 153.8 | AG86: 156.8 | AH86: 2039.4 | AI86: 155.5 | AJ86: 146.2 | AK86: 160.2 | AL86: 1583.2
A87: Rural+Urban | B87: 44287 | C87: 2021 | D87: April | E87: Apr-21 | F87: 4 | G87: 144.3 | H87: 198 | I87: 164.6 | J87: 155.4 | K87: 170.1 | L87: 164.4 | M87: 144.1 | N87: 161.7 | O87: 113.1 | P87: 163.9 | Q87: 157.6 | R87: 168.9 | S87: 158 | T87: 188.8 | U87: 158.8 | V87: 148.5 | W87: 157.3 | X87: 161.4 | Y87: 155.6 | Z87: 151.8 | AA87: 162.3 | AB87: 146.6 | AC87: 153.2 | AD87: 160.3 | AE87: 155.4 | AF87: 154.4 | AG87: 157.8 | AH87: 2064.1 | AI87: 155.6 | AJ87: 146.6 | AK87: 160.3 | AL87: 1591.9
A88: Rural+Urban | B88: 44317 | C88: 2021 | D88: May | E88: May-21 | F88: 5 | G88: 146.3 | H88: 200.5 | I88: 170.3 | J88: 156.1 | K88: 178.7 | L88: 167.1 | M88: 147.9 | N88: 165.4 | O88: 114.8 | P88: 168.2 | Q88: 159.3 | R88: 170.4 | S88: 160.7 | T88: 191.9 | U88: 161.8 | V88: 152.1 | W88: 160.4 | X88: 161.6 | Y88: 159.4 | Z88: 154.7 | AA88: 165.8 | AB88: 148.9 | AC88: 155.8 | AD88: 161.2 | AE88: 158.6 | AF88: 156.8 | AG88: 160.4 | AH88: 2105.7 | AI88: 159.4 | AJ88: 148.9 | AK88: 161.2 | AL88: 1619.5
A89: Rural+Urban | B89: 44348 | C89: 2021 | D89: June | E89: Jun-21 | F89: 6 | G89: 146.7 | H89: 202 | I89: 180.7 | J89: 156.2 | K89: 183.7 | L89: 164.6 | M89: 155.4 | N89: 166 | O89: 115.1 | P89: 168.5 | Q89: 160 | R89: 172.4 | S89: 162.6 | T89: 190.8 | U89: 162.2 | V89: 151.8 | W89: 160.7 | X89: 160.5 | Y89: 159.8 | Z89: 154.8 | AA89: 166.3 | AB89: 150.7 | AC89: 154.9 | AD89: 161.7 | AE89: 158.8 | AF89: 157.6 | AG89: 161.3 | AH89: 2133.9 | AI89: 159.8 | AJ89: 150.7 | AK89: 161.7 | AL89: 1618.4
A90: Rural+Urban | B90: 44378 | C90: 2021 | D90: July | E90: Jul-21 | F90: 7 | G90: 146.4 | H90: 206.8 | I90: 182.2 | J90: 157.5 | K90: 182.1 | L90: 163.9 | M90: 164.2 | N90: 164 | O90: 114.5 | P90: 168.3 | Q90: 160.9 | R90: 172.2 | S90: 164 | T90: 191.2 | U90: 162.8 | V90: 153.1 | W90: 161.4 | X90: 161.5 | Y90: 160.7 | Z90: 155.8 | AA90: 167 | AB90: 153.1 | AC90: 155.3 | AD90: 163.2 | AE90: 160.1 | AF90: 159 | AG90: 162.5 | AH90: 2147 | AI90: 160.7 | AJ90: 153.1 | AK90: 163.2 | AL90: 1627.2
A91: Rural+Urban | B91: 44409 | C91: 2021 | D91: August | E91: Aug-21 | F91: 8 | G91: 146.6 | H91: 204 | I91: 172.8 | J91: 158.4 | K91: 188 | L91: 156.8 | M91: 162.2 | N91: 164.1 | O91: 119.7 | P91: 168.8 | Q91: 162.7 | R91: 173.9 | S91: 164 | T91: 192.1 | U91: 164.5 | V91: 155.3 | W91: 163.2 | X91: 162.1 | Y91: 162.6 | Z91: 157.5 | AA91: 168.4 | AB91: 154 | AC91: 157.6 | AD91: 163.8 | AE91: 160 | AF91: 160 | AG91: 163.2 | AH91: 2142 | AI91: 162.6 | AJ91: 154 | AK91: 163.8 | AL91: 1640.7
A92: Rural+Urban | B92: 44440 | C92: 2021 | D92: September | E92: Sep-21 | F92: 9 | G92: 146.6 | H92: 204 | I92: 172.8 | J92: 158.4 | K92: 188 | L92: 156.7 | M92: 162.3 | N92: 164.1 | O92: 119.7 | P92: 168.8 | Q92: 162.7 | R92: 173.9 | S92: 164 | T92: 192.1 | U92: 164.6 | V92: 155.3 | W92: 163.3 | X92: 162.1 | Y92: 162.6 | Z92: 157.5 | AA92: 168.4 | AB92: 154 | AC92: 157.7 | AD92: 163.7 | AE92: 160 | AF92: 160 | AG92: 163.2 | AH92: 2142 | AI92: 162.6 | AJ92: 154 | AK92: 163.7 | AL92: 1641
A93: Rural+Urban | B93: 44470 | C93: 2021 | D93: October | E93: Oct-21 | F93: 10 | G93: 147.4 | H93: 204.6 | I93: 171.2 | J93: 158.7 | K93: 190.6 | L93: 155.7 | M93: 185.3 | N93: 165.2 | O93: 121.9 | P93: 169.3 | Q93: 163.2 | R93: 174.7 | S93: 167.7 | T93: 192.7 | U93: 165.7 | V93: 156.3 | W93: 164.3 | X93: 163.6 | Y93: 164.2 | Z93: 158.4 | AA93: 169.1 | AB93: 155.7 | AC93: 158.6 | AD93: 163.9 | AE93: 160.8 | AF93: 161 | AG93: 165.5 | AH93: 2175.5 | AI93: 164.2 | AJ93: 155.7 | AK93: 163.9 | AL93: 1650.5
A94: Rural+Urban | B94: 44501 | C94: 2021 | D94: November | E94: Nov-21 | F94: 11 | G94: 148.2 | H94: 201.6 | I94: 173 | J94: 159.3 | K94: 190.1 | L94: 156.5 | M94: 199.2 | N94: 165.3 | O94: 122.4 | P94: 169.6 | Q94: 163.7 | R94: 175.5 | S94: 169.7 | T94: 192.9 | U94: 167.2 | V94: 157.4 | W94: 165.8 | X94: 164.2 | Y94: 163.9 | Z94: 159.3 | AA94: 169.9 | AB94: 154.8 | AC94: 159.8 | AD94: 164.3 | AE94: 162.2 | AF94: 161.4 | AG94: 166.7 | AH94: 2194.1 | AI94: 163.9 | AJ94: 154.8 | AK94: 164.3 | AL94: 1660.1
A95: Rural+Urban | B95: 44531 | C95: 2021 | D95: December | E95: Dec-21 | F95: 12 | G95: 148.7 | H95: 198.8 | I95: 177.9 | J95: 159.9 | K95: 187.6 | L95: 154.9 | M95: 188.3 | N95: 164.4 | O95: 121 | P95: 170.5 | Q95: 164.2 | R95: 176.5 | S95: 168.2 | T95: 192.4 | U95: 168.5 | V95: 158.7 | W95: 167 | X95: 163.4 | Y95: 164.1 | Z95: 160.2 | AA95: 170.6 | AB95: 155.7 | AC95: 160.6 | AD95: 164.4 | AE95: 162.6 | AF95: 162 | AG95: 166.2 | AH95: 2180.9 | AI95: 164.1 | AJ95: 155.7 | AK95: 164.4 | AL95: 1666
A96: Rural+Urban | B96: 44562 | C96: 2022 | D96: January | E96: Jan-22 | F96: 1 | G96: 149.5 | H96: 198.7 | I96: 178.8 | J96: 160.5 | K96: 184.7 | L96: 153.7 | M96: 174.3 | N96: 163.9 | O96: 120 | P96: 172.1 | Q96: 164.3 | R96: 177.3 | S96: 166.4 | T96: 192.2 | U96: 169.9 | V96: 160.7 | W96: 168.5 | X96: 164.5 | Y96: 164.2 | Z96: 161.1 | AA96: 171.4 | AB96: 156.5 | AC96: 161.2 | AD96: 164.7 | AE96: 163 | AF96: 162.7 | AG96: 165.7 | AH96: 2164.2 | AI96: 164.2 | AJ96: 156.5 | AK96: 164.7 | AL96: 1675.2
... A109: Rural+Urban | B109: 44958 | C109: 2023 | D109: February | E109: Feb-23 | F109: 2 | G109: 174.4 | H109: 207.7 | I109: 175.2 | J109: 177.3 | K109: 179.3 | L109: 169.5 | M109: 152.7 | N109: 171 | O109: 120 | P109: 209.7 | Q109: 172.3 | R109: 193 | S109: 177 | T109: 199.5 | U109: 186.2 | V109: 178.7 | W109: 185.1 | X109: 173.5 | Y109: 182.1 | Z109: 174.2 | AA109: 184.4 | AB109: 164.2 | AC109: 170.3 | AD109: 175 | AE109: 181 | AF109: 174.1 | AG109: 177.2 | AH109: 2279.1 | AI109: 182.1 | AJ109: 164.2 | AK109: 175 | AL109: 1807

Sheet Insights
A6: CPI INFLATION CASE STUDY ANALYSIS
A7: The main aim is to analyze the key drivers and trends of inflation in India by examining the Consumer Price Index (CPI) data across various categories, identify the main contributors to rising prices, and assess the impact of major events such as COVID-19 and global oil price fluctuations on overall inflation. This analysis will help policymakers and businesses understand inflation dynamics and make informed decisions.
A13: Key Insights 1) 2020 – Highest inflation in food category due to COVID-19-related supply chain disruptions and increased demand 2) 2021 – Energy category saw highest CPI inflation driven by global crude oil price hikes and fuel costs 3) 2021 – Transportation category also peaked due to rising fuel prices and post-pandemic logistics costs 4) Food is the top contributing category in CPI; sharp food price increases significantly impact overall inflation 5) 2022 – Likely the year with highest overall inflation due to global supply chain disruptions and commodity spikes 6) Post-March 2020 – Healthcare and essential goods inflation rose due to pandemic-driven demand and supply challenges 7) July 2022 – Highest food inflation observed, especially in vegetables and edible oils 8) 2021–2023 – Crude oil price fluctuations directly impacted fuel and transportation costs, pushing up inflation 9) Oil price changes have a strong impact on overall inflation and all major CPI categories in India | C13: 1. 2020 – Food Inflation Surge (COVID Impact) | M13: 2. 2021 – Energy Inflation (Oil Price Spike) | V13: 3. 2021 – Transportation Inflation (Fuel & Logistics)
D33: 5. 2022 – Peak Overall Inflation (Global Disruptions) | M33: 6. Precovid and post covid Inflation Trends across all the Categories
W34: YOY CORRELATION WITH OIL PRICES (2021-2023) | AA34: MOM CORRELATION WITH OIL PRICES (2021-2023)
P40: Problem State,ent 4 and 5
A51: Recommendations
A53: 1)Targeted Subsidies – Offer subsidies or tax relief on food and fuel to reduce consumer burden during inflation spikes
A54: 2)Diversify Imports – Reduce dependence on volatile oil markets by diversifying energy imports and investing in renewables
A55: 3)Strengthen Supply Chains – Improve logistics and support local producers to stabilize prices, especially post-COVID
A56: 4)Monitor and Regulate Hoarding – Prevent artificial price hikes in high-inflation categories like food through stricter monitoring
A57: 5)Promote Urban-Rural Balance – Tailor inflation policies to address distinct CPI-U (urban) and CPI-R (rural) inflation patterns
A58: 6)Public Awareness – Educate consumers on inflation trends and encourage smart spending and saving habits
A59: 7)Data-Driven Policy – Use real-time CPI data to inform timely decisions like interest rate changes or trade adjustments
A64: Footer: Complete
A65: Dataset : CPI Inflation Data set
A66: Time period -October - November 2025

Sheet Sheet8
A2: 🎬 Opening
A4: "Inflation is not just a number—it’s a story of how everyday lives are impacted by changing prices. By analyzing CPI data across categories, we can trace how global events like COVID-19 and oil price shocks ripple through households and businesses, shaping decisions for policymakers and industries alike."
A6: 🧩 Step 1: Understanding the Data
A8: The dataset covers rural and urban cities, tracking both year-on-year (YoY) and month-on-month (MoM) price fluctuations.
A9: To simplify analysis, categories were grouped into Food, Transportation, Energy, Education, and Others.
A11: 📊 Step 2: Insights Across Time
A13: 2020 – The Food Shock
A15: COVID-19 disrupted supply chains and increased demand for essentials.
A16: Result: Food inflation surged across both rural and urban areas.
A17: This was the first major spike, highlighting how crises directly affect basic needs.
A19: 2021 – The Energy Wave
A21: As economies reopened, fuel and oil prices climbed sharply.
... A50: In Precovid and post covid data comparision I got that all the major inflation was observed in Food transportation and energy rest education and other categories remained unimpacted

Sheet Crude oil
A1: Month | B1: Indian Basket of Crude Oil (USD/Barrel) | C1: General index | D1: Food | E1: Energy | F1: Transportation | G1: Education | H1: Others
A2: Jan-21 | B2: 54.79 | C2: =INDEX(Sheet2!$E$83:$AL$109, MATCH('Crude oil'!$A2, Sheet2!$E$83:$E$109, 0), MATCH('Crude oil'!C$1, Sheet2!$E$83:$AL$83, 0)) -> #N/A | D2: =INDEX(Sheet2!$E$83:$AL$109, MATCH('Crude oil'!$A2, Sheet2!$E$83:$E$109, 0), MATCH('Crude oil'!D$1, Sheet2!$E$83:$AL$83, 0)) -> #N/A | E2: =INDEX(Sheet2!$E$83:$AL$109, MATCH('Crude oil'!$A2, Sheet2!$E$83:$E$109, 0), MATCH('Crude oil'!E$1, Sheet2!$E$83:$AL$83, 0)) -> #N/A | F2: =INDEX(Sheet2!$E$83:$AL$109, MATCH('Crude oil'!$A2, Sheet2!$E$83:$E$109, 0), MATCH('Crude oil'!F$1, Sheet2!$E$83:$AL$83, 0)) -> #N/A | G2: =INDEX(Sheet2!$E$83:$AL$109, MATCH('Crude oil'!$A2, Sheet2!$E$83:$E$109, 0), MATCH('Crude oil'!G$1, Sheet2!$E$83:$AL$83, 0)) -> #N/A | H2: =INDEX(Sheet2!$E$83:$AL$109, MATCH('Crude oil'!$A2, Sheet2!$E$83:$E$109, 0), MATCH('Crude oil'!H$1, Sheet2!$E$83:$AL$83, 0)) -> #N/A
A3: Feb-21 | B3: 61.22 | C3: =INDEX(Sheet2!$E$83:$AL$109, MATCH('Crude oil'!$A3, Sheet2!$E$83:$E$109, 0), MATCH('Crude oil'!C$1, Sheet2!$E$83:$AL$83, 0)) -> #N/A | D3: =INDEX(Sheet2!$E$83:$AL$109, MATCH('Crude oil'!$A3, Sheet2!$E$83:$E$109, 0), MATCH('Crude oil'!D$1, Sheet2!$E$83:$AL$83, 0)) -> #N/A | E3: =INDEX(Sheet2!$E$83:$AL$109, MATCH('Crude oil'!$A3, Sheet2!$E$83:$E$109, 0), MATCH('Crude oil'!E$1, Sheet2!$E$83:$AL$83, 0)) -> #N/A | F3: =INDEX(Sheet2!$E$83:$AL$109, MATCH('Crude oil'!$A3, Sheet2!$E$83:$E$109, 0), MATCH('Crude oil'!F$1, Sheet2!$E$83:$AL$83, 0)) -> #N/A | G3: =INDEX(Sheet2!$E$83:$AL$109, MATCH('Crude oil'!$A3, Sheet2!$E$83:$E$109, 0), MATCH('Crude oil'!G$1, Sheet2!$E$83:$AL$83, 0)) -> #N/A | H3: =INDEX(Sheet2!$E$83:$AL$109, MATCH('Crude oil'!$A3, Sheet2!$E$83:$E$109, 0), MATCH('Crude oil'!H$1, Sheet2!$E$83:$AL$83, 0)) -> #N/A
A4: Mar-21 | B4: 64.73 | C4: =INDEX(Sheet2!$E$83:$AL$109, MATCH('Crude oil'!$A4, Sheet2!$E$83:$E$109, 0), MATCH('Crude oil'!C$1, Sheet2!$E$83:$AL$83, 0)) -> 156.8 | D4: =INDEX(Sheet2!$E$83:$AL$109, MATCH('Crude oil'!$A4, Sheet2!$E$83:$E$109, 0), MATCH('Crude oil'!D$1, Sheet2!$E$83:$AL$83, 0)) -> 2039.4 | E4: =INDEX(Sheet2!$E$83:$AL$109, MATCH('Crude oil'!$A4, Sheet2!$E$83:$E$109, 0), MATCH('Crude oil'!E$1, Sheet2!$E$83:$AL$83, 0)) -> 155.5 | F4: =INDEX(Sheet2!$E$83:$AL$109, MATCH('Crude oil'!$A4, Sheet2!$E$83:$E$109, 0), MATCH('Crude oil'!F$1, Sheet2!$E$83:$AL$83, 0)) -> 146.2 | G4: =INDEX(Sheet2!$E$83:$AL$109, MATCH('Crude oil'!$A4, Sheet2!$E$83:$E$109, 0), MATCH('Crude oil'!G$1, Sheet2!$E$83:$AL$83, 0)) -> 160.2 | H4: =INDEX(Sheet2!$E$83:$AL$109, MATCH('Crude oil'!$A4, Sheet2!$E$83:$E$109, 0), MATCH('Crude oil'!H$1, Sheet2!$E$83:$AL$83, 0)) -> 1583.2
A5: Apr-21 | B5: 63.4 | C5: =INDEX(Sheet2!$E$83:$AL$109, MATCH('Crude oil'!$A5, Sheet2!$E$83:$E$109, 0), MATCH('Crude oil'!C$1, Sheet2!$E$83:$AL$83, 0)) -> 157.8 | D5: =INDEX(Sheet2!$E$83:$AL$109, MATCH('Crude oil'!$A5, Sheet2!$E$83:$E$109, 0), MATCH('Crude oil'!D$1, Sheet2!$E$83:$AL$83, 0)) -> 2064.1 | E5: =INDEX(Sheet2!$E$83:$AL$109, MATCH('Crude oil'!$A5, Sheet2!$E$83:$E$109, 0), MATCH('Crude oil'!E$1, Sheet2!$E$83:$AL$83, 0)) -> 155.6 | F5: =INDEX(Sheet2!$E$83:$AL$109, MATCH('Crude oil'!$A5, Sheet2!$E$83:$E$109, 0), MATCH('Crude oil'!F$1, Sheet2!$E$83:$AL$83, 0)) -> 146.6 | G5: =INDEX(Sheet2!$E$83:$AL$109, MATCH('Crude oil'!$A5, Sheet2!$E$83:$E$109, 0), MATCH('Crude oil'!G$1, Sheet2!$E$83:$AL$83, 0)) -> 160.3 | H5: =INDEX(Sheet2!$E$83:$AL$109, MATCH('Crude oil'!$A5, Sheet2!$E$83:$E$109, 0), MATCH('Crude oil'!H$1, Sheet2!$E$83:$AL$83, 0)) -> 1591.9
A6: May-21 | B6: 66.95 | C6: =INDEX(Sheet2!$E$83:$AL$109, MATCH('Crude oil'!$A6, Sheet2!$E$83:$E$109, 0), MATCH('Crude oil'!C$1, Sheet2!$E$83:$AL$83, 0)) -> 160.4 | D6: =INDEX(Sheet2!$E$83:$AL$109, MATCH('Crude oil'!$A6, Sheet2!$E$83:$E$109, 0), MATCH('Crude oil'!D$1, Sheet2!$E$83:$AL$83, 0)) -> 2105.7 | E6: =INDEX(Sheet2!$E$83:$AL$109, MATCH('Crude oil'!$A6, Sheet2!$E$83:$E$109, 0), MATCH('Crude oil'!E$1, Sheet2!$E$83:$AL$83, 0)) -> 159.4 | F6: =INDEX(Sheet2!$E$83:$AL$109, MATCH('Crude oil'!$A6, Sheet2!$E$83:$E$109, 0), MATCH('Crude oil'!F$1, Sheet2!$E$83:$AL$83, 0)) -> 148.9 | G6: =INDEX(Sheet2!$E$83:$AL$109, MATCH('Crude oil'!$A6, Sheet2!$E$83:$E$109, 0), MATCH('Crude oil'!G$1, Sheet2!$E$83:$AL$83, 0)) -> 161.2 | H6: =INDEX(Sheet2!$E$83:$AL$109, MATCH('Crude oil'!$A6, Sheet2!$E$83:$E$109, 0), MATCH('Crude oil'!H$1, Sheet2!$E$83:$AL$83, 0)) -> 1619.5
A7: Jun-21 | B7: 71.98 | C7: =INDEX(Sheet2!$E$83:$AL$109, MATCH('Crude oil'!$A7, Sheet2!$E$83:$E$109, 0), MATCH('Crude oil'!C$1, Sheet2!$E$83:$AL$83, 0)) -> 161.3 | D7: =INDEX(Sheet2!$E$83:$AL$109, MATCH('Crude oil'!$A7, Sheet2!$E$83:$E$109, 0), MATCH('Crude oil'!D$1, Sheet2!$E$83:$AL$83, 0)) -> 2133.9 | E7: =INDEX(Sheet2!$E$83:$AL$109, MATCH('Crude oil'!$A7, Sheet2!$E$83:$E$109, 0), MATCH('Crude oil'!E$1, Sheet2!$E$83:$AL$83, 0)) -> 159.8 | F7: =INDEX(Sheet2!$E$83:$AL$109, MATCH('Crude oil'!$A7, Sheet2!$E$83:$E$109, 0), MATCH('Crude oil'!F$1, Sheet2!$E$83:$AL$83, 0)) -> 150.7 | G7: =INDEX(Sheet2!$E$83:$AL$109, MATCH('Crude oil'!$A7, Sheet2!$E$83:$E$109, 0), MATCH('Crude oil'!G$1, Sheet2!$E$83:$AL$83, 0)) -> 161.7 | H7: =INDEX(Sheet2!$E$83:$AL$109, MATCH('Crude oil'!$A7, Sheet2!$E$83:$E$109, 0), MATCH('Crude oil'!H$1, Sheet2!$E$83:$AL$83, 0)) -> 1618.4
A8: Jul-21 | B8: 73.54 | C8: =INDEX(Sheet2!$E$83:$AL$109, MATCH('Crude oil'!$A8, Sheet2!$E$83:$E$109, 0), MATCH('Crude oil'!C$1, Sheet2!$E$83:$AL$83, 0)) -> 162.5 | D8: =INDEX(Sheet2!$E$83:$AL$109, MATCH('Crude oil'!$A8, Sheet2!$E$83:$E$109, 0), MATCH('Crude oil'!D$1, Sheet2!$E$83:$AL$83, 0)) -> 2147 | E8: =INDEX(Sheet2!$E$83:$AL$109, MATCH('Crude oil'!$A8, Sheet2!$E$83:$E$109, 0), MATCH('Crude oil'!E$1, Sheet2!$E$83:$AL$83, 0)) -> 160.7 | F8: =INDEX(Sheet2!$E$83:$AL$109, MATCH('Crude oil'!$A8, Sheet2!$E$83:$E$109, 0), MATCH('Crude oil'!F$1, Sheet2!$E$83:$AL$83, 0)) -> 153.1 | G8: =INDEX(Sheet2!$E$83:$AL$109, MATCH('Crude oil'!$A8, Sheet2!$E$83:$E$109, 0), MATCH('Crude oil'!G$1, Sheet2!$E$83:$AL$83, 0)) -> 163.2 | H8: =INDEX(Sheet2!$E$83:$AL$109, MATCH('Crude oil'!$A8, Sheet2!$E$83:$E$109, 0), MATCH('Crude oil'!H$1, Sheet2!$E$83:$AL$83, 0)) -> 1627.2
A9: Aug-21 | B9: 69.8 | C9: =INDEX(Sheet2!$E$83:$AL$109, MATCH('Crude oil'!$A9, Sheet2!$E$83:$E$109, 0), MATCH('Crude oil'!C$1, Sheet2!$E$83:$AL$83, 0)) -> 163.2 | D9: =INDEX(Sheet2!$E$83:$AL$109, MATCH('Crude oil'!$A9, Sheet2!$E$83:$E$109, 0), MATCH('Crude oil'!D$1, Sheet2!$E$83:$AL$83, 0)) -> 2142 | E9: =INDEX(Sheet2!$E$83:$AL$109, MATCH('Crude oil'!$A9, Sheet2!$E$83:$E$109, 0), MATCH('Crude oil'!E$1, Sheet2!$E$83:$AL$83, 0)) -> 162.6 | F9: =INDEX(Sheet2!$E$83:$AL$109, MATCH('Crude oil'!$A9, Sheet2!$E$83:$E$109, 0), MATCH('Crude oil'!F$1, Sheet2!$E$83:$AL$83, 0)) -> 154 | G9: =INDEX(Sheet2!$E$83:$AL$109, MATCH('Crude oil'!$A9, Sheet2!$E$83:$E$109, 0), MATCH('Crude oil'!G$1, Sheet2!$E$83:$AL$83, 0)) -> 163.8 | H9: =INDEX(Sheet2!$E$83:$AL$109, MATCH('Crude oil'!$A9, Sheet2!$E$83:$E$109, 0), MATCH('Crude oil'!H$1, Sheet2!$E$83:$AL$83, 0)) -> 1640.7
A10: Sep-21 | B10: 73.13 | C10: =INDEX(Sheet2!$E$83:$AL$109, MATCH('Crude oil'!$A10, Sheet2!$E$83:$E$109, 0), MATCH('Crude oil'!C$1, Sheet2!$E$83:$AL$83, 0)) -> 163.2 | D10: =INDEX(Sheet2!$E$83:$AL$109, MATCH('Crude oil'!$A10, Sheet2!$E$83:$E$109, 0), MATCH('Crude oil'!D$1, Sheet2!$E$83:$AL$83, 0)) -> 2142 | E10: =INDEX(Sheet2!$E$83:$AL$109, MATCH('Crude oil'!$A10, Sheet2!$E$83:$E$109, 0), MATCH('Crude oil'!E$1, Sheet2!$E$83:$AL$83, 0)) -> 162.6 | F10: =INDEX(Sheet2!$E$83:$AL$109, MATCH('Crude oil'!$A10, Sheet2!$E$83:$E$109, 0), MATCH('Crude oil'!F$1, Sheet2!$E$83:$AL$83, 0)) -> 154 | G10: =INDEX(Sheet2!$E$83:$AL$109, MATCH('Crude oil'!$A10, Sheet2!$E$83:$E$109, 0), MATCH('Crude oil'!G$1, Sheet2!$E$83:$AL$83, 0)) -> 163.7 | H10: =INDEX(Sheet2!$E$83:$AL$109, MATCH('Crude oil'!$A10, Sheet2!$E$83:$E$109, 0), MATCH('Crude oil'!H$1, Sheet2!$E$83:$AL$83, 0)) -> 1641
A11: Oct-21 | B11: 82.11 | C11: =INDEX(Sheet2!$E$83:$AL$109, MATCH('Crude oil'!$A11, Sheet2!$E$83:$E$109, 0), MATCH('Crude oil'!C$1, Sheet2!$E$83:$AL$83, 0)) -> 165.5 | D11: =INDEX(Sheet2!$E$83:$AL$109, MATCH('Crude oil'!$A11, Sheet2!$E$83:$E$109, 0), MATCH('Crude oil'!D$1, Sheet2!$E$83:$AL$83, 0)) -> 2175.5 | E11: =INDEX(Sheet2!$E$83:$AL$109, MATCH('Crude oil'!$A11, Sheet2!$E$83:$E$109, 0), MATCH('Crude oil'!E$1, Sheet2!$E$83:$AL$83, 0)) -> 164.2 | F11: =INDEX(Sheet2!$E$83:$AL$109, MATCH('Crude oil'!$A11, Sheet2!$E$83:$E$109, 0), MATCH('Crude oil'!F$1, Sheet2!$E$83:$AL$83, 0)) -> 155.7 | G11: =INDEX(Sheet2!$E$83:$AL$109, MATCH('Crude oil'!$A11, Sheet2!$E$83:$E$109, 0), MATCH('Crude oil'!G$1, Sheet2!$E$83:$AL$83, 0)) -> 163.9 | H11: =INDEX(Sheet2!$E$83:$AL$109, MATCH('Crude oil'!$A11, Sheet2!$E$83:$E$109, 0), MATCH('Crude oil'!H$1, Sheet2!$E$83:$AL$83, 0)) -> 1650.5
A12: Nov-21 | B12: 80.64 | C12: =INDEX(Sheet2!$E$83:$AL$109, MATCH('Crude oil'!$A12, Sheet2!$E$83:$E$109, 0), MATCH('Crude oil'!C$1, Sheet2!$E$83:$AL$83, 0)) -> 166.7 | D12: =INDEX(Sheet2!$E$83:$AL$109, MATCH('Crude oil'!$A12, Sheet2!$E$83:$E$109, 0), MATCH('Crude oil'!D$1, Sheet2!$E$83:$AL$83, 0)) -> 2194.1 | E12: =INDEX(Sheet2!$E$83:$AL$109, MATCH('Crude oil'!$A12, Sheet2!$E$83:$E$109, 0), MATCH('Crude oil'!E$1, Sheet2!$E$83:$AL$83, 0)) -> 163.9 | F12: =INDEX(Sheet2!$E$83:$AL$109, MATCH('Crude oil'!$A12, Sheet2!$E$83:$E$109, 0), MATCH('Crude oil'!F$1, Sheet2!$E$83:$AL$83, 0)) -> 154.8 | G12: =INDEX(Sheet2!$E$83:$AL$109, MATCH('Crude oil'!$A12, Sheet2!$E$83:$E$109, 0), MATCH('Crude oil'!G$1, Sheet2!$E$83:$AL$83, 0)) -> 164.3 | H12: =INDEX(Sheet2!$E$83:$AL$109, MATCH('Crude oil'!$A12, Sheet2!$E$83:$E$109, 0), MATCH('Crude oil'!H$1, Sheet2!$E$83:$AL$83, 0)) -> 1660.1
A13: Dec-21 | B13: 73.3 | C13: =INDEX(Sheet2!$E$83:$AL$109, MATCH('Crude oil'!$A13, Sheet2!$E$83:$E$109, 0), MATCH('Crude oil'!C$1, Sheet2!$E$83:$AL$83, 0)) -> 166.2 | D13: =INDEX(Sheet2!$E$83:$AL$109, MATCH('Crude oil'!$A13, Sheet2!$E$83:$E$109, 0), MATCH('Crude oil'!D$1, Sheet2!$E$83:$AL$83, 0)) -> 2180.9 | E13: =INDEX(Sheet2!$E$83:$AL$109, MATCH('Crude oil'!$A13, Sheet2!$E$83:$E$109, 0), MATCH('Crude oil'!E$1, Sheet2!$E$83:$AL$83, 0)) -> 164.1 | F13: =INDEX(Sheet2!$E$83:$AL$109, MATCH('Crude oil'!$A13, Sheet2!$E$83:$E$109, 0), MATCH('Crude oil'!F$1, Sheet2!$E$83:$AL$83, 0)) -> 155.7 | G13: =INDEX(Sheet2!$E$83:$AL$109, MATCH('Crude oil'!$A13, Sheet2!$E$83:$E$109, 0), MATCH('Crude oil'!G$1, Sheet2!$E$83:$AL$83, 0)) -> 164.4 | H13: =INDEX(Sheet2!$E$83:$AL$109, MATCH('Crude oil'!$A13, Sheet2!$E$83:$E$109, 0), MATCH('Crude oil'!H$1, Sheet2!$E$83:$AL$83, 0)) -> 1666
... A27: Feb-23 | B27: 82.28 | C27: =INDEX(Sheet2!$E$83:$AL$109, MATCH('Crude oil'!$A27, Sheet2!$E$83:$E$109, 0), MATCH('Crude oil'!C$1, Sheet2!$E$83:$AL$83, 0)) -> 177.2 | D27: =INDEX(Sheet2!$E$83:$AL$109, MATCH('Crude oil'!$A27, Sheet2!$E$83:$E$109, 0), MATCH('Crude oil'!D$1, Sheet2!$E$83:$AL$83, 0)) -> 2279.1 | E27: =INDEX(Sheet2!$E$83:$AL$109, MATCH('Crude oil'!$A27, Sheet2!$E$83:$E$109, 0), MATCH('Crude oil'!E$1, Sheet2!$E$83:$AL$83, 0)) -> 182.1 | F27: =INDEX(Sheet2!$E$83:$AL$109, MATCH('Crude oil'!$A27, Sheet2!$E$83:$E$109, 0), MATCH('Crude oil'!F$1, Sheet2!$E$83:$AL$83, 0)) -> 164.2 | G27: =INDEX(Sheet2!$E$83:$AL$109, MATCH('Crude oil'!$A27, Sheet2!$E$83:$E$109, 0), MATCH('Crude oil'!G$1, Sheet2!$E$83:$AL$83, 0)) -> 175 | H27: =INDEX(Sheet2!$E$83:$AL$109, MATCH('Crude oil'!$A27, Sheet2!$E$83:$E$109, 0), MATCH('Crude oil'!H$1, Sheet2!$E$83:$AL$83, 0)) -> 1807

Sheet Sheet1
A1: Cereals and products | D1: Food:
A2: Meat and fish
A3: Egg | D3: Cereals and products
A4: Milk and products | D4: Meat and fish
A5: Oils and fats | D5: Egg
A6: Fruits | D6: Milk and products
A7: Vegetables | D7: Oils and fats
A8: Pulses and products | D8: Fruits
A9: Sugar and Confectionery | D9: Vegetables
A10: Spices | D10: Pulses and products
A11: Non-alcoholic beverages | D11: Sugar and Confectionery
A12: Prepared meals, snacks, sweets etc. | D12: Spices
A13: Food and beverages | D13: Non-alcoholic beverages
A14: Pan, tobacco and intoxicants | D14: Prepared meals, snacks, sweets etc.
A15: Clothing | D15: Food and beverages
A16: Footwear
A17: Clothing and footwear | D17: Energy:
A18: Housing
A19: Fuel and light | D19: Fuel and light
A20: Household goods and services
A21: Health | D21: Transportation:
A22: Transport and communication
A23: Recreation and amusement | D23: Transport (from "Transport and communication," only the transport part)
A24: Education
A25: Personal care and effects | D25: Other:
A26: Miscellaneous
D27: Pan, tobacco and intoxicants
D28: Clothing
D29: Footwear
D30: Clothing and footwear
D31: Housing
D32: Household goods and services
D33: Health
D34: Recreation and amusement
D35: Education
D36: Personal care and effects
D37: Miscellaneous
B64: Data Analysis Tasks: | D64: To analyze year-on-year (Y-o-Y) CPI growth since 2017 and find the year with the highest inflation, follow these steps:
B66: Find which category (e.g., food or energy) contributed most to inflation in the latest month. | D66: 1. Collect Data:
B67: Analyze year-on-year CPI growth since 2017 and identify the year with the highest inflation (e.g., 2020 due to COVID-19).
B68: Examine food price trends over the last 12 months, find the month with the highest food inflation, and the biggest contributor (e.g., vegetables). | D68: Gather monthly or yearly CPI values for each year from 2017 onwards (for both rural and urban, or the General Index).
B69: Study the impact of COVID-19 and global events (like oil price changes) on inflation. | D69: 2. Calculate Annual Inflation Rate:
B70: Example Calculation:
D71: Use the formula:
B72: If CPI for food in Jan is 120 and in Feb is 126: | D72: Annual Inflation Rate = ((CPI at end of year – CPI at start of year) / CPI at start of year) × 100
B73: Monthly inflation = (126-120)/120 × 100 = 5% | D73: Example: If CPI in Jan 2017 = 100 and Dec 2017 = 105,
D74: Inflation Rate = ((105-100)/100) × 100 = 5%
D75: 3. Repeat for Each Year:
D77: Do this calculation for 2017, 2018, 2019, 2020, 2021, 2022, and 2023.
D78: 4. Compare Results:
D80: List the annual inflation rates for each year.
D81: Identify the year with the highest value.
D82: 5. Interpretation:
D84: For example, if 2020 shows the highest inflation, it’s likely due to COVID-19 disruptions (supply chain issues, increased demand for essentials, etc.).
D86: Example Table:
D87: Year | E87: CPI Start | F87: CPI End | G87: Inflation Rate (%)
D88: 2017 | E88: 100 | F88: 105 | G88: 5
D89: 2018 | E89: 105 | F89: 110 | G89: 4.76
D90: 2019 | E90: 110 | F90: 115 | G90: 4.54
D91: 2020 | E91: 115 | F91: 125 | G91: 8.7
D92: 2021 | E92: 125 | F92: 130 | G92: 4
D93: Tip: Use Excel to automate calculations and plot a line graph for visual analysis. Let me know if you need help with Excel formulas or graph creation!

Sheet Sheet3
A1: Sector | B1: Year | C1: Month | D1: Cereals and products | E1: Meat and fish | F1: Egg | G1: Milk and products | H1: Oils and fats | I1: Fruits | J1: Vegetables | K1: Pulses and products | L1: Sugar and Confectionery | M1: Spices | N1: Non-alcoholic beverages | O1: Prepared meals, snacks, sweets etc. | P1: Food and beverages | Q1: Pan, tobacco and intoxicants | R1: Clothing | S1: Footwear | T1: Clothing and footwear | U1: Housing | V1: Fuel and light | W1: Household goods and services | X1: Health | Y1: Transport and communication | Z1: Recreation and amusement | AA1: Education | AB1: Personal care and effects | AC1: Miscellaneous | AD1: General index | AE1: Food | AF1: Energy | AG1: Transportation | AH1: Education | AI1: Others
A2: Rural | B2: 2023 | C2: January | D2: 174 | E2: 208.3 | F2: 192.9 | G2: 174.3 | H2: 192.6 | I2: 156.3 | J2: 142.9 | K2: 170.7 | L2: 120.3 | M2: 210.5 | N2: 176.9 | O2: 188.5 | P2: 175 | Q2: 196.9 | R2: 189 | S2: 186.3 | T2: 188.6 | U2: 172.1 | V2: 183.2 | W2: 177.2 | X2: 184.7 | Y2: 168.2 | Z2: 171.8 | AA2: 177.8 | AB2: 178.4 | AC2: 176.5 | AD2: 177.8 | AE2: 2283.2 | AF2: 183.2 | AG2: 168.2 | AH2: 177.8 | AI2: 1821.5
A3: Urban | B3: 2023 | C3: January | D3: 173.3 | E3: 215.2 | F3: 197 | G3: 175.2 | H3: 178 | I3: 160.5 | J3: 175.3 | K3: 171.2 | L3: 122.7 | M3: 204.3 | N3: 163.7 | O3: 194.3 | P3: 179.5 | Q3: 201.6 | R3: 178.7 | S3: 165.3 | T3: 176.6 | U3: 172.1 | V3: 180.1 | W3: 168 | X3: 178.5 | Y3: 159.5 | Z3: 167.8 | AA3: 171.8 | AB3: 178.8 | AC3: 168.9 | AD3: 174.9 | AE3: 2310.2 | AF3: 180.1 | AG3: 159.5 | AH3: 171.8 | AI3: 1756.3
A4: Rural+Urban | B4: 2023 | C4: January | D4: 173.8 | E4: 210.7 | F4: 194.5 | G4: 174.6 | H4: 187.2 | I4: 158.3 | J4: 153.9 | K4: 170.9 | L4: 121.1 | M4: 208.4 | N4: 171.4 | O4: 191.2 | P4: 176.7 | Q4: 198.2 | R4: 184.9 | S4: 177.6 | T4: 183.8 | U4: 172.1 | V4: 182 | W4: 172.9 | X4: 182.3 | Y4: 163.6 | Z4: 169.5 | AA4: 174.3 | AB4: 178.6 | AC4: 172.8 | AD4: 176.5 | AE4: 2292.7 | AF4: 182 | AG4: 163.6 | AH4: 174.3 | AI4: 1792.7
A5: Rural | B5: 2023 | C5: February | D5: 174.2 | E5: 205.2 | F5: 173.9 | G5: 177 | H5: 183.4 | I5: 167.2 | J5: 140.9 | K5: 170.4 | L5: 119.1 | M5: 212.1 | N5: 177.6 | O5: 189.9 | P5: 174.8 | Q5: 198.3 | R5: 190 | S5: 187 | T5: 189.6 | U5: 173.5 | V5: 181.6 | W5: 178.6 | X5: 186.6 | Y5: 169 | Z5: 172.8 | AA5: 178.5 | AB5: 180.7 | AC5: 177.9 | AD5: 178 | AE5: 2265.7 | AF5: 181.6 | AG5: 169 | AH5: 178.5 | AI5: 1835
A6: Urban | B6: 2023 | C6: February | D6: 174.7 | E6: 212.2 | F6: 177.2 | G6: 177.9 | H6: 172.2 | I6: 172.1 | J6: 175.8 | K6: 172.2 | L6: 121.9 | M6: 204.8 | N6: 164.9 | O6: 196.6 | P6: 180.7 | Q6: 202.7 | R6: 180.3 | S6: 167 | T6: 178.2 | U6: 173.5 | V6: 182.8 | W6: 169.2 | X6: 180.8 | Y6: 159.8 | Z6: 168.4 | AA6: 172.5 | AB6: 181.4 | AC6: 170 | AD6: 176.3 | AE6: 2303.2 | AF6: 182.8 | AG6: 159.8 | AH6: 172.5 | AI6: 1771.5
A7: Rural+Urban | B7: 2023 | C7: February | D7: 174.4 | E7: 207.7 | F7: 175.2 | G7: 177.3 | H7: 179.3 | I7: 169.5 | J7: 152.7 | K7: 171 | L7: 120 | M7: 209.7 | N7: 172.3 | O7: 193 | P7: 177 | Q7: 199.5 | R7: 186.2 | S7: 178.7 | T7: 185.1 | U7: 173.5 | V7: 182.1 | W7: 174.2 | X7: 184.4 | Y7: 164.2 | Z7: 170.3 | AA7: 175 | AB7: 181 | AC7: 174.1 | AD7: 177.2 | AE7: 2279.1 | AF7: 182.1 | AG7: 164.2 | AH7: 175 | AI7: 1807
A8: Rural | B8: 2023 | C8: March | D8: 174.3 | E8: 205.2 | F8: 173.9 | G8: 177 | H8: 183.3 | I8: 167.2 | J8: 140.9 | K8: 170.5 | L8: 119.1 | M8: 212.1 | N8: 177.6 | O8: 189.9 | P8: 174.8 | Q8: 198.4 | R8: 190 | S8: 187 | T8: 189.6 | U8: 173.5 | V8: 181.4 | W8: 178.6 | X8: 186.6 | Y8: 169 | Z8: 172.8 | AA8: 178.5 | AB8: 180.7 | AC8: 177.9 | AD8: 178 | AE8: 2265.8 | AF8: 181.4 | AG8: 169 | AH8: 178.5 | AI8: 1835.1
A9: Urban | B9: 2023 | C9: March | D9: 174.7 | E9: 212.2 | F9: 177.2 | G9: 177.9 | H9: 172.2 | I9: 172.1 | J9: 175.9 | K9: 172.2 | L9: 121.9 | M9: 204.8 | N9: 164.9 | O9: 196.6 | P9: 180.8 | Q9: 202.7 | R9: 180.2 | S9: 167 | T9: 178.2 | U9: 173.5 | V9: 182.6 | W9: 169.2 | X9: 180.8 | Y9: 159.8 | Z9: 168.4 | AA9: 172.5 | AB9: 181.5 | AC9: 170 | AD9: 176.3 | AE9: 2303.4 | AF9: 182.6 | AG9: 159.8 | AH9: 172.5 | AI9: 1771.5
A10: Rural+Urban | B10: 2023 | C10: March | D10: 174.4 | E10: 207.7 | F10: 175.2 | G10: 177.3 | H10: 179.2 | I10: 169.5 | J10: 152.8 | K10: 171.1 | L10: 120 | M10: 209.7 | N10: 172.3 | O10: 193 | P10: 177 | Q10: 199.5 | R10: 186.1 | S10: 178.7 | T10: 185.1 | U10: 173.5 | V10: 181.9 | W10: 174.2 | X10: 184.4 | Y10: 164.2 | Z10: 170.3 | AA10: 175 | AB10: 181 | AC10: 174.1 | AD10: 177.2 | AE10: 2279.2 | AF10: 181.9 | AG10: 164.2 | AH10: 175 | AI10: 1806.9
A11: Rural | B11: 2023 | C11: April | D11: 173.3 | E11: 206.9 | F11: 167.9 | G11: 178.2 | H11: 178.5 | I11: 173.7 | J11: 142.8 | K11: 172.8 | L11: 120.4 | M11: 215.5 | N11: 178.2 | O11: 190.5 | P11: 175.5 | Q11: 199.5 | R11: 190.7 | S11: 187.3 | T11: 190.2 | U11: 175.2 | V11: 181.5 | W11: 179.1 | X11: 187.2 | Y11: 169.4 | Z11: 173.2 | AA11: 179.4 | AB11: 183.8 | AC11: 178.9 | AD11: 178.8 | AE11: 2274.2 | AF11: 181.5 | AG11: 169.4 | AH11: 179.4 | AI11: 1845.1
A12: Urban | B12: 2023 | C12: April | D12: 174.8 | E12: 213.7 | F12: 172.4 | G12: 178.8 | H12: 168.7 | I12: 179.2 | J12: 179.9 | K12: 174.7 | L12: 123.1 | M12: 207.8 | N12: 165.5 | O12: 197 | P12: 182.1 | Q12: 203.5 | R12: 181 | S12: 167.7 | T12: 178.9 | U12: 175.2 | V12: 182.1 | W12: 169.6 | X12: 181.5 | Y12: 160.1 | Z12: 168.8 | AA12: 174.2 | AB12: 184.4 | AC12: 170.9 | AD12: 177.4 | AE12: 2317.7 | AF12: 182.1 | AG12: 160.1 | AH12: 174.2 | AI12: 1781.5
A13: Rural+Urban | B13: 2023 | C13: April | D13: 173.8 | E13: 209.3 | F13: 169.6 | G13: 178.4 | H13: 174.9 | I13: 176.3 | J13: 155.4 | K13: 173.4 | L13: 121.3 | M13: 212.9 | N13: 172.9 | O13: 193.5 | P13: 177.9 | Q13: 200.6 | R13: 186.9 | S13: 179.2 | T13: 185.7 | U13: 175.2 | V13: 181.7 | W13: 174.6 | X13: 185 | Y13: 164.5 | Z13: 170.7 | AA13: 176.4 | AB13: 184 | AC13: 175 | AD13: 178.1 | AE13: 2289.6 | AF13: 181.7 | AG13: 164.5 | AH13: 176.4 | AI13: 1816.9
... A16: Rural+Urban | B16: 2023 | C16: May | D16: 173.7 | E16: 214.3 | F16: 173.2 | G16: 179.5 | H16: 170 | I16: 172.2 | J16: 161 | K16: 175.6 | L16: 122.7 | M16: 218 | N16: 173.4 | O16: 194.2 | P16: 179.1 | Q16: 201 | R16: 187.3 | S16: 179.7 | T16: 186.2 | U16: 175.6 | V16: 182.8 | W16: 175.2 | X16: 185.7 | Y16: 164.8 | Z16: 171.2 | AA16: 177.1 | AB16: 185.2 | AC16: 175.7 | AD16: 179.1 | AE16: 2306.9 | AF16: 182.8 | AG16: 164.8 | AH16: 177.1 | AI16: 1822.8

Sheet Problem Statement 1
B1: 2023
A2: Category | B2: January | C2: February | D2: March | E2: April | F2: May | G2: Total | H2: Percentage
A3: Food | B3: =SUMIFS(Sheet3!$AE$2:$AE$16,Sheet3!$C$2:$C$16,B$2) -> 6886.1 | C3: =SUMIFS(Sheet3!$AE$2:$AE$16,Sheet3!$C$2:$C$16,C$2) -> 6848 | D3: =SUMIFS(Sheet3!$AE$2:$AE$16,Sheet3!$C$2:$C$16,D$2) -> 6848.4 | E3: =SUMIFS(Sheet3!$AE$2:$AE$16,Sheet3!$C$2:$C$16,E$2) -> 6881.5 | F3: =SUMIFS(Sheet3!$AE$2:$AE$16,Sheet3!$C$2:$C$16,F$2) -> 6932.7 | G3: =SUM(B3:F3) -> 34396.7 | H3: =(G3/$G$8) -> 0.49609504
A4: Energy | B4: =SUMIFS(Sheet3!$AF$2:$AF$16,Sheet3!$C$2:$C$16,B$2) -> 545.3 | C4: =SUMIFS(Sheet3!$AF$2:$AF$16,Sheet3!$C$2:$C$16,C$2) -> 546.5 | D4: =SUMIFS(Sheet3!$AF$2:$AF$16,Sheet3!$C$2:$C$16,D$2) -> 545.9 | E4: =SUMIFS(Sheet3!$AF$2:$AF$16,Sheet3!$C$2:$C$16,E$2) -> 545.3 | F4: =SUMIFS(Sheet3!$AF$2:$AF$16,Sheet3!$C$2:$C$16,F$2) -> 548.7 | G4: =SUM(B4:F4) -> 2731.7 | H4: =(G4/$G$8) -> 0.039398629
A5: Transportation | B5: =SUMIFS(Sheet3!$AG$2:$AG$16,Sheet3!$C$2:$C$16,B$2) -> 491.3 | C5: =SUMIFS(Sheet3!$AG$2:$AG$16,Sheet3!$C$2:$C$16,C$2) -> 493 | D5: =SUMIFS(Sheet3!$AG$2:$AG$16,Sheet3!$C$2:$C$16,D$2) -> 493 | E5: =SUMIFS(Sheet3!$AG$2:$AG$16,Sheet3!$C$2:$C$16,E$2) -> 494 | F5: =SUMIFS(Sheet3!$AG$2:$AG$16,Sheet3!$C$2:$C$16,F$2) -> 494.9 | G5: =SUM(B5:F5) -> 2466.2 | H5: =(G5/$G$8) -> 0.035569389
A6: Education | B6: =SUMIFS(Sheet3!$AH$2:$AH$16,Sheet3!$C$2:$C$16,B$2) -> 523.9 | C6: =SUMIFS(Sheet3!$AH$2:$AH$16,Sheet3!$C$2:$C$16,C$2) -> 526 | D6: =SUMIFS(Sheet3!$AH$2:$AH$16,Sheet3!$C$2:$C$16,D$2) -> 526 | E6: =SUMIFS(Sheet3!$AH$2:$AH$16,Sheet3!$C$2:$C$16,E$2) -> 530 | F6: =SUMIFS(Sheet3!$AH$2:$AH$16,Sheet3!$C$2:$C$16,F$2) -> 532.2 | G6: =SUM(B6:F6) -> 2638.1 | H6: =(G6/$G$8) -> 0.038048659
A7: Others | B7: =SUMIFS(Sheet3!$AI$2:$AI$16,Sheet3!$C$2:$C$16,B$2) -> 5370.5 | C7: =SUMIFS(Sheet3!$AI$2:$AI$16,Sheet3!$C$2:$C$16,C$2) -> 5413.5 | D7: =SUMIFS(Sheet3!$AI$2:$AI$16,Sheet3!$C$2:$C$16,D$2) -> 5413.5 | E7: =SUMIFS(Sheet3!$AI$2:$AI$16,Sheet3!$C$2:$C$16,E$2) -> 5443.5 | F7: =SUMIFS(Sheet3!$AI$2:$AI$16,Sheet3!$C$2:$C$16,F$2) -> 5461.2 | G7: =SUM(B7:F7) -> 27102.2 | H7: =(G7/$G$8) -> 0.39088828
A8: Total | B8: =SUM(B3:B7) -> 13817.1 | C8: =SUM(C3:C7) -> 13827 | D8: =SUM(D3:D7) -> 13826.8 | E8: =SUM(E3:E7) -> 13894.3 | F8: =SUM(F3:F7) -> 13969.7 | G8: =SUM(B8:F8) -> 69334.9 | H8: =(G8/$G$8) -> 1
B11: Insight 1
B12: “In May, Food contributed 50% to the CPI basket, making it the highest contributor, followed by Others (39%). This indicates that food prices have the largest impact on overall inflation.”

Sheet Problem Statement 2
E2: January | F2: December | I2: Food | K2: January | L2: December | O2: Energy | Q2: January | R2: December
D3: Year | E3: CPI Start | F3: CPI End | G3: Inflation Rate (%) | I3: Category | J3: Year | K3: CPI Start | L3: CPI End | M3: Inflation Rate (%) | O3: Category | P3: Year | Q3: CPI Start | R3: CPI End | S3: Inflation Rate (%)
D4: 2017 | E4: =AVERAGEIFS('Main Data'!$AG:$AG, 'Main Data'!$C:$C, 'Problem Statement 2'!$D4, 'Main Data'!$D:$D, 'Problem Statement 2'!E$2,'Main Data'!$A:$A,"Rural+Urban") -> 130.3 | F4: =AVERAGEIFS('Main Data'!$AG:$AG, 'Main Data'!$C:$C, 'Problem Statement 2'!$D4, 'Main Data'!$D:$D, 'Problem Statement 2'!F$2,'Main Data'!$A:$A,"Rural+Urban") -> 137.2 | G4: =(F4-E4)/E4 -> 0.05295472 | I4: Food | J4: 2017 | K4: =AVERAGEIFS('Main Data'!$AH:$AH, 'Main Data'!$C:$C, 'Problem Statement 2'!$J4, 'Main Data'!$D:$D, 'Problem Statement 2'!K$2) -> 1725.9333 | L4: =AVERAGEIFS('Main Data'!$AH:$AH, 'Main Data'!$C:$C, 'Problem Statement 2'!$J4, 'Main Data'!$D:$D, 'Problem Statement 2'!L$2) -> 1792.0333 | M4: =(L4-K4)/K4 -> 0.038298119 | O4: Energy | P4: 2017 | Q4: =AVERAGEIFS('Main Data'!$AI:$AI, 'Main Data'!$C:$C, 'Problem Statement 2'!$P4, 'Main Data'!$D:$D, 'Problem Statement 2'!Q$2) -> 125.63333 | R4: =AVERAGEIFS('Main Data'!$AI:$AI, 'Main Data'!$C:$C, 'Problem Statement 2'!$P4, 'Main Data'!$D:$D, 'Problem Statement 2'!R$2) -> 135.33333 | S4: =(R4-Q4)/Q4 -> 0.077208809
D5: 2018 | E5: =AVERAGEIFS('Main Data'!$AG:$AG, 'Main Data'!$C:$C, 'Problem Statement 2'!$D5, 'Main Data'!$D:$D, 'Problem Statement 2'!E$2,'Main Data'!$A:$A,"Rural+Urban") -> 136.9 | F5: =AVERAGEIFS('Main Data'!$AG:$AG, 'Main Data'!$C:$C, 'Problem Statement 2'!$D5, 'Main Data'!$D:$D, 'Problem Statement 2'!F$2,'Main Data'!$A:$A,"Rural+Urban") -> 140.1 | G5: =(F5-E5)/E5 -> 0.023374726 | I5: Food | J5: 2018 | K5: =AVERAGEIFS('Main Data'!$AH:$AH, 'Main Data'!$C:$C, 'Problem Statement 2'!$J5, 'Main Data'!$D:$D, 'Problem Statement 2'!K$2) -> 1776.3 | L5: =AVERAGEIFS('Main Data'!$AH:$AH, 'Main Data'!$C:$C, 'Problem Statement 2'!$J5, 'Main Data'!$D:$D, 'Problem Statement 2'!L$2) -> 1760.8333 | M5: =(L5-K5)/K5 -> -0.0087072379 | O5: Energy | P5: 2018 | Q5: =AVERAGEIFS('Main Data'!$AI:$AI, 'Main Data'!$C:$C, 'Problem Statement 2'!$P5, 'Main Data'!$D:$D, 'Problem Statement 2'!Q$2) -> 135.4 | R5: =AVERAGEIFS('Main Data'!$AI:$AI, 'Main Data'!$C:$C, 'Problem Statement 2'!$P5, 'Main Data'!$D:$D, 'Problem Statement 2'!R$2) -> 141.36667 | S5: =(R5-Q5)/Q5 -> 0.044066962
D6: 2019 | E6: =AVERAGEIFS('Main Data'!$AG:$AG, 'Main Data'!$C:$C, 'Problem Statement 2'!$D6, 'Main Data'!$D:$D, 'Problem Statement 2'!E$2,'Main Data'!$A:$A,"Rural+Urban") -> 139.6 | F6: =AVERAGEIFS('Main Data'!$AG:$AG, 'Main Data'!$C:$C, 'Problem Statement 2'!$D6, 'Main Data'!$D:$D, 'Problem Statement 2'!F$2,'Main Data'!$A:$A,"Rural+Urban") -> 150.4 | G6: =(F6-E6)/E6 -> 0.077363897 | I6: Food | J6: 2019 | K6: =AVERAGEIFS('Main Data'!$AH:$AH, 'Main Data'!$C:$C, 'Problem Statement 2'!$J6, 'Main Data'!$D:$D, 'Problem Statement 2'!K$2) -> 1752.4333 | L6: =AVERAGEIFS('Main Data'!$AH:$AH, 'Main Data'!$C:$C, 'Problem Statement 2'!$J6, 'Main Data'!$D:$D, 'Problem Statement 2'!L$2) -> 1947.9333 | M6: =(L6-K6)/K6 -> 0.11155917 | O6: Energy | P6: 2019 | Q6: =AVERAGEIFS('Main Data'!$AI:$AI, 'Main Data'!$C:$C, 'Problem Statement 2'!$P6, 'Main Data'!$D:$D, 'Problem Statement 2'!Q$2) -> 138.1 | R6: =AVERAGEIFS('Main Data'!$AI:$AI, 'Main Data'!$C:$C, 'Problem Statement 2'!$P6, 'Main Data'!$D:$D, 'Problem Statement 2'!R$2) -> 142.4 | S6: =(R6-Q6)/Q6 -> 0.031136857
D7: 2020 | E7: =AVERAGEIFS('Main Data'!$AG:$AG, 'Main Data'!$C:$C, 'Problem Statement 2'!$D7, 'Main Data'!$D:$D, 'Problem Statement 2'!E$2,'Main Data'!$A:$A,"Rural+Urban") -> 150.2 | F7: =AVERAGEIFS('Main Data'!$AG:$AG, 'Main Data'!$C:$C, 'Problem Statement 2'!$D7, 'Main Data'!$D:$D, 'Problem Statement 2'!F$2,'Main Data'!$A:$A,"Rural+Urban") -> 158.9 | G7: =(F7-E7)/E7 -> 0.05792277 | I7: Food | J7: 2020 | K7: =AVERAGEIFS('Main Data'!$AH:$AH, 'Main Data'!$C:$C, 'Problem Statement 2'!$J7, 'Main Data'!$D:$D, 'Problem Statement 2'!K$2) -> 1941.4667 | L7: =AVERAGEIFS('Main Data'!$AH:$AH, 'Main Data'!$C:$C, 'Problem Statement 2'!$J7, 'Main Data'!$D:$D, 'Problem Statement 2'!L$2) -> 2111.6667 | M7: =(L7-K7)/K7 -> 0.087665682 | O7: Energy | P7: 2020 | Q7: =AVERAGEIFS('Main Data'!$AI:$AI, 'Main Data'!$C:$C, 'Problem Statement 2'!$P7, 'Main Data'!$D:$D, 'Problem Statement 2'!Q$2) -> 143.36667 | R7: =AVERAGEIFS('Main Data'!$AI:$AI, 'Main Data'!$C:$C, 'Problem Statement 2'!$P7, 'Main Data'!$D:$D, 'Problem Statement 2'!R$2) -> 143.73333 | S7: =(R7-Q7)/Q7 -> 0.0025575448
D8: 2021 | E8: =AVERAGEIFS('Main Data'!$AG:$AG, 'Main Data'!$C:$C, 'Problem Statement 2'!$D8, 'Main Data'!$D:$D, 'Problem Statement 2'!E$2,'Main Data'!$A:$A,"Rural+Urban") -> 157.3 | F8: =AVERAGEIFS('Main Data'!$AG:$AG, 'Main Data'!$C:$C, 'Problem Statement 2'!$D8, 'Main Data'!$D:$D, 'Problem Statement 2'!F$2,'Main Data'!$A:$A,"Rural+Urban") -> 166.2 | G8: =(F8-E8)/E8 -> 0.056579784 | I8: Food | J8: 2021 | K8: =AVERAGEIFS('Main Data'!$AH:$AH, 'Main Data'!$C:$C, 'Problem Statement 2'!$J8, 'Main Data'!$D:$D, 'Problem Statement 2'!K$2) -> 2079.7333 | L8: =AVERAGEIFS('Main Data'!$AH:$AH, 'Main Data'!$C:$C, 'Problem Statement 2'!$J8, 'Main Data'!$D:$D, 'Problem Statement 2'!L$2) -> 2185.1333 | M8: =(L8-K8)/K8 -> 0.050679574 | O8: Energy | P8: 2021 | Q8: =AVERAGEIFS('Main Data'!$AI:$AI, 'Main Data'!$C:$C, 'Problem Statement 2'!$P8, 'Main Data'!$D:$D, 'Problem Statement 2'!Q$2) -> 147.23333 | R8: =AVERAGEIFS('Main Data'!$AI:$AI, 'Main Data'!$C:$C, 'Problem Statement 2'!$P8, 'Main Data'!$D:$D, 'Problem Statement 2'!R$2) -> 163.8 | S8: =(R8-Q8)/Q8 -> 0.11251981
D9: 2022 | E9: =AVERAGEIFS('Main Data'!$AG:$AG, 'Main Data'!$C:$C, 'Problem Statement 2'!$D9, 'Main Data'!$D:$D, 'Problem Statement 2'!E$2,'Main Data'!$A:$A,"Rural+Urban") -> 165.7 | F9: =AVERAGEIFS('Main Data'!$AG:$AG, 'Main Data'!$C:$C, 'Problem Statement 2'!$D9, 'Main Data'!$D:$D, 'Problem Statement 2'!F$2,'Main Data'!$A:$A,"Rural+Urban") -> 175.7 | G9: =(F9-E9)/E9 -> 0.06035003 | I9: Food | J9: 2022 | K9: =AVERAGEIFS('Main Data'!$AH:$AH, 'Main Data'!$C:$C, 'Problem Statement 2'!$J9, 'Main Data'!$D:$D, 'Problem Statement 2'!K$2) -> 2167.9667 | L9: =AVERAGEIFS('Main Data'!$AH:$AH, 'Main Data'!$C:$C, 'Problem Statement 2'!$J9, 'Main Data'!$D:$D, 'Problem Statement 2'!L$2) -> 2285.4333 | M9: =(L9-K9)/K9 -> 0.054182875 | O9: Energy | P9: 2022 | Q9: =AVERAGEIFS('Main Data'!$AI:$AI, 'Main Data'!$C:$C, 'Problem Statement 2'!$P9, 'Main Data'!$D:$D, 'Problem Statement 2'!Q$2) -> 163.86667 | R9: =AVERAGEIFS('Main Data'!$AI:$AI, 'Main Data'!$C:$C, 'Problem Statement 2'!$P9, 'Main Data'!$D:$D, 'Problem Statement 2'!R$2) -> 181.8 | S9: =(R9-Q9)/Q9 -> 0.10943857 | U9: Insight 2
D10: 2023 | E10: =AVERAGEIFS('Main Data'!$AG:$AG, 'Main Data'!$C:$C, 'Problem Statement 2'!$D10, 'Main Data'!$D:$D, 'Problem Statement 2'!E$2,'Main Data'!$A:$A,"Rural+Urban") -> 176.5 | F10: =AVERAGEIFS('Main Data'!$AG:$AG, 'Main Data'!$C:$C, 'Problem Statement 2'!$D10, 'Main Data'!$D:$D, "May",'Main Data'!$A:$A,"Rural+Urban") -> 179.1 | G10: =(F10-E10)/E10 -> 0.014730878 | I10: Food | J10: 2023 | K10: =AVERAGEIFS('Main Data'!$AH:$AH, 'Main Data'!$C:$C, 'Problem Statement 2'!$J10, 'Main Data'!$D:$D, 'Problem Statement 2'!K$2) -> 2295.3667 | L10: =AVERAGEIFS('Main Data'!$AH:$AH, 'Main Data'!$C:$C, 'Problem Statement 2'!$J10, 'Main Data'!$D:$D, "May") -> 2310.9 | M10: =(L10-K10)/K10 -> 0.0067672558 | O10: Energy | P10: 2023 | Q10: =AVERAGEIFS('Main Data'!$AI:$AI, 'Main Data'!$C:$C, 'Problem Statement 2'!$P10, 'Main Data'!$D:$D, 'Problem Statement 2'!Q$2) -> 181.76667 | R10: =AVERAGEIFS('Main Data'!$AI:$AI, 'Main Data'!$C:$C, 'Problem Statement 2'!$P10, 'Main Data'!$D:$D,"May") -> 182.9 | S10: =(R10-Q10)/Q10 -> 0.0062350999 | U10: General Index (Rural +Urban city Inflation )"Highest Inflation was recoreded for the year 2019 as per the data "
C12: Transport | E12: January | F12: December | I12: Education | K12: January | L12: December | O12: Others | Q12: January | R12: December
C13: Category | D13: Year | E13: CPI Start | F13: CPI End | G13: Inflation Rate (%) | I13: Category | J13: Year | K13: CPI Start | L13: CPI End | M13: Inflation Rate (%) | O13: Category | P13: Year | Q13: CPI Start | R13: CPI End | S13: Inflation Rate (%)
C14: Transport | D14: 2017 | E14: =AVERAGEIFS('Main Data'!$AJ:$AJ, 'Main Data'!$C:$C, 'Problem Statement 2'!$D14, 'Main Data'!$D:$D, 'Problem Statement 2'!E$12) -> 117.1 | F14: =AVERAGEIFS('Main Data'!$AJ:$AJ, 'Main Data'!$C:$C, 'Problem Statement 2'!$D14, 'Main Data'!$D:$D, 'Problem Statement 2'!F$12) -> 118.6 | G14: =(F14-E14)/E14 -> 0.012809564 | I14: Education | J14: 2017 | K14: =AVERAGEIFS('Main Data'!$AK:$AK, 'Main Data'!$C:$C, 'Problem Statement 2'!$J14, 'Main Data'!$D:$D, 'Problem Statement 2'!K$12) -> 133.43333 | L14: =AVERAGEIFS('Main Data'!$AK:$AK, 'Main Data'!$C:$C, 'Problem Statement 2'!$J14, 'Main Data'!$D:$D, 'Problem Statement 2'!L$12) -> 138.76667 | M14: =(L14-K14)/K14 -> 0.039970022 | O14: Others | P14: 2017 | Q14: =AVERAGEIFS('Main Data'!$AL:$AL, 'Main Data'!$C:$C, 'Problem Statement 2'!$P14, 'Main Data'!$D:$D, 'Problem Statement 2'!Q$12) -> 1300.0667 | R14: =AVERAGEIFS('Main Data'!$AL:$AL, 'Main Data'!$C:$C, 'Problem Statement 2'!$P14, 'Main Data'!$D:$D, 'Problem Statement 2'!R$12) -> 1362.5333 | S14: =(R14-Q14)/Q14 -> 0.048048818
C15: Transport | D15: 2018 | E15: =AVERAGEIFS('Main Data'!$AJ:$AJ, 'Main Data'!$C:$C, 'Problem Statement 2'!$D15, 'Main Data'!$D:$D, 'Problem Statement 2'!E$12) -> 119.43333 | F15: =AVERAGEIFS('Main Data'!$AJ:$AJ, 'Main Data'!$C:$C, 'Problem Statement 2'!$D15, 'Main Data'!$D:$D, 'Problem Statement 2'!F$12) -> 123.76667 | G15: =(F15-E15)/E15 -> 0.036282445 | I15: Education | J15: 2018 | K15: =AVERAGEIFS('Main Data'!$AK:$AK, 'Main Data'!$C:$C, 'Problem Statement 2'!$J15, 'Main Data'!$D:$D, 'Problem Statement 2'!K$12) -> 139.23333 | L15: =AVERAGEIFS('Main Data'!$AK:$AK, 'Main Data'!$C:$C, 'Problem Statement 2'!$J15, 'Main Data'!$D:$D, 'Problem Statement 2'!L$12) -> 150.56667 | M15: =(L15-K15)/K15 -> 0.081398133 | O15: Others | P15: 2018 | Q15: =AVERAGEIFS('Main Data'!$AL:$AL, 'Main Data'!$C:$C, 'Problem Statement 2'!$P15, 'Main Data'!$D:$D, 'Problem Statement 2'!Q$12) -> 1368.0667 | R15: =AVERAGEIFS('Main Data'!$AL:$AL, 'Main Data'!$C:$C, 'Problem Statement 2'!$P15, 'Main Data'!$D:$D, 'Problem Statement 2'!R$12) -> 1434.9 | S15: =(R15-Q15)/Q15 -> 0.048852395
C16: Transport | D16: 2019 | E16: =AVERAGEIFS('Main Data'!$AJ:$AJ, 'Main Data'!$C:$C, 'Problem Statement 2'!$D16, 'Main Data'!$D:$D, 'Problem Statement 2'!E$12) -> 123.5 | F16: =AVERAGEIFS('Main Data'!$AJ:$AJ, 'Main Data'!$C:$C, 'Problem Statement 2'!$D16, 'Main Data'!$D:$D, 'Problem Statement 2'!F$12) -> 130 | G16: =(F16-E16)/E16 -> 0.052631579 | I16: Education | J16: 2019 | K16: =AVERAGEIFS('Main Data'!$AK:$AK, 'Main Data'!$C:$C, 'Problem Statement 2'!$J16, 'Main Data'!$D:$D, 'Problem Statement 2'!K$12) -> 150.66667 | L16: =AVERAGEIFS('Main Data'!$AK:$AK, 'Main Data'!$C:$C, 'Problem Statement 2'!$J16, 'Main Data'!$D:$D, 'Problem Statement 2'!L$12) -> 156.23333 | M16: =(L16-K16)/K16 -> 0.036946903 | O16: Others | P16: 2019 | Q16: =AVERAGEIFS('Main Data'!$AL:$AL, 'Main Data'!$C:$C, 'Problem Statement 2'!$P16, 'Main Data'!$D:$D, 'Problem Statement 2'!Q$12) -> 1436.4 | R16: =AVERAGEIFS('Main Data'!$AL:$AL, 'Main Data'!$C:$C, 'Problem Statement 2'!$P16, 'Main Data'!$D:$D, 'Problem Statement 2'!R$12) -> 1481.3333 | S16: =(R16-Q16)/Q16 -> 0.031281908
C17: Transport | D17: 2020 | E17: =AVERAGEIFS('Main Data'!$AJ:$AJ, 'Main Data'!$C:$C, 'Problem Statement 2'!$D17, 'Main Data'!$D:$D, 'Problem Statement 2'!E$12) -> 131.1 | F17: =AVERAGEIFS('Main Data'!$AJ:$AJ, 'Main Data'!$C:$C, 'Problem Statement 2'!$D17, 'Main Data'!$D:$D, 'Problem Statement 2'!F$12) -> 140.86667 | G17: =(F17-E17)/E17 -> 0.074497839 | I17: Education | J17: 2020 | K17: =AVERAGEIFS('Main Data'!$AK:$AK, 'Main Data'!$C:$C, 'Problem Statement 2'!$J17, 'Main Data'!$D:$D, 'Problem Statement 2'!K$12) -> 156.63333 | L17: =AVERAGEIFS('Main Data'!$AK:$AK, 'Main Data'!$C:$C, 'Problem Statement 2'!$J17, 'Main Data'!$D:$D, 'Problem Statement 2'!L$12) -> 159.73333 | M17: =(L17-K17)/K17 -> 0.019791445 | O17: Others | P17: 2020 | Q17: =AVERAGEIFS('Main Data'!$AL:$AL, 'Main Data'!$C:$C, 'Problem Statement 2'!$P17, 'Main Data'!$D:$D, 'Problem Statement 2'!Q$12) -> 1488.1667 | R17: =AVERAGEIFS('Main Data'!$AL:$AL, 'Main Data'!$C:$C, 'Problem Statement 2'!$P17, 'Main Data'!$D:$D, 'Problem Statement 2'!R$12) -> 1561.5 | S17: =(R17-Q17)/Q17 -> 0.049277635
C18: Transport | D18: 2021 | E18: =AVERAGEIFS('Main Data'!$AJ:$AJ, 'Main Data'!$C:$C, 'Problem Statement 2'!$D18, 'Main Data'!$D:$D, 'Problem Statement 2'!E$12) -> 142.1 | F18: =AVERAGEIFS('Main Data'!$AJ:$AJ, 'Main Data'!$C:$C, 'Problem Statement 2'!$D18, 'Main Data'!$D:$D, 'Problem Statement 2'!F$12) -> 155.86667 | G18: =(F18-E18)/E18 -> 0.096880131 | I18: Education | J18: 2021 | K18: =AVERAGEIFS('Main Data'!$AK:$AK, 'Main Data'!$C:$C, 'Problem Statement 2'!$J18, 'Main Data'!$D:$D, 'Problem Statement 2'!K$12) -> 159.6 | L18: =AVERAGEIFS('Main Data'!$AK:$AK, 'Main Data'!$C:$C, 'Problem Statement 2'!$J18, 'Main Data'!$D:$D, 'Problem Statement 2'!L$12) -> 164.9 | M18: =(L18-K18)/K18 -> 0.03320802 | O18: Others | P18: 2021 | Q18: =AVERAGEIFS('Main Data'!$AL:$AL, 'Main Data'!$C:$C, 'Problem Statement 2'!$P18, 'Main Data'!$D:$D, 'Problem Statement 2'!Q$12) -> 1566.7333 | R18: =AVERAGEIFS('Main Data'!$AL:$AL, 'Main Data'!$C:$C, 'Problem Statement 2'!$P18, 'Main Data'!$D:$D, 'Problem Statement 2'!R$12) -> 1663.8333 | S18: =(R18-Q18)/Q18 -> 0.061976086
C19: Transport | D19: 2022 | E19: =AVERAGEIFS('Main Data'!$AJ:$AJ, 'Main Data'!$C:$C, 'Problem Statement 2'!$D19, 'Main Data'!$D:$D, 'Problem Statement 2'!E$12) -> 156.66667 | F19: =AVERAGEIFS('Main Data'!$AJ:$AJ, 'Main Data'!$C:$C, 'Problem Statement 2'!$D19, 'Main Data'!$D:$D, 'Problem Statement 2'!F$12) -> 163.53333 | G19: =(F19-E19)/E19 -> 0.043829787 | I19: Education | J19: 2022 | K19: =AVERAGEIFS('Main Data'!$AK:$AK, 'Main Data'!$C:$C, 'Problem Statement 2'!$J19, 'Main Data'!$D:$D, 'Problem Statement 2'!K$12) -> 165.2 | L19: =AVERAGEIFS('Main Data'!$AK:$AK, 'Main Data'!$C:$C, 'Problem Statement 2'!$J19, 'Main Data'!$D:$D, 'Problem Statement 2'!L$12) -> 174.4 | M19: =(L19-K19)/K19 -> 0.055690073 | O19: Others | P19: 2022 | Q19: =AVERAGEIFS('Main Data'!$AL:$AL, 'Main Data'!$C:$C, 'Problem Statement 2'!$P19, 'Main Data'!$D:$D, 'Problem Statement 2'!Q$12) -> 1672.9667 | R19: =AVERAGEIFS('Main Data'!$AL:$AL, 'Main Data'!$C:$C, 'Problem Statement 2'!$P19, 'Main Data'!$D:$D, 'Problem Statement 2'!R$12) -> 1779.3667 | S19: =(R19-Q19)/Q19 -> 0.063599594
C20: Transport | D20: 2023 | E20: =AVERAGEIFS('Main Data'!$AJ:$AJ, 'Main Data'!$C:$C, 'Problem Statement 2'!$D20, 'Main Data'!$D:$D, 'Problem Statement 2'!E$12) -> 163.76667 | F20: =AVERAGEIFS('Main Data'!$AJ:$AJ, 'Main Data'!$C:$C, 'Problem Statement 2'!$D20, 'Main Data'!$D:$D, "May") -> 164.96667 | G20: =(F20-E20)/E20 -> 0.0073274985 | I20: Education | J20: 2023 | K20: =AVERAGEIFS('Main Data'!$AK:$AK, 'Main Data'!$C:$C, 'Problem Statement 2'!$J20, 'Main Data'!$D:$D, 'Problem Statement 2'!K$12) -> 174.63333 | L20: =AVERAGEIFS('Main Data'!$AK:$AK, 'Main Data'!$C:$C, 'Problem Statement 2'!$J20, 'Main Data'!$D:$D,"May") -> 177.4 | M20: =(L20-K20)/K20 -> 0.015842718 | O20: Others | P20: 2023 | Q20: =AVERAGEIFS('Main Data'!$AL:$AL, 'Main Data'!$C:$C, 'Problem Statement 2'!$P20, 'Main Data'!$D:$D, 'Problem Statement 2'!Q$12) -> 1790.1667 | R20: =AVERAGEIFS('Main Data'!$AL:$AL, 'Main Data'!$C:$C, 'Problem Statement 2'!$P20, 'Main Data'!$D:$D, "May") -> 1820.4 | S20: =(R20-Q20)/Q20 -> 0.016888558

Sheet Problem Statement 3
A1: Food | F1: Food Sub Category(Rural +Urban)
A2: Year | B2: Month | C2: CPI | D2: MOM Inflation % | F2: Year | G2: CPI '2022 | H2: CPI' 2023 | I2: YOY Inflation %
A3: 2022 | B3: June | C3: =AVERAGEIFS('Main Data'!$AH:$AH,'Main Data'!$C:$C,'Problem Statement 3'!$A3,'Main Data'!$D:$D,'Problem Statement 3'!$B3,'Main Data'!A:A,"Rural+Urban") -> 2261.9 | D3: 0 | F3: Cereals and products | G3: =AVERAGEIFS('Main Data'!$G:$G,'Main Data'!$B:$B,">="&"01-06-2022",'Main Data'!$B:$B,"<="&"01-12-2022",'Main Data'!$A:$A,"Rural+Urban") -> 162.44286 | H3: =AVERAGEIFS('Main Data'!$G:$G,'Main Data'!$B:$B,">="&"01-01-2023",'Main Data'!$B:$B,"<="&"01-12-2023",'Main Data'!$A:$A,"Rural+Urban") -> 174.02 | I3: =(H3-G3)/G3 -> 0.071269018
A4: 2022 | B4: July | C4: =AVERAGEIFS('Main Data'!$AH:$AH,'Main Data'!$C:$C,'Problem Statement 3'!$A4,'Main Data'!$D:$D,'Problem Statement 3'!$B4,'Main Data'!A:A,"Rural+Urban") -> 2266.3 | D4: =(C4-C3)/C3 -> 0.0019452673 | F4: Meat and fish | G4: =AVERAGEIFS('Main Data'!$H:$H,'Main Data'!$B:$B,">="&"01-06-2022",'Main Data'!$B:$B,"<="&"01-12-2022",'Main Data'!$A:$A,"Rural+Urban") -> 211.05714 | H4: =AVERAGEIFS('Main Data'!$H:$H,'Main Data'!$B:$B,">="&"01-01-2023",'Main Data'!$B:$B,"<="&"01-12-2023",'Main Data'!$A:$A,"Rural+Urban") -> 209.94 | I4: =(H4-G4)/G4 -> -0.0052930824
A5: 2022 | B5: August | C5: =AVERAGEIFS('Main Data'!$AH:$AH,'Main Data'!$C:$C,'Problem Statement 3'!$A5,'Main Data'!$D:$D,'Problem Statement 3'!$B5,'Main Data'!A:A,"Rural+Urban") -> 2269.2 | D5: =(C5-C4)/C4 -> 0.0012796188 | F5: Egg | G5: =AVERAGEIFS('Main Data'!$I:$I,'Main Data'!$B:$B,">="&"01-06-2022",'Main Data'!$B:$B,"<="&"01-12-2022",'Main Data'!$A:$A,"Rural+Urban") -> 175.34286 | H5: =AVERAGEIFS('Main Data'!$I:$I,'Main Data'!$B:$B,">="&"01-01-2023",'Main Data'!$B:$B,"<="&"01-12-2023",'Main Data'!$A:$A,"Rural+Urban") -> 177.54 | I5: =(H5-G5)/G5 -> 0.012530552
A6: 2022 | B6: September | C6: =AVERAGEIFS('Main Data'!$AH:$AH,'Main Data'!$C:$C,'Problem Statement 3'!$A6,'Main Data'!$D:$D,'Problem Statement 3'!$B6,'Main Data'!A:A,"Rural+Urban") -> 2280.9 | D6: =(C6-C5)/C5 -> 0.0051560021 | F6: Milk and products | G6: =AVERAGEIFS('Main Data'!$J:$J,'Main Data'!$B:$B,">="&"01-06-2022",'Main Data'!$B:$B,"<="&"01-12-2022",'Main Data'!$A:$A,"Rural+Urban") -> 169.57143 | H6: =AVERAGEIFS('Main Data'!$J:$J,'Main Data'!$B:$B,">="&"01-01-2023",'Main Data'!$B:$B,"<="&"01-12-2023",'Main Data'!$A:$A,"Rural+Urban") -> 177.42 | I6: =(H6-G6)/G6 -> 0.046284751
A7: 2022 | B7: October | C7: =AVERAGEIFS('Main Data'!$AH:$AH,'Main Data'!$C:$C,'Problem Statement 3'!$A7,'Main Data'!$D:$D,'Problem Statement 3'!$B7,'Main Data'!A:A,"Rural+Urban") -> 2297.3 | D7: =(C7-C6)/C6 -> 0.0071901442 | F7: Oils and fats | G7: =AVERAGEIFS('Main Data'!$K:$K,'Main Data'!$B:$B,">="&"01-06-2022",'Main Data'!$B:$B,"<="&"01-12-2022",'Main Data'!$A:$A,"Rural+Urban") -> 191.67143 | H7: =AVERAGEIFS('Main Data'!K:K,'Main Data'!$B:$B,">="&"01-01-2023",'Main Data'!$B:$B,"<="&"01-12-2023",'Main Data'!$A:$A,"Rural+Urban") -> 178.12 | I7: =(H7-G7)/G7 -> -0.070701349
A8: 2022 | B8: November | C8: =AVERAGEIFS('Main Data'!$AH:$AH,'Main Data'!$C:$C,'Problem Statement 3'!$A8,'Main Data'!$D:$D,'Problem Statement 3'!$B8,'Main Data'!A:A,"Rural+Urban") -> 2296.8 | D8: =(C8-C7)/C7 -> -0.0002176468 | F8: Fruits | G8: =AVERAGEIFS('Main Data'!L:L,'Main Data'!$B:$B,">="&"01-06-2022",'Main Data'!$B:$B,"<="&"01-12-2022",'Main Data'!$A:$A,"Rural+Urban") -> 166.42857 | H8: =AVERAGEIFS('Main Data'!L:L,'Main Data'!$B:$B,">="&"01-01-2023",'Main Data'!$B:$B,"<="&"01-12-2023",'Main Data'!$A:$A,"Rural+Urban") -> 169.16 | I8: =(H8-G8)/G8 -> 0.016412017
A9: 2022 | B9: December | C9: =AVERAGEIFS('Main Data'!$AH:$AH,'Main Data'!$C:$C,'Problem Statement 3'!$A9,'Main Data'!$D:$D,'Problem Statement 3'!$B9,'Main Data'!A:A,"Rural+Urban") -> 2283.4 | D9: =(C9-C8)/C8 -> -0.0058342041 | F9: Vegetables | G9: =AVERAGEIFS('Main Data'!M:M,'Main Data'!$B:$B,">="&"01-06-2022",'Main Data'!$B:$B,"<="&"01-12-2022",'Main Data'!$A:$A,"Rural+Urban") -> 183.65714 | H9: =AVERAGEIFS('Main Data'!M:M,'Main Data'!$B:$B,">="&"01-01-2023",'Main Data'!$B:$B,"<="&"01-12-2023",'Main Data'!$A:$A,"Rural+Urban") -> 155.16 | I9: =(H9-G9)/G9 -> -0.1551649
A10: 2023 | B10: January | C10: =AVERAGEIFS('Main Data'!$AH:$AH,'Main Data'!$C:$C,'Problem Statement 3'!$A10,'Main Data'!$D:$D,'Problem Statement 3'!$B10,'Main Data'!A:A,"Rural+Urban") -> 2292.7 | D10: =(C10-C9)/C9 -> 0.0040728738 | F10: Pulses and products | G10: =AVERAGEIFS('Main Data'!N:N,'Main Data'!$B:$B,">="&"01-06-2022",'Main Data'!$B:$B,"<="&"01-12-2022",'Main Data'!$A:$A,"Rural+Urban") -> 168 | H10: =AVERAGEIFS('Main Data'!N:N,'Main Data'!$B:$B,">="&"01-01-2023",'Main Data'!$B:$B,"<="&"01-12-2023",'Main Data'!$A:$A,"Rural+Urban") -> 172.4 | I10: =(H10-G10)/G10 -> 0.026190476
A11: 2023 | B11: February | C11: =AVERAGEIFS('Main Data'!$AH:$AH,'Main Data'!$C:$C,'Problem Statement 3'!$A11,'Main Data'!$D:$D,'Problem Statement 3'!$B11,'Main Data'!A:A,"Rural+Urban") -> 2279.1 | D11: =(C11-C10)/C10 -> -0.0059318707 | F11: Sugar and Confectionery | G11: =AVERAGEIFS('Main Data'!O:O,'Main Data'!$B:$B,">="&"01-06-2022",'Main Data'!$B:$B,"<="&"01-12-2022",'Main Data'!$A:$A,"Rural+Urban") -> 121.17143 | H11: =AVERAGEIFS('Main Data'!O:O,'Main Data'!$B:$B,">="&"01-01-2023",'Main Data'!$B:$B,"<="&"01-12-2023",'Main Data'!$A:$A,"Rural+Urban") -> 121.02 | I11: =(H11-G11)/G11 -> -0.0012497053
A12: 2023 | B12: March | C12: =AVERAGEIFS('Main Data'!$AH:$AH,'Main Data'!$C:$C,'Problem Statement 3'!$A12,'Main Data'!$D:$D,'Problem Statement 3'!$B12,'Main Data'!A:A,"Rural+Urban") -> 2279.2 | D12: =(C12-C11)/C11 -> 4.3876969e-05 | F12: Spices | G12: =AVERAGEIFS('Main Data'!P:P,'Main Data'!$B:$B,">="&"01-06-2022",'Main Data'!$B:$B,"<="&"01-12-2022",'Main Data'!$A:$A,"Rural+Urban") -> 196.55714 | H12: =AVERAGEIFS('Main Data'!P:P,'Main Data'!$B:$B,">="&"01-01-2023",'Main Data'!$B:$B,"<="&"01-12-2023",'Main Data'!$A:$A,"Rural+Urban") -> 211.74 | I12: =(H12-G12)/G12 -> 0.077243986
A13: 2023 | B13: April | C13: =AVERAGEIFS('Main Data'!$AH:$AH,'Main Data'!$C:$C,'Problem Statement 3'!$A13,'Main Data'!$D:$D,'Problem Statement 3'!$B13,'Main Data'!A:A,"Rural+Urban") -> 2289.6 | D13: =(C13-C12)/C12 -> 0.0045630046 | F13: Non-alcoholic beverages | G13: =AVERAGEIFS('Main Data'!Q:Q,'Main Data'!$B:$B,">="&"01-06-2022",'Main Data'!$B:$B,"<="&"01-12-2022",'Main Data'!$A:$A,"Rural+Urban") -> 169.4 | H13: =AVERAGEIFS('Main Data'!Q:Q,'Main Data'!$B:$B,">="&"01-01-2023",'Main Data'!$B:$B,"<="&"01-12-2023",'Main Data'!$A:$A,"Rural+Urban") -> 172.46 | I13: =(H13-G13)/G13 -> 0.018063754
A14: 2023 | B14: May | C14: =AVERAGEIFS('Main Data'!$AH:$AH,'Main Data'!$C:$C,'Problem Statement 3'!$A14,'Main Data'!$D:$D,'Problem Statement 3'!$B14,'Main Data'!A:A,"Rural+Urban") -> 2306.9 | D14: =(C14-C13)/C13 -> 0.007555905 | F14: Prepared meals, snacks, sweets etc. | G14: =AVERAGEIFS('Main Data'!R:R,'Main Data'!$B:$B,">="&"01-06-2022",'Main Data'!$B:$B,"<="&"01-12-2022",'Main Data'!$A:$A,"Rural+Urban") -> 187.27143 | H14: =AVERAGEIFS('Main Data'!R:R,'Main Data'!$B:$B,">="&"01-01-2023",'Main Data'!$B:$B,"<="&"01-12-2023",'Main Data'!$A:$A,"Rural+Urban") -> 192.98 | I14: =(H14-G14)/G14 -> 0.030482874
F15: Food and beverages | G15: =AVERAGEIFS('Main Data'!S:S,'Main Data'!$B:$B,">="&"01-06-2022",'Main Data'!$B:$B,"<="&"01-12-2022",'Main Data'!$A:$A,"Rural+Urban") -> 176.82857 | H15: =AVERAGEIFS('Main Data'!S:S,'Main Data'!$B:$B,">="&"01-01-2023",'Main Data'!$B:$B,"<="&"01-12-2023",'Main Data'!$A:$A,"Rural+Urban") -> 177.54 | I15: =(H15-G15)/G15 -> 0.0040232671

Sheet Problem Statement 4
A1: Category | B1: PreCovid | C1: Post Covid | D1: % Change | E1: Interpretation
A2: Food | B2: =AVERAGEIFS(Sheet6!$I:$I,Sheet6!$G:$G,'Problem Statement 4'!$A2,Sheet6!$H:$H,'Problem Statement 4'!B$1) -> 0.21647103 | C2: =AVERAGEIFS(Sheet6!$I:$I,Sheet6!$G:$G,'Problem Statement 4'!$A2,Sheet6!$H:$H,'Problem Statement 4'!C$1) -> 0.48797339 | D2: =C2-B2 -> 0.27150236 | E2: Significant increase due to heightened focus on food security, home cooking, and supply chain resilience during lockdowns. | G2: January | H2: 1
A3: Energy | B3: =AVERAGEIFS(Sheet6!$I:$I,Sheet6!$G:$G,'Problem Statement 4'!$A3,Sheet6!$H:$H,'Problem Statement 4'!B$1) -> 0.42429221 | C3: =AVERAGEIFS(Sheet6!$I:$I,Sheet6!$G:$G,'Problem Statement 4'!$A3,Sheet6!$H:$H,'Problem Statement 4'!C$1) -> 0.56320209 | D3: =C3-B3 -> 0.13890989 | E3: Moderate rise driven by increased residential energy consumption and digital infrastructure needs. | G3: February | H3: 2
A4: Transportation | B4: =AVERAGEIFS(Sheet6!$I:$I,Sheet6!$G:$G,'Problem Statement 4'!$A4,Sheet6!$H:$H,'Problem Statement 4'!B$1) -> 0.30737576 | C4: =AVERAGEIFS(Sheet6!$I:$I,Sheet6!$G:$G,'Problem Statement 4'!$A4,Sheet6!$H:$H,'Problem Statement 4'!C$1) -> 0.60862186 | D4: =C4-B4 -> 0.30124611 | E4: Largest increase, reflecting the critical role of logistics, delivery services, and mobility solutions during restricted movement periods. | G4: March | H4: 3
A5: Education | B5: =AVERAGEIFS(Sheet6!$I:$I,Sheet6!$G:$G,'Problem Statement 4'!$A5,Sheet6!$H:$H,'Problem Statement 4'!B$1) -> 0.41786207 | C5: =AVERAGEIFS(Sheet6!$I:$I,Sheet6!$G:$G,'Problem Statement 4'!$A5,Sheet6!$H:$H,'Problem Statement 4'!C$1) -> 0.32322467 | D5: =C5-B5 -> -0.094637406 | E5: Decline due to school closures, shift to remote learning, and reclassification of education as non-essential in early phases. | G5: April | H5: 4
A6: Others | B6: =AVERAGEIFS(Sheet6!$I:$I,Sheet6!$G:$G,'Problem Statement 4'!$A6,Sheet6!$H:$H,'Problem Statement 4'!B$1) -> 0.36632668 | C6: =AVERAGEIFS(Sheet6!$I:$I,Sheet6!$G:$G,'Problem Statement 4'!$A6,Sheet6!$H:$H,'Problem Statement 4'!C$1) -> 0.51023633 | D6: =C6-B6 -> 0.14390964 | E6: Includes services like sanitation, digital access, and mental health—gained importance as broader definitions of “essential” evolved. | G6: May | H6: 5
G7: June | H7: 6
G8: July | H8: 7
G9: August | H9: 8
G10: September | H10: 9
G11: October | H11: 10
G12: November | H12: 11
G13: December | H13: 12

Sheet Sheet6
A1: Sector | B1: Date | C1: Year | D1: Month | E1: Month Number | F1: Food | G1: Category | H1: Precovid /Post | I1: %
A2: Rural+Urban | B2: =DATE(C2,E2,1) -> 42675 | C2: 2016 | D2: November | E2: =VLOOKUP(D2,'Problem Statement 4'!$G$2:$H$13,2,0) -> 11 | F2: 1759.8 | G2: Food | H2: =IF(B2<DATE(2020,3,1),"PreCovid","Post Covid") -> PreCovid | I2: 0
A3: Rural+Urban | B3: =DATE(C3,E3,1) -> 42705 | C3: 2016 | D3: December | E3: =VLOOKUP(D3,'Problem Statement 4'!$G$2:$H$13,2,0) -> 12 | F3: 1740.7 | G3: Food | H3: =IF(B3<DATE(2020,3,1),"PreCovid","Post Covid") -> PreCovid | I3: =(F3-F2)/F2*100 -> -1.0853506
A4: Rural+Urban | B4: =DATE(C4,E4,1) -> 42736 | C4: 2017 | D4: January | E4: =VLOOKUP(D4,'Problem Statement 4'!$G$2:$H$13,2,0) -> 1 | F4: 1727.3 | G4: Food | H4: =IF(B4<DATE(2020,3,1),"PreCovid","Post Covid") -> PreCovid | I4: =(F4-F3)/F3*100 -> -0.76980525
A5: Rural+Urban | B5: =DATE(C5,E5,1) -> 42767 | C5: 2017 | D5: February | E5: =VLOOKUP(D5,'Problem Statement 4'!$G$2:$H$13,2,0) -> 2 | F5: 1722.3 | G5: Food | H5: =IF(B5<DATE(2020,3,1),"PreCovid","Post Covid") -> PreCovid | I5: =(F5-F4)/F4*100 -> -0.28946911
A6: Rural+Urban | B6: =DATE(C6,E6,1) -> 42795 | C6: 2017 | D6: March | E6: =VLOOKUP(D6,'Problem Statement 4'!$G$2:$H$13,2,0) -> 3 | F6: 1718.9 | G6: Food | H6: =IF(B6<DATE(2020,3,1),"PreCovid","Post Covid") -> PreCovid | I6: =(F6-F5)/F5*100 -> -0.19741044
A7: Rural+Urban | B7: =DATE(C7,E7,1) -> 42826 | C7: 2017 | D7: April | E7: =VLOOKUP(D7,'Problem Statement 4'!$G$2:$H$13,2,0) -> 4 | F7: 1718.4 | G7: Food | H7: =IF(B7<DATE(2020,3,1),"PreCovid","Post Covid") -> PreCovid | I7: =(F7-F6)/F6*100 -> -0.02908837
A8: Rural+Urban | B8: =DATE(C8,E8,1) -> 42856 | C8: 2017 | D8: May | E8: =VLOOKUP(D8,'Problem Statement 4'!$G$2:$H$13,2,0) -> 5 | F8: 1719.6 | G8: Food | H8: =IF(B8<DATE(2020,3,1),"PreCovid","Post Covid") -> PreCovid | I8: =(F8-F7)/F7*100 -> 0.069832402
A9: Rural+Urban | B9: =DATE(C9,E9,1) -> 42887 | C9: 2017 | D9: June | E9: =VLOOKUP(D9,'Problem Statement 4'!$G$2:$H$13,2,0) -> 6 | F9: 1734.7 | G9: Food | H9: =IF(B9<DATE(2020,3,1),"PreCovid","Post Covid") -> PreCovid | I9: =(F9-F8)/F8*100 -> 0.87811119
A10: Rural+Urban | B10: =DATE(C10,E10,1) -> 42917 | C10: 2017 | D10: July | E10: =VLOOKUP(D10,'Problem Statement 4'!$G$2:$H$13,2,0) -> 7 | F10: 1769.4 | G10: Food | H10: =IF(B10<DATE(2020,3,1),"PreCovid","Post Covid") -> PreCovid | I10: =(F10-F9)/F9*100 -> 2.0003459
A11: Rural+Urban | B11: =DATE(C11,E11,1) -> 42948 | C11: 2017 | D11: August | E11: =VLOOKUP(D11,'Problem Statement 4'!$G$2:$H$13,2,0) -> 8 | F11: 1783.8 | G11: Food | H11: =IF(B11<DATE(2020,3,1),"PreCovid","Post Covid") -> PreCovid | I11: =(F11-F10)/F10*100 -> 0.8138352
A12: Rural+Urban | B12: =DATE(C12,E12,1) -> 42979 | C12: 2017 | D12: September | E12: =VLOOKUP(D12,'Problem Statement 4'!$G$2:$H$13,2,0) -> 9 | F12: 1770 | G12: Food | H12: =IF(B12<DATE(2020,3,1),"PreCovid","Post Covid") -> PreCovid | I12: =(F12-F11)/F11*100 -> -0.77362933
A13: Rural+Urban | B13: =DATE(C13,E13,1) -> 43009 | C13: 2017 | D13: October | E13: =VLOOKUP(D13,'Problem Statement 4'!$G$2:$H$13,2,0) -> 10 | F13: 1779.7 | G13: Food | H13: =IF(B13<DATE(2020,3,1),"PreCovid","Post Covid") -> PreCovid | I13: =(F13-F12)/F12*100 -> 0.5480226
A14: Rural+Urban | B14: =DATE(C14,E14,1) -> 43040 | C14: 2017 | D14: November | E14: =VLOOKUP(D14,'Problem Statement 4'!$G$2:$H$13,2,0) -> 11 | F14: 1808.2 | G14: Food | H14: =IF(B14<DATE(2020,3,1),"PreCovid","Post Covid") -> PreCovid | I14: =(F14-F13)/F13*100 -> 1.6013935
... A79: Rural+Urban | B79: =DATE(C79,E79,1) -> 45047 | C79: 2023 | D79: May | E79: =VLOOKUP(D79,'Problem Statement 4'!$G$2:$H$13,2,0) -> 5 | F79: 2306.9 | G79: Food | H79: =IF(B79<DATE(2020,3,1),"PreCovid","Post Covid") -> Post Covid | I79: =(F79-F78)/F78*100 -> 0.7555905
A80: Rural+Urban | B80: =DATE(C80,E80,1) -> 42675 | C80: 2016 | D80: November | E80: =VLOOKUP(D80,'Problem Statement 4'!$G$2:$H$13,2,0) -> 11 | F80: 125 | G80: Energy | H80: =IF(B80<DATE(2020,3,1),"PreCovid","Post Covid") -> PreCovid | I80: 0
A81: Rural+Urban | B81: =DATE(C81,E81,1) -> 42705 | C81: 2016 | D81: December | E81: =VLOOKUP(D81,'Problem Statement 4'!$G$2:$H$13,2,0) -> 12 | F81: 126.6 | G81: Energy | H81: =IF(B81<DATE(2020,3,1),"PreCovid","Post Covid") -> PreCovid | I81: =(F81-F80)/F80*100 -> 1.28
A82: Rural+Urban | B82: =DATE(C82,E82,1) -> 42736 | C82: 2017 | D82: January | E82: =VLOOKUP(D82,'Problem Statement 4'!$G$2:$H$13,2,0) -> 1 | F82: 126.8 | G82: Energy | H82: =IF(B82<DATE(2020,3,1),"PreCovid","Post Covid") -> PreCovid | I82: =(F82-F81)/F81*100 -> 0.15797788
A83: Rural+Urban | B83: =DATE(C83,E83,1) -> 42767 | C83: 2017 | D83: February | E83: =VLOOKUP(D83,'Problem Statement 4'!$G$2:$H$13,2,0) -> 2 | F83: 127.9 | G83: Energy | H83: =IF(B83<DATE(2020,3,1),"PreCovid","Post Covid") -> PreCovid | I83: =(F83-F82)/F82*100 -> 0.86750789
A84: Rural+Urban | B84: =DATE(C84,E84,1) -> 42795 | C84: 2017 | D84: March | E84: =VLOOKUP(D84,'Problem Statement 4'!$G$2:$H$13,2,0) -> 3 | F84: 129.1 | G84: Energy | H84: =IF(B84<DATE(2020,3,1),"PreCovid","Post Covid") -> PreCovid | I84: =(F84-F83)/F83*100 -> 0.93823299
A85: Rural+Urban | B85: =DATE(C85,E85,1) -> 42826 | C85: 2017 | D85: April | E85: =VLOOKUP(D85,'Problem Statement 4'!$G$2:$H$13,2,0) -> 4 | F85: 129.8 | G85: Energy | H85: =IF(B85<DATE(2020,3,1),"PreCovid","Post Covid") -> PreCovid | I85: =(F85-F84)/F84*100 -> 0.54221534
A86: Rural+Urban | B86: =DATE(C86,E86,1) -> 42856 | C86: 2017 | D86: May | E86: =VLOOKUP(D86,'Problem Statement 4'!$G$2:$H$13,2,0) -> 5 | F86: 129.4 | G86: Energy | H86: =IF(B86<DATE(2020,3,1),"PreCovid","Post Covid") -> PreCovid | I86: =(F86-F85)/F85*100 -> -0.30816641
A87: Rural+Urban | B87: =DATE(C87,E87,1) -> 42887 | C87: 2017 | D87: June | E87: =VLOOKUP(D87,'Problem Statement 4'!$G$2:$H$13,2,0) -> 6 | F87: 128.8 | G87: Energy | H87: =IF(B87<DATE(2020,3,1),"PreCovid","Post Covid") -> PreCovid | I87: =(F87-F86)/F86*100 -> -0.46367852
A88: Rural+Urban | B88: =DATE(C88,E88,1) -> 42917 | C88: 2017 | D88: July | E88: =VLOOKUP(D88,'Problem Statement 4'!$G$2:$H$13,2,0) -> 7 | F88: 129.4 | G88: Energy | H88: =IF(B88<DATE(2020,3,1),"PreCovid","Post Covid") -> PreCovid | I88: =(F88-F87)/F87*100 -> 0.46583851
A89: Rural+Urban | B89: =DATE(C89,E89,1) -> 42948 | C89: 2017 | D89: August | E89: =VLOOKUP(D89,'Problem Statement 4'!$G$2:$H$13,2,0) -> 8 | F89: 129.8 | G89: Energy | H89: =IF(B89<DATE(2020,3,1),"PreCovid","Post Covid") -> PreCovid | I89: =(F89-F88)/F88*100 -> 0.30911901
A90: Rural+Urban | B90: =DATE(C90,E90,1) -> 42979 | C90: 2017 | D90: September | E90: =VLOOKUP(D90,'Problem Statement 4'!$G$2:$H$13,2,0) -> 9 | F90: 131 | G90: Energy | H90: =IF(B90<DATE(2020,3,1),"PreCovid","Post Covid") -> PreCovid | I90: =(F90-F89)/F89*100 -> 0.92449923
A91: Rural+Urban | B91: =DATE(C91,E91,1) -> 43009 | C91: 2017 | D91: October | E91: =VLOOKUP(D91,'Problem Statement 4'!$G$2:$H$13,2,0) -> 10 | F91: 132.2 | G91: Energy | H91: =IF(B91<DATE(2020,3,1),"PreCovid","Post Covid") -> PreCovid | I91: =(F91-F90)/F90*100 -> 0.91603053
A92: Rural+Urban | B92: =DATE(C92,E92,1) -> 43040 | C92: 2017 | D92: November | E92: =VLOOKUP(D92,'Problem Statement 4'!$G$2:$H$13,2,0) -> 11 | F92: 135.3 | G92: Energy | H92: =IF(B92<DATE(2020,3,1),"PreCovid","Post Covid") -> PreCovid | I92: =(F92-F91)/F91*100 -> 2.3449319
... A157: Rural+Urban | B157: =DATE(C157,E157,1) -> 45047 | C157: 2023 | D157: May | E157: =VLOOKUP(D157,'Problem Statement 4'!$G$2:$H$13,2,0) -> 5 | F157: 182.8 | G157: Energy | H157: =IF(B157<DATE(2020,3,1),"PreCovid","Post Covid") -> Post Covid | I157: =(F157-F156)/F156*100 -> 0.60539351
A158: Rural+Urban | B158: =DATE(C158,E158,1) -> 42675 | C158: 2016 | D158: November | E158: =VLOOKUP(D158,'Problem Statement 4'!$G$2:$H$13,2,0) -> 11 | F158: 115.7 | G158: Transportation | H158: =IF(B158<DATE(2020,3,1),"PreCovid","Post Covid") -> PreCovid | I158: 0
A159: Rural+Urban | B159: =DATE(C159,E159,1) -> 42705 | C159: 2016 | D159: December | E159: =VLOOKUP(D159,'Problem Statement 4'!$G$2:$H$13,2,0) -> 12 | F159: 116 | G159: Transportation | H159: =IF(B159<DATE(2020,3,1),"PreCovid","Post Covid") -> PreCovid | I159: =(F159-F158)/F158*100 -> 0.25929127
A160: Rural+Urban | B160: =DATE(C160,E160,1) -> 42736 | C160: 2017 | D160: January | E160: =VLOOKUP(D160,'Problem Statement 4'!$G$2:$H$13,2,0) -> 1 | F160: 117 | G160: Transportation | H160: =IF(B160<DATE(2020,3,1),"PreCovid","Post Covid") -> PreCovid | I160: =(F160-F159)/F159*100 -> 0.86206897
A161: Rural+Urban | B161: =DATE(C161,E161,1) -> 42767 | C161: 2017 | D161: February | E161: =VLOOKUP(D161,'Problem Statement 4'!$G$2:$H$13,2,0) -> 2 | F161: 117.4 | G161: Transportation | H161: =IF(B161<DATE(2020,3,1),"PreCovid","Post Covid") -> PreCovid | I161: =(F161-F160)/F160*100 -> 0.34188034
A162: Rural+Urban | B162: =DATE(C162,E162,1) -> 42795 | C162: 2017 | D162: March | E162: =VLOOKUP(D162,'Problem Statement 4'!$G$2:$H$13,2,0) -> 3 | F162: 117.6 | G162: Transportation | H162: =IF(B162<DATE(2020,3,1),"PreCovid","Post Covid") -> PreCovid | I162: =(F162-F161)/F161*100 -> 0.17035775
A163: Rural+Urban | B163: =DATE(C163,E163,1) -> 42826 | C163: 2017 | D163: April | E163: =VLOOKUP(D163,'Problem Statement 4'!$G$2:$H$13,2,0) -> 4 | F163: 116.6 | G163: Transportation | H163: =IF(B163<DATE(2020,3,1),"PreCovid","Post Covid") -> PreCovid | I163: =(F163-F162)/F162*100 -> -0.85034014
A164: Rural+Urban | B164: =DATE(C164,E164,1) -> 42856 | C164: 2017 | D164: May | E164: =VLOOKUP(D164,'Problem Statement 4'!$G$2:$H$13,2,0) -> 5 | F164: 116.7 | G164: Transportation | H164: =IF(B164<DATE(2020,3,1),"PreCovid","Post Covid") -> PreCovid | I164: =(F164-F163)/F163*100 -> 0.085763293
A165: Rural+Urban | B165: =DATE(C165,E165,1) -> 42887 | C165: 2017 | D165: June | E165: =VLOOKUP(D165,'Problem Statement 4'!$G$2:$H$13,2,0) -> 6 | F165: 116.5 | G165: Transportation | H165: =IF(B165<DATE(2020,3,1),"PreCovid","Post Covid") -> PreCovid | I165: =(F165-F164)/F164*100 -> -0.17137961
A166: Rural+Urban | B166: =DATE(C166,E166,1) -> 42917 | C166: 2017 | D166: July | E166: =VLOOKUP(D166,'Problem Statement 4'!$G$2:$H$13,2,0) -> 7 | F166: 116 | G166: Transportation | H166: =IF(B166<DATE(2020,3,1),"PreCovid","Post Covid") -> PreCovid | I166: =(F166-F165)/F165*100 -> -0.42918455
A167: Rural+Urban | B167: =DATE(C167,E167,1) -> 42948 | C167: 2017 | D167: August | E167: =VLOOKUP(D167,'Problem Statement 4'!$G$2:$H$13,2,0) -> 8 | F167: 117.3 | G167: Transportation | H167: =IF(B167<DATE(2020,3,1),"PreCovid","Post Covid") -> PreCovid | I167: =(F167-F166)/F166*100 -> 1.1206897
A168: Rural+Urban | B168: =DATE(C168,E168,1) -> 42979 | C168: 2017 | D168: September | E168: =VLOOKUP(D168,'Problem Statement 4'!$G$2:$H$13,2,0) -> 9 | F168: 118.3 | G168: Transportation | H168: =IF(B168<DATE(2020,3,1),"PreCovid","Post Covid") -> PreCovid | I168: =(F168-F167)/F167*100 -> 0.85251492
A169: Rural+Urban | B169: =DATE(C169,E169,1) -> 43009 | C169: 2017 | D169: October | E169: =VLOOKUP(D169,'Problem Statement 4'!$G$2:$H$13,2,0) -> 10 | F169: 117.8 | G169: Transportation | H169: =IF(B169<DATE(2020,3,1),"PreCovid","Post Covid") -> PreCovid | I169: =(F169-F168)/F168*100 -> -0.42265427
A170: Rural+Urban | B170: =DATE(C170,E170,1) -> 43040 | C170: 2017 | D170: November | E170: =VLOOKUP(D170,'Problem Statement 4'!$G$2:$H$13,2,0) -> 11 | F170: 118.3 | G170: Transportation | H170: =IF(B170<DATE(2020,3,1),"PreCovid","Post Covid") -> PreCovid | I170: =(F170-F169)/F169*100 -> 0.42444822
... A235: Rural+Urban | B235: =DATE(C235,E235,1) -> 45047 | C235: 2023 | D235: May | E235: =VLOOKUP(D235,'Problem Statement 4'!$G$2:$H$13,2,0) -> 5 | F235: 164.8 | G235: Transportation | H235: =IF(B235<DATE(2020,3,1),"PreCovid","Post Covid") -> Post Covid | I235: =(F235-F234)/F234*100 -> 0.18237082
A236: Rural+Urban | B236: =DATE(C236,E236,1) -> 42675 | C236: 2016 | D236: November | E236: =VLOOKUP(D236,'Problem Statement 4'!$G$2:$H$13,2,0) -> 11 | F236: 132.8 | G236: Education | H236: =IF(B236<DATE(2020,3,1),"PreCovid","Post Covid") -> PreCovid | I236: 0
A237: Rural+Urban | B237: =DATE(C237,E237,1) -> 42705 | C237: 2016 | D237: December | E237: =VLOOKUP(D237,'Problem Statement 4'!$G$2:$H$13,2,0) -> 12 | F237: 133.1 | G237: Education | H237: =IF(B237<DATE(2020,3,1),"PreCovid","Post Covid") -> PreCovid | I237: =(F237-F236)/F236*100 -> 0.22590361
A238: Rural+Urban | B238: =DATE(C238,E238,1) -> 42736 | C238: 2017 | D238: January | E238: =VLOOKUP(D238,'Problem Statement 4'!$G$2:$H$13,2,0) -> 1 | F238: 133.3 | G238: Education | H238: =IF(B238<DATE(2020,3,1),"PreCovid","Post Covid") -> PreCovid | I238: =(F238-F237)/F237*100 -> 0.15026296
A239: Rural+Urban | B239: =DATE(C239,E239,1) -> 42767 | C239: 2017 | D239: February | E239: =VLOOKUP(D239,'Problem Statement 4'!$G$2:$H$13,2,0) -> 2 | F239: 133.4 | G239: Education | H239: =IF(B239<DATE(2020,3,1),"PreCovid","Post Covid") -> PreCovid | I239: =(F239-F238)/F238*100 -> 0.075018755
A240: Rural+Urban | B240: =DATE(C240,E240,1) -> 42795 | C240: 2017 | D240: March | E240: =VLOOKUP(D240,'Problem Statement 4'!$G$2:$H$13,2,0) -> 3 | F240: 133.8 | G240: Education | H240: =IF(B240<DATE(2020,3,1),"PreCovid","Post Covid") -> PreCovid | I240: =(F240-F239)/F239*100 -> 0.29985007
A241: Rural+Urban | B241: =DATE(C241,E241,1) -> 42826 | C241: 2017 | D241: April | E241: =VLOOKUP(D241,'Problem Statement 4'!$G$2:$H$13,2,0) -> 4 | F241: 134.5 | G241: Education | H241: =IF(B241<DATE(2020,3,1),"PreCovid","Post Covid") -> PreCovid | I241: =(F241-F240)/F240*100 -> 0.52316891
A242: Rural+Urban | B242: =DATE(C242,E242,1) -> 42856 | C242: 2017 | D242: May | E242: =VLOOKUP(D242,'Problem Statement 4'!$G$2:$H$13,2,0) -> 5 | F242: 134.8 | G242: Education | H242: =IF(B242<DATE(2020,3,1),"PreCovid","Post Covid") -> PreCovid | I242: =(F242-F241)/F241*100 -> 0.22304833
A243: Rural+Urban | B243: =DATE(C243,E243,1) -> 42887 | C243: 2017 | D243: June | E243: =VLOOKUP(D243,'Problem Statement 4'!$G$2:$H$13,2,0) -> 6 | F243: 135.4 | G243: Education | H243: =IF(B243<DATE(2020,3,1),"PreCovid","Post Covid") -> PreCovid | I243: =(F243-F242)/F242*100 -> 0.44510386
A244: Rural+Urban | B244: =DATE(C244,E244,1) -> 42917 | C244: 2017 | D244: July | E244: =VLOOKUP(D244,'Problem Statement 4'!$G$2:$H$13,2,0) -> 7 | F244: 136.8 | G244: Education | H244: =IF(B244<DATE(2020,3,1),"PreCovid","Post Covid") -> PreCovid | I244: =(F244-F243)/F243*100 -> 1.0339734
A245: Rural+Urban | B245: =DATE(C245,E245,1) -> 42948 | C245: 2017 | D245: August | E245: =VLOOKUP(D245,'Problem Statement 4'!$G$2:$H$13,2,0) -> 8 | F245: 137.6 | G245: Education | H245: =IF(B245<DATE(2020,3,1),"PreCovid","Post Covid") -> PreCovid | I245: =(F245-F244)/F244*100 -> 0.58479532
A246: Rural+Urban | B246: =DATE(C246,E246,1) -> 42979 | C246: 2017 | D246: September | E246: =VLOOKUP(D246,'Problem Statement 4'!$G$2:$H$13,2,0) -> 9 | F246: 137.4 | G246: Education | H246: =IF(B246<DATE(2020,3,1),"PreCovid","Post Covid") -> PreCovid | I246: =(F246-F245)/F245*100 -> -0.14534884
A247: Rural+Urban | B247: =DATE(C247,E247,1) -> 43009 | C247: 2017 | D247: October | E247: =VLOOKUP(D247,'Problem Statement 4'!$G$2:$H$13,2,0) -> 10 | F247: 137.9 | G247: Education | H247: =IF(B247<DATE(2020,3,1),"PreCovid","Post Covid") -> PreCovid | I247: =(F247-F246)/F246*100 -> 0.36390102
A248: Rural+Urban | B248: =DATE(C248,E248,1) -> 43040 | C248: 2017 | D248: November | E248: =VLOOKUP(D248,'Problem Statement 4'!$G$2:$H$13,2,0) -> 11 | F248: 138.6 | G248: Education | H248: =IF(B248<DATE(2020,3,1),"PreCovid","Post Covid") -> PreCovid | I248: =(F248-F247)/F247*100 -> 0.50761421
... A313: Rural+Urban | B313: =DATE(C313,E313,1) -> 45047 | C313: 2023 | D313: May | E313: =VLOOKUP(D313,'Problem Statement 4'!$G$2:$H$13,2,0) -> 5 | F313: 177.1 | G313: Education | H313: =IF(B313<DATE(2020,3,1),"PreCovid","Post Covid") -> Post Covid | I313: =(F313-F312)/F312*100 -> 0.3968254
A314: Rural+Urban | B314: =DATE(C314,E314,1) -> 42675 | C314: 2016 | D314: November | E314: =VLOOKUP(D314,'Problem Statement 4'!$G$2:$H$13,2,0) -> 11 | F314: 1296.6 | G314: Others | H314: =IF(B314<DATE(2020,3,1),"PreCovid","Post Covid") -> PreCovid | I314: 0
A315: Rural+Urban | B315: =DATE(C315,E315,1) -> 42705 | C315: 2016 | D315: December | E315: =VLOOKUP(D315,'Problem Statement 4'!$G$2:$H$13,2,0) -> 12 | F315: 1298.4 | G315: Others | H315: =IF(B315<DATE(2020,3,1),"PreCovid","Post Covid") -> PreCovid | I315: =(F315-F314)/F314*100 -> 0.13882462
A316: Rural+Urban | B316: =DATE(C316,E316,1) -> 42736 | C316: 2017 | D316: January | E316: =VLOOKUP(D316,'Problem Statement 4'!$G$2:$H$13,2,0) -> 1 | F316: 1302.6 | G316: Others | H316: =IF(B316<DATE(2020,3,1),"PreCovid","Post Covid") -> PreCovid | I316: =(F316-F315)/F315*100 -> 0.32347505
A317: Rural+Urban | B317: =DATE(C317,E317,1) -> 42767 | C317: 2017 | D317: February | E317: =VLOOKUP(D317,'Problem Statement 4'!$G$2:$H$13,2,0) -> 2 | F317: 1307 | G317: Others | H317: =IF(B317<DATE(2020,3,1),"PreCovid","Post Covid") -> PreCovid | I317: =(F317-F316)/F316*100 -> 0.33778597
A318: Rural+Urban | B318: =DATE(C318,E318,1) -> 42795 | C318: 2017 | D318: March | E318: =VLOOKUP(D318,'Problem Statement 4'!$G$2:$H$13,2,0) -> 3 | F318: 1311.1 | G318: Others | H318: =IF(B318<DATE(2020,3,1),"PreCovid","Post Covid") -> PreCovid | I318: =(F318-F317)/F317*100 -> 0.31369549
A319: Rural+Urban | B319: =DATE(C319,E319,1) -> 42826 | C319: 2017 | D319: April | E319: =VLOOKUP(D319,'Problem Statement 4'!$G$2:$H$13,2,0) -> 4 | F319: 1315 | G319: Others | H319: =IF(B319<DATE(2020,3,1),"PreCovid","Post Covid") -> PreCovid | I319: =(F319-F318)/F318*100 -> 0.29746015
A320: Rural+Urban | B320: =DATE(C320,E320,1) -> 42856 | C320: 2017 | D320: May | E320: =VLOOKUP(D320,'Problem Statement 4'!$G$2:$H$13,2,0) -> 5 | F320: 1318.4 | G320: Others | H320: =IF(B320<DATE(2020,3,1),"PreCovid","Post Covid") -> PreCovid | I320: =(F320-F319)/F319*100 -> 0.25855513
A321: Rural+Urban | B321: =DATE(C321,E321,1) -> 42887 | C321: 2017 | D321: June | E321: =VLOOKUP(D321,'Problem Statement 4'!$G$2:$H$13,2,0) -> 6 | F321: 1320.1 | G321: Others | H321: =IF(B321<DATE(2020,3,1),"PreCovid","Post Covid") -> PreCovid | I321: =(F321-F320)/F320*100 -> 0.12894417
A322: Rural+Urban | B322: =DATE(C322,E322,1) -> 42917 | C322: 2017 | D322: July | E322: =VLOOKUP(D322,'Problem Statement 4'!$G$2:$H$13,2,0) -> 7 | F322: 1327.9 | G322: Others | H322: =IF(B322<DATE(2020,3,1),"PreCovid","Post Covid") -> PreCovid | I322: =(F322-F321)/F321*100 -> 0.59086433
A323: Rural+Urban | B323: =DATE(C323,E323,1) -> 42948 | C323: 2017 | D323: August | E323: =VLOOKUP(D323,'Problem Statement 4'!$G$2:$H$13,2,0) -> 8 | F323: 1338.4 | G323: Others | H323: =IF(B323<DATE(2020,3,1),"PreCovid","Post Covid") -> PreCovid | I323: =(F323-F322)/F322*100 -> 0.79072219
A324: Rural+Urban | B324: =DATE(C324,E324,1) -> 42979 | C324: 2017 | D324: September | E324: =VLOOKUP(D324,'Problem Statement 4'!$G$2:$H$13,2,0) -> 9 | F324: 1346 | G324: Others | H324: =IF(B324<DATE(2020,3,1),"PreCovid","Post Covid") -> PreCovid | I324: =(F324-F323)/F323*100 -> 0.5678422
A325: Rural+Urban | B325: =DATE(C325,E325,1) -> 43009 | C325: 2017 | D325: October | E325: =VLOOKUP(D325,'Problem Statement 4'!$G$2:$H$13,2,0) -> 10 | F325: 1353 | G325: Others | H325: =IF(B325<DATE(2020,3,1),"PreCovid","Post Covid") -> PreCovid | I325: =(F325-F324)/F324*100 -> 0.52005944
A326: Rural+Urban | B326: =DATE(C326,E326,1) -> 43040 | C326: 2017 | D326: November | E326: =VLOOKUP(D326,'Problem Statement 4'!$G$2:$H$13,2,0) -> 11 | F326: 1362.5 | G326: Others | H326: =IF(B326<DATE(2020,3,1),"PreCovid","Post Covid") -> PreCovid | I326: =(F326-F325)/F325*100 -> 0.70214339
... A391: Rural+Urban | B391: =DATE(C391,E391,1) -> 45047 | C391: 2023 | D391: May | E391: =VLOOKUP(D391,'Problem Statement 4'!$G$2:$H$13,2,0) -> 5 | F391: 1822.8 | G391: Others | H391: =IF(B391<DATE(2020,3,1),"PreCovid","Post Covid") -> Post Covid | I391: =(F391-F390)/F390*100 -> 0.32472893

Sheet Problem Satatement 5
J1: MOM INFLATION %
A2: Year | B2: Month | C2: Indian Basket of Crude Oil (USD/Barrel) | D2: General index | E2: Food | F2: Energy | G2: Transportation | H2: Education | I2: Others | J2: Indian Basket of Crude Oil (USD/Barrel) | K2: General index | L2: Food | M2: Energy | N2: Transportation | O2: Education | P2: Others
A3: =_xlfn.NUMBERVALUE(TEXT(B3,"yyyy")) -> 2021 | B3: Jan-21 | C3: 54.79 | D3: 157.3 | E3: 2076.5 | F3: 147.9 | G3: 141.9 | H3: 159.2 | I3: 1567.6 | J3: 0 | K3: 0 | L3: 0 | M3: 0 | N3: 0 | O3: 0 | P3: 0
A4: =_xlfn.NUMBERVALUE(TEXT(B4,"yyyy")) -> 2021 | B4: Feb-21 | C4: 61.22 | D4: 156.6 | E4: 2039.3 | F4: 152.4 | G4: 145.1 | H4: 159.5 | I4: 1581.4 | J4: =(C4-C3)/C3*100 -> 11.735718 | K4: =(D4-D3)/D3*100 -> -0.44500954 | L4: =(E4-E3)/E3*100 -> -1.791476 | M4: =(F4-F3)/F3*100 -> 3.0425963 | N4: =(G4-G3)/G3*100 -> 2.2551092 | O4: =(H4-H3)/H3*100 -> 0.18844221 | P4: =(I4-I3)/I3*100 -> 0.88032661
A5: =_xlfn.NUMBERVALUE(TEXT(B5,"yyyy")) -> 2021 | B5: Mar-21 | C5: 64.73 | D5: 156.8 | E5: 2039.4 | F5: 155.5 | G5: 146.2 | H5: 160.2 | I5: 1583.2 | J5: =(C5-C4)/C4*100 -> 5.7334205 | K5: =(D5-D4)/D4*100 -> 0.12771392 | L5: =(E5-E4)/E4*100 -> 0.0049036434 | M5: =(F5-F4)/F4*100 -> 2.0341207 | N5: =(G5-G4)/G4*100 -> 0.75809786 | O5: =(H5-H4)/H4*100 -> 0.43887147 | P5: =(I5-I4)/I4*100 -> 0.11382319
A6: =_xlfn.NUMBERVALUE(TEXT(B6,"yyyy")) -> 2021 | B6: Apr-21 | C6: 63.4 | D6: 157.8 | E6: 2064.1 | F6: 155.6 | G6: 146.6 | H6: 160.3 | I6: 1591.9 | J6: =(C6-C5)/C5*100 -> -2.0546887 | K6: =(D6-D5)/D5*100 -> 0.6377551 | L6: =(E6-E5)/E5*100 -> 1.2111405 | M6: =(F6-F5)/F5*100 -> 0.064308682 | N6: =(G6-G5)/G5*100 -> 0.27359781 | O6: =(H6-H5)/H5*100 -> 0.062421973 | P6: =(I6-I5)/I5*100 -> 0.54951996
A7: =_xlfn.NUMBERVALUE(TEXT(B7,"yyyy")) -> 2021 | B7: May-21 | C7: 66.95 | D7: 160.4 | E7: 2105.7 | F7: 159.4 | G7: 148.9 | H7: 161.2 | I7: 1619.5 | J7: =(C7-C6)/C6*100 -> 5.5993691 | K7: =(D7-D6)/D6*100 -> 1.6476553 | L7: =(E7-E6)/E6*100 -> 2.0154062 | M7: =(F7-F6)/F6*100 -> 2.4421594 | N7: =(G7-G6)/G6*100 -> 1.568895 | O7: =(H7-H6)/H6*100 -> 0.56144729 | P7: =(I7-I6)/I6*100 -> 1.7337772
A8: =_xlfn.NUMBERVALUE(TEXT(B8,"yyyy")) -> 2021 | B8: Jun-21 | C8: 71.98 | D8: 161.3 | E8: 2133.9 | F8: 159.8 | G8: 150.7 | H8: 161.7 | I8: 1618.4 | J8: =(C8-C7)/C7*100 -> 7.5130695 | K8: =(D8-D7)/D7*100 -> 0.56109726 | L8: =(E8-E7)/E7*100 -> 1.3392221 | M8: =(F8-F7)/F7*100 -> 0.25094103 | N8: =(G8-G7)/G7*100 -> 1.208865 | O8: =(H8-H7)/H7*100 -> 0.3101737 | P8: =(I8-I7)/I7*100 -> -0.067922198
A9: =_xlfn.NUMBERVALUE(TEXT(B9,"yyyy")) -> 2021 | B9: Jul-21 | C9: 73.54 | D9: 162.5 | E9: 2147 | F9: 160.7 | G9: 153.1 | H9: 163.2 | I9: 1627.2 | J9: =(C9-C8)/C8*100 -> 2.1672687 | K9: =(D9-D8)/D8*100 -> 0.74395536 | L9: =(E9-E8)/E8*100 -> 0.61389943 | M9: =(F9-F8)/F8*100 -> 0.56320401 | N9: =(G9-G8)/G8*100 -> 1.592568 | O9: =(H9-H8)/H8*100 -> 0.92764378 | P9: =(I9-I8)/I8*100 -> 0.54374691 | AH9: ppac.gov.in
A10: =_xlfn.NUMBERVALUE(TEXT(B10,"yyyy")) -> 2021 | B10: Aug-21 | C10: 69.8 | D10: 163.2 | E10: 2142 | F10: 162.6 | G10: 154 | H10: 163.8 | I10: 1640.7 | J10: =(C10-C9)/C9*100 -> -5.0856677 | K10: =(D10-D9)/D9*100 -> 0.43076923 | L10: =(E10-E9)/E9*100 -> -0.23288309 | M10: =(F10-F9)/F9*100 -> 1.1823273 | N10: =(G10-G9)/G9*100 -> 0.58785108 | O10: =(H10-H9)/H9*100 -> 0.36764706 | P10: =(I10-I9)/I9*100 -> 0.82964602
A11: =_xlfn.NUMBERVALUE(TEXT(B11,"yyyy")) -> 2021 | B11: Sep-21 | C11: 73.13 | D11: 163.2 | E11: 2142 | F11: 162.6 | G11: 154 | H11: 163.7 | I11: 1641 | J11: =(C11-C10)/C10*100 -> 4.7707736 | K11: =(D11-D10)/D10*100 -> 0 | L11: =(E11-E10)/E10*100 -> 0 | M11: =(F11-F10)/F10*100 -> 0 | N11: =(G11-G10)/G10*100 -> 0 | O11: =(H11-H10)/H10*100 -> -0.061050061 | P11: =(I11-I10)/I10*100 -> 0.018284878
A12: =_xlfn.NUMBERVALUE(TEXT(B12,"yyyy")) -> 2021 | B12: Oct-21 | C12: 82.11 | D12: 165.5 | E12: 2175.5 | F12: 164.2 | G12: 155.7 | H12: 163.9 | I12: 1650.5 | J12: =(C12-C11)/C11*100 -> 12.279502 | K12: =(D12-D11)/D11*100 -> 1.4093137 | L12: =(E12-E11)/E11*100 -> 1.5639589 | M12: =(F12-F11)/F11*100 -> 0.98400984 | N12: =(G12-G11)/G11*100 -> 1.1038961 | O12: =(H12-H11)/H11*100 -> 0.12217471 | P12: =(I12-I11)/I11*100 -> 0.5789153
A13: =_xlfn.NUMBERVALUE(TEXT(B13,"yyyy")) -> 2021 | B13: Nov-21 | C13: 80.64 | D13: 166.7 | E13: 2194.1 | F13: 163.9 | G13: 154.8 | H13: 164.3 | I13: 1660.1 | J13: =(C13-C12)/C12*100 -> -1.7902813 | K13: =(D13-D12)/D12*100 -> 0.72507553 | L13: =(E13-E12)/E12*100 -> 0.85497587 | M13: =(F13-F12)/F12*100 -> -0.18270402 | N13: =(G13-G12)/G12*100 -> -0.57803468 | O13: =(H13-H12)/H12*100 -> 0.24405125 | P13: =(I13-I12)/I12*100 -> 0.58164193
A14: =_xlfn.NUMBERVALUE(TEXT(B14,"yyyy")) -> 2021 | B14: Dec-21 | C14: 73.3 | D14: 166.2 | E14: 2180.9 | F14: 164.1 | G14: 155.7 | H14: 164.4 | I14: 1666 | J14: =(C14-C13)/C13*100 -> -9.1021825 | K14: =(D14-D13)/D13*100 -> -0.29994001 | L14: =(E14-E13)/E13*100 -> -0.60161342 | M14: =(F14-F13)/F13*100 -> 0.12202563 | N14: =(G14-G13)/G13*100 -> 0.58139535 | O14: =(H14-H13)/H13*100 -> 0.060864273 | P14: =(I14-I13)/I13*100 -> 0.35540028
A15: =_xlfn.NUMBERVALUE(TEXT(B15,"yyyy")) -> 2022 | B15: Jan-22 | C15: 84.67 | D15: 165.7 | E15: 2164.2 | F15: 164.2 | G15: 156.5 | H15: 164.7 | I15: 1675.2 | J15: =(C15-C14)/C14*100 -> 15.511596 | K15: =(D15-D14)/D14*100 -> -0.30084236 | L15: =(E15-E14)/E14*100 -> -0.76573892 | M15: =(F15-F14)/F14*100 -> 0.060938452 | N15: =(G15-G14)/G14*100 -> 0.51380861 | O15: =(H15-H14)/H14*100 -> 0.18248175 | P15: =(I15-I14)/I14*100 -> 0.55222089
A16: =_xlfn.NUMBERVALUE(TEXT(B16,"yyyy")) -> 2022 | B16: Feb-22 | C16: 94.07 | D16: 166.1 | E16: 2161.2 | F16: 165.7 | G16: 156.9 | H16: 165.4 | I16: 1685.1 | J16: =(C16-C15)/C15*100 -> 11.101925 | K16: =(D16-D15)/D15*100 -> 0.24140012 | L16: =(E16-E15)/E15*100 -> -0.13861935 | M16: =(F16-F15)/F15*100 -> 0.9135201 | N16: =(G16-G15)/G15*100 -> 0.25559105 | O16: =(H16-H15)/H15*100 -> 0.42501518 | P16: =(I16-I15)/I15*100 -> 0.59097421
A17: =_xlfn.NUMBERVALUE(TEXT(B17,"yyyy")) -> 2022 | B17: Mar-22 | C17: 112.87 | D17: 167.7 | E17: 2184.2 | F17: 167.2 | G17: 157.9 | H17: 166 | I17: 1697.7 | J17: =(C17-C16)/C16*100 -> 19.985117 | K17: =(D17-D16)/D16*100 -> 0.96327514 | L17: =(E17-E16)/E16*100 -> 1.0642236 | M17: =(F17-F16)/F16*100 -> 0.90525045 | N17: =(G17-G16)/G16*100 -> 0.63734863 | O17: =(H17-H16)/H16*100 -> 0.36275695 | P17: =(I17-I16)/I16*100 -> 0.74773011
A18: =_xlfn.NUMBERVALUE(TEXT(B18,"yyyy")) -> 2022 | B18: Apr-22 | C18: 102.97 | D18: 170.1 | E18: 2214.3 | F18: 172.2 | G18: 162.6 | H18: 166.9 | I18: 1712.1 | J18: =(C18-C17)/C17*100 -> -8.7711527 | K18: =(D18-D17)/D17*100 -> 1.431127 | L18: =(E18-E17)/E17*100 -> 1.3780789 | M18: =(F18-F17)/F17*100 -> 2.9904306 | N18: =(G18-G17)/G17*100 -> 2.9765674 | O18: =(H18-H17)/H17*100 -> 0.54216867 | P18: =(I18-I17)/I17*100 -> 0.8482064
A19: =_xlfn.NUMBERVALUE(TEXT(B19,"yyyy")) -> 2022 | B19: May-22 | C19: 109.51 | D19: 171.7 | E19: 2238.9 | F19: 174.6 | G19: 163 | H19: 167.9 | I19: 1721.2 | J19: =(C19-C18)/C18*100 -> 6.3513645 | K19: =(D19-D18)/D18*100 -> 0.94062316 | L19: =(E19-E18)/E18*100 -> 1.1109606 | M19: =(F19-F18)/F18*100 -> 1.3937282 | N19: =(G19-G18)/G18*100 -> 0.24600246 | O19: =(H19-H18)/H18*100 -> 0.59916117 | P19: =(I19-I18)/I18*100 -> 0.53151101
A20: =_xlfn.NUMBERVALUE(TEXT(B20,"yyyy")) -> 2022 | B20: Jun-22 | C20: 116.01 | D20: 172.6 | E20: 2261.9 | F20: 176 | G20: 161.1 | H20: 169 | I20: 1728.6 | J20: =(C20-C19)/C19*100 -> 5.935531 | K20: =(D20-D19)/D19*100 -> 0.52417006 | L20: =(E20-E19)/E19*100 -> 1.0272902 | M20: =(F20-F19)/F19*100 -> 0.80183276 | N20: =(G20-G19)/G19*100 -> -1.1656442 | O20: =(H20-H19)/H19*100 -> 0.65515188 | P20: =(I20-I19)/I19*100 -> 0.42993261
A21: =_xlfn.NUMBERVALUE(TEXT(B21,"yyyy")) -> 2022 | B21: Jul-22 | C21: 105.49 | D21: 173.4 | E21: 2266.3 | F21: 179.6 | G21: 161.6 | H21: 171.4 | I21: 1737.2 | J21: =(C21-C20)/C20*100 -> -9.0681838 | K21: =(D21-D20)/D20*100 -> 0.46349942 | L21: =(E21-E20)/E20*100 -> 0.19452673 | M21: =(F21-F20)/F20*100 -> 2.0454545 | N21: =(G21-G20)/G20*100 -> 0.31036623 | O21: =(H21-H20)/H20*100 -> 1.4201183 | P21: =(I21-I20)/I20*100 -> 0.49751244
... A28: =_xlfn.NUMBERVALUE(TEXT(B28,"yyyy")) -> 2023 | B28: Feb-23 | C28: 82.28 | D28: 177.2 | E28: 2279.1 | F28: 182.1 | G28: 164.2 | H28: 175 | I28: 1807 | J28: =(C28-C27)/C27*100 -> 1.6806723 | K28: =(D28-D27)/D27*100 -> 0.39660057 | L28: =(E28-E27)/E27*100 -> -0.59318707 | M28: =(F28-F27)/F27*100 -> 0.054945055 | N28: =(G28-G27)/G27*100 -> 0.36674817 | O28: =(H28-H27)/H27*100 -> 0.40160643 | P28: =(I28-I27)/I27*100 -> 0.79767948
I31: YOY INFLATION %
A32: Year | B32: Indian Basket of Crude Oil (USD/Barrel) | C32: General index | D32: Food | E32: Energy | F32: Transportation | G32: Education | H32: Others | I32: Indian Basket of Crude Oil (USD/Barrel) | J32: General index | K32: Food | L32: Energy | M32: Transportation | N32: Education | O32: Others
A33: 2021 | B33: =SUMIFS(C$3:C$28,$A$3:$A$28,$A33) -> 835.59 | C33: =SUMIFS(D$3:D$28,$A$3:$A$28,$A33) -> 1937.5 | D33: =SUMIFS(E$3:E$28,$A$3:$A$28,$A33) -> 25440.4 | E33: =SUMIFS(F$3:F$28,$A$3:$A$28,$A33) -> 1908.7 | F33: =SUMIFS(G$3:G$28,$A$3:$A$28,$A33) -> 1806.7 | G33: =SUMIFS(H$3:H$28,$A$3:$A$28,$A33) -> 1945.4 | H33: =SUMIFS(I$3:I$28,$A$3:$A$28,$A33) -> 19447.5 | I33: 0 | J33: 0 | K33: 0 | L33: 0 | M33: 0 | N33: 0 | O33: 0
A34: 2022 | B34: =SUMIFS(C$3:C$28,$A$3:$A$28,$A34) -> 1171.05 | C34: =SUMIFS(D$3:D$28,$A$3:$A$28,$A34) -> 2065.8 | D34: =SUMIFS(E$3:E$28,$A$3:$A$28,$A34) -> 26918.6 | E34: =SUMIFS(F$3:F$28,$A$3:$A$28,$A34) -> 2101.6 | F34: =SUMIFS(G$3:G$28,$A$3:$A$28,$A34) -> 1933.1 | G34: =SUMIFS(H$3:H$28,$A$3:$A$28,$A34) -> 2037.9 | H34: =SUMIFS(I$3:I$28,$A$3:$A$28,$A34) -> 20782.3 | I34: =(B34-B33)/B33*100 -> 40.146483 | J34: =(C34-C33)/C33*100 -> 6.6219355 | K34: =(D34-D33)/D33*100 -> 5.8104432 | L34: =(E34-E33)/E33*100 -> 10.106355 | M34: =(F34-F33)/F33*100 -> 6.9961809 | N34: =(G34-G33)/G33*100 -> 4.7548062 | O34: =(H34-H33)/H33*100 -> 6.8636071
A35: 2023 | B35: =SUMIFS(C$3:C$28,$A$3:$A$28,$A35) -> 163.2 | C35: =SUMIFS(D$3:D$28,$A$3:$A$28,$A35) -> 353.7 | D35: =SUMIFS(E$3:E$28,$A$3:$A$28,$A35) -> 4571.8 | E35: =SUMIFS(F$3:F$28,$A$3:$A$28,$A35) -> 364.1 | F35: =SUMIFS(G$3:G$28,$A$3:$A$28,$A35) -> 327.8 | G35: =SUMIFS(H$3:H$28,$A$3:$A$28,$A35) -> 349.3 | H35: =SUMIFS(I$3:I$28,$A$3:$A$28,$A35) -> 3599.7 | I35: =(B35-B34)/B34*100 -> -86.063789 | J35: =(C35-C34)/C34*100 -> -82.878304 | K35: =(D35-D34)/D34*100 -> -83.016204 | L35: =(E35-E34)/E34*100 -> -82.675105 | M35: =(F35-F34)/F34*100 -> -83.042781 | N35: =(G35-G34)/G34*100 -> -82.859807 | O35: =(H35-H34)/H34*100 -> -82.679011
C41: MOM Correl
C42: Category | D42: General index | E42: Food | F42: Energy | G42: Transportation | H42: Education | I42: Others
C43: Oil | D43: =CORREL($J$3:$J$28,K3:K28) -> 0.11523812 | E43: =CORREL($J$3:$J$28,L3:L28) -> 0.088910314 | F43: =CORREL($J$3:$J$28,M3:M28) -> 0.1129093 | G43: =CORREL($J$3:$J$28,N3:N28) -> 0.083959005 | H43: =CORREL($J$3:$J$28,O3:O28) -> -0.18279011 | I43: =CORREL($J$3:$J$28,P3:P28) -> 0.074647892
C45: YOY CORREL
C46: Category | D46: General index | E46: Food | F46: Energy | G46: Transportation | H46: Education | I46: Others
C47: Oil | D47: =CORREL($I$33:$I$35,J33:J35) -> 0.9688826 | E47: =CORREL($I$33:$I$35,K33:K35) -> 0.96688658 | F47: =CORREL($I$33:$I$35,L33:L35) -> 0.97652152 | G47: =CORREL($I$33:$I$35,M33:M35) -> 0.9697329 | H47: =CORREL($I$33:$I$35,N33:N35) -> 0.96422632 | I47: =CORREL($I$33:$I$35,O33:O35) -> 0.96949341

Sheet Sheet7
A1: To effectively use storytelling for your CPI Inflation case study in a data analytics interview, follow these steps:
A3: Start with the Problem: Briefly explain what CPI (Consumer Price Index) inflation is and why it matters.
A5: Example*: “CPI inflation measures the average change in prices paid by consumers. High inflation affects purchasing power and economic stability.”
A6: Describe Your Approach: Outline how you analyzed the data.
A8: Example*: “I collected monthly CPI data for the last five years, cleaned it in Excel, and visualized trends using line charts.”
A9: Highlight Key Insights: Share the main findings from your analysis.
A11: Example*: “I observed a sharp rise in inflation during 2022, mainly due to increased food and fuel prices.”
A12: Explain the Impact: Discuss what these findings mean.
A14: Example*: “This spike in inflation led to higher living costs, impacting household budgets and savings.”
A15: Recommend Actions: Suggest possible solutions or next steps.
A17: Example*: “To manage inflation, policymakers could focus on stabilizing food supply chains and monitoring fuel prices.”
A18: Use Visuals: Refer to charts or graphs you created in Excel to support your story.
... A21: This approach shows your analytical thinking and communication skills, both crucial for data analytics roles.

Sheet Sheet5
A1: Sector | B1: Rural+Urban
A3: Row Labels | B3: Average of Food
A4: 2013 | B4: 1446.3917
A5: 2014 | B5: 1542.0833
A6: 2015 | B6: 1624.425
A7: 2016 | B7: 1735.8083
A8: 2017 | B8: 1753.9417
A9: 2018 | B9: 1772.9583
A10: 2019 | B10: 1833.0636
A11: 2020 | B11: 1986.2583
A12: 2021 | B12: 2120.0333
A13: 2022 | B13: 2243.2167
A14: 2023 | B14: 2289.5
A15: Grand Total | B15: 1825.1016
